Workbook
Name _10_Note_1: '10C'!$D$76
Name _10_Note_1: '10M'!$D$79
Name _10_Note_1: '20C'!$D$77
Name _10_Note_1: ACCT!#REF!
Name _10_Note_2: '10C'!$D$77
Name _10_Note_2: '10M'!$D$80
Name _10_Note_2: '20C'!$D$78
Name _10_Note_2: ACCT!$H$100
Name _10_Note_3: '10C'!$D$78
Name _10_Note_3: '10M'!$D$81
Name _10_Note_3: '20C'!$D$79
Name _10_Note_3: ACCT!$H$101
Name _10_Note_4: '10C'!$D$79
Name _10_Note_4: '10M'!$D$82
Name _10_Note_4: '20C'!$D$80
Name _10_Note_4: ACCT!$H$102
Name _10_Note_5: '10C'!$D$80
Name _10_Note_5: '10M'!$D$83
Name _10_Note_5: '20C'!$D$81
Name _10_Note_5: ACCT!$H$103
Name _20_Note_1: '20B'!$D$131
Name _20_Note_1: '20IC'!$D$134
Name _20_Note_1: '20R'!$D$138
Name _20_Note_1: EMAIL!$F$135
Name _20_Note_1: PHN!$F$134
Name _20_Note_1: POE!$F$135
Name _20_Note_1: PRTY!$G$159
Name _20_Note_1: PRTY!$F$95
Name _20_Note_2: '20B'!$D$132
Name _20_Note_2: '20IC'!$D$135
Name _20_Note_2: '20R'!$D$139
Name _20_Note_2: EMAIL!$F$136
Name _20_Note_2: PHN!$F$135
Name _20_Note_2: POE!$F$136
Name _20_Note_2: PRTY!$G$161
Name _20_Note_2: PRTY!$F$96
Name _20_Note_3: '20B'!$D$133
Name _20_Note_3: '20IC'!$D$136
Name _20_Note_3: '20R'!$D$140
Name _20_Note_3: EMAIL!$F$137
Name _20_Note_3: PHN!$F$136
Name _20_Note_3: POE!$F$137
Name _20_Note_3: PRTY!$G$162
Name _20_Note_3: PRTY!$F$97
Name _20R_Note_1: '20R'!#REF!
Name _30_Note_1: ANOT!$G$15
Name _30_Note_2: ANOT!$G$32
Name _40_Note_1: TRNH!$F$140
Name _40_Note_2: TRNH!$F$141
Name _40_Note_3: TRNH!$F$142
Name _40_Note_4: TRNH!$F$143
Name _40_Note_5: TRNH!$F$144
Name _40_SourceTransactionId: TRNH!$H$7
Name _50_Note_1: '50'!$E$130
Name _50_Note_2: '50'!$E$131
Name _50_Note_3: '50'!$E$132
Name _50_Note_4: '50'!$E$133
Name _60_Note_1: #REF!
Name _60_Note_1: #REF!
Name _60_Note_1: #REF!

Sheet File Specifications
A1: Character Set | B1: ASCII
A2: File Type | B2: Comma Separated Values (CSV) | C2: Note 1
A3: Delimiter | B3: Comma (,)
A4: Field Qualifier | B4: Double Quote (") | C4: Must be used when the field contains the delimiter.
A5: Line Terminator | B5: Carriage Return, Line Feed (CRLF)
A6: Record Id Position | B6: 1 | C6: See Record Ids tab for the list of Record Id values.
A8: Data Type | B8: Format
A9: AMT | B9: -#########.##
A10: CHR | B10: Exclude all control characters
A11: DATE | B11: MM/DD/YYYY
A12: NUMBER | B12: ###########
A13: PHONE | B13: Exactly 10 digits (area code is required)
A14: SSN | B14: Exactly 9 digits
A15: TIME | B15: HH:MM[:SS] (24 hour time) HH:MM[:SS] AM/PM (12 hour time)
A16: ZIP | B16: US or Canadian
A19: Note 1 | B19: Data containing a line break, double-quote, or a comma must be quoted. (If they are not, the file will likely be impossible to process correctly). A double-quote character in a data must be represented by two double-quote characters. See http://en.wikipedia.org/wiki/Comma-separated_values for more information on CSV formatting.

Sheet Record Ids
A1: Record ID | B1: New Rec ID | C1: SaaS timeline | D1: Category | E1: Subcategory | F1: Required? | G1: Instruction | H1: Records Per | J1: Priority
A2: ACCT | B2: ACCT | C2: MVP | D2: Account | E2: Account information | F2: Yes | H2: One | J2: 1
A3: 10C | C3: NA | D3: Account | E3: Custom Account Information
A4: 10M | C4: Data need to be merged with record 10 for MVP | D4: Account | E4: Migrated Account Information | H4: Zero to one
A5: BAL | B5: BAL | C5: MVP | D5: Account | E5: Balance information | F5: Yes | H5: One | J5: 2
A6: 12 | C6: NA | D6: Account | E6: Delinquency information | H6: Zero to one | L6: =ACCT!$G$1 -> 33
A7: 14 | C7: GA | D7: Account | E7: Financial information | H7: Zero to one | L7: =ACCT!$G$1 -> 33
A8: 16 | C8: Later | D8: Account | E8: Alerts | H8: Zero to many per account | L8: =ACCT!$G$1 -> 33
A9: 17 | C9: GA | D9: Loan | E9: Loan Information | F9: No | H9: Zero to one | L9: =ACCT!$G$1 -> 33
A10: 19 | B10: DOC | C10: MVP2 | D10: Doc | E10: Document Information | F10: No | H10: Zero to many
A11: PRTY | B11: PRTY | C11: MVP | D11: Party | E11: Party information | F11: Yes | G11: Must have one and only one primary party (PRIM) | H11: One to many per account | J11: 3
A12: 20B | C12: GA | D12: Party | E12: Party Balances | F12: No | H12: Zero to One per Party | L12: =ACCT!$G$1 -> 33
A13: 20R | C13: GA | D13: Party | E13: Party References | F13: No | H13: Zero to many per Party | L13: =ACCT!$G$1 -> 33
A14: 20C | C14: NA | D14: Party | E14: Custom Party Information | F14: No | H14: Zero to many per Party | L14: =ACCT!$G$1 -> 33
A15: 20IC | C15: Later | D15: Party | E15: Insurance Coverage | H15: Zero to one | L15: =ACCT!$G$1 -> 33
A16: PHN | B16: PHN | C16: MVP | D16: Phone | E16: Phone Information | G16: Use only if UsePhoneTable option is enabled. | H16: Zero to many per Party | J16: 4
A17: POE | B17: POE | C17: MVP | D17: POE | E17: POE Information | G17: Use only if UsePOETable option is enabled. | H17: Zero to many per Party
A18: PADD | B18: PADD | C18: MVP | D18: Previous Address | E18: Previous Address Information | H18: Zero to many per Party
A19: LTRH | B19: LTRH | C19: MVP2 | D19: Letter History | E19: Letter History Information | H19: Zero to many per Party
A20: AKA | B20: AKA | C20: MVP | D20: Party | E20: Aliases | G20: This is not for name changes | H20: Zero to many per Party
A21: 27 | C21: MVP2 | D21: Party | E21: Nearby | H21: Zero to many per Party | I21: This Feature not available in SaaS
A22: 28 | C22: Later | D22: Account or Party | E22: Tasks | G22: These are tasks to be performed after the migration | H22: Zero to many per Account and Party | L22: =ACCT!$G$1 -> 33
A23: 29 | C23: MVP (RM) | D23: Account or Party | E23: Action History | H23: Zero to many per Account and Party | J23: 9 | L23: =ACCT!$G$1 -> 33
A24: ANOT | B24: ANOT | C24: MVP | D24: Account | E24: Notes | G24: Account and relationship notes | H24: Zero to many per Account | I24: Note 1 | J24: 6
A25: PNOT | B25: PNOT | C25: MVP2 | D25: Account | E25: Notes | G25: Account and party notes | H25: Zero to many per Account | J25: Note 2 8
A26: TRNH | B26: TRNH | C26: MVP | D26: Account | E26: Transaction history | G26: Include payments, reversals, and adjustments that have already been applied to the account | H26: Zero to many per Account | J26: 5
A27: 45 | C27: Combine with Transaction History | D27: Account | E27: Memo transactions | G27: Any transaction that must never effect the balance | H27: Zero to many per Account | I27: Future use | L27: =ACCT!$G$1 -> 33
A28: PDTR | B28: PDTR | C28: MVP | D28: Account | E28: Post-dated transactions | G28: Includes payments and adjustments that have not been applied to the account | H28: Zero to many per Account
A29: 50 | C29: GA | D29: Account | E29: Placement history | G29: Include placements, recalls, asset sales, and buy backs | H29: Zero to many per Account | L29: =ACCT!$G$1 -> 33
A30: 51 | C30: GA | D30: Account | E30: Vendor Status Code History | H30: Zero to many per Account | L30: =ACCT!$G$1 -> 33
A31: ACTH | B31: ACTH | C31: MVP | D31: Account | E31: Activity History | H31: Zero to many per Account | J31: 7
A32: PA | B32: PA | C32: MVP | D32: PA Hist | E32: Payment Arrangement | H32: Zero to many per Account
A33: PS | B33: PS | C33: MVP | D33: PA Hist | E33: Payment Schedule | H33: Zero to many per Account
A34: PSC | B34: PSC | C34: MVP2 | D34: PA Hist | E34: Payment Schedule for ECC | H34: Zero to many per Account
A35: PSK | B35: PSK | C35: MVP2 | D35: PA Hist | E35: Payment Schedule for ECK | H35: Zero to many per Account
A36: 61CW | C36: NA | D36: PA Hist | E36: Payment Schedule for CW | H36: Zero to many per Account
A37: 70 | C37: BeyondGA | D37: Account | E37: Collateral information | G37: Cars, houses, etc | H37: Zero to many per Account
A38: 71 | C38: BeyondGA | D38: Account or Collateral | E38: Insurance Information | G38: Insurance on person or collateral | H38: Zero to many per Account or Collateral
A39: 75 | C39: BeyondGA | E39: Detailed Bill Information
A40: 80 | C40: BeyondGA | D40: Account | E40: Debt Buyer purchase history | G40: Required if account was purchased | H40: Zero to many per Account
A41: ITMZ | B41: ITMZ | C41: MVP | D41: Account | E41: Itemization data | H41: One
A43: 99 | C43: NA | D43: Custom | E43: Custom Data 1 | G43: A custom script must be written for each | H43: Zero to many per Account
A44: 99 | C44: NA | D44: Custom | E44: Custom Data 2
D45: …
A46: 99 | C46: NA | D46: Custom | E46: Custom Data n
A49: Note 1 | D49: When there are many accounts to migrate notes can be migrated using a separate file. Ask Ontario Systems for the file layout.
A50: Note 2 | D50: Use the 31 notes record to reduce duplicate notes when the source of the note is linked directly to the party.
D53: How to set foreign keys
D54: Account_ID | E54: Account # in Legacy system
D55: Consumer_ID | E55: P/S/C for Primary, Spouse, or Comaker
D56: Transaction_ID
D60: Record Creation Status
D61: Record | E61: TCS Status | F61: RM Status | G61: FACS Status
D62: Account | E62: Done
D63: Balances | E63: Done
D64: Party | E64: Done
D65: POE | E65: Done
D66: Acct Notes | E66: Done
D67: Phone | E67: Done
D68: Previous Address | E68: Done May not have test data
D69: Aliasis | E69: Done May not have test data
D70: Transaction History | E70: Done
D71: Post Dated Trans | E71: Done May not have test data
D72: Action History | E72: Out of scope
D73: Party Notes | E73: N/A no party notes
D74: Letter History | E74: Out of scope

Sheet Change Log
A1: Version | B1: Date | C1: Change Note
B100: 41465 | C100: Removed length from all TIME fields. Time data can be sent in various external formats. See File Specifications tab.
B101: 41465 | C101: Changed the record 40 format. Inserted fields for Vendor Credit and CCC Expense information.
B102: 41466 | C102: Added record 15 (Metro 2 Reporting History)
B103: 41481 | C103: Replaced destination field in record 20 position 30, ARRELENPENDRSPBAL, with ARRELENINIRSPBAL. The old field in that position is calculated from the contents of the new field.
B104: 41491 | C104: Removed table FSDLQSTATUS from the Initial Setup list for accounts. It is still required for the client migration.
B105: 41505 | C105: Added 51 more custom fields to the 99 record for even longer custom records.
B106: 41555 | C106: Added record 16 (Account Alert)
B107: 41556 | C107: Removed record 30 (Account Notes). There will be a separate spreadsheet for migrating account notes.
B108: 41568 | C108: Added record 28 (Account/Party Task)
B109: 41568 | C109: Added record 29 (Action History)
B110: 41570 | C110: Added notes to Converted Account Number (record 10) and Source Party Id (record 20) concerning migrating accounts from multiple systems.
B111: 41571 | C111: Updated Note 1 on record 40
... B135: 43005 | C135: Added Bankruptcy, Deceased, Incarceration, and Litigacy information to end of Record 20
A136: V7 | B136: 43055 | C136: Added letter delete date to record 25
A137: V7 | B137: 43070 | C137: Changed record 20R. Inserted phone flag fields. Removed note about creating a POE record.

Sheet ACCT
A1: Source | G1: =COUNTIF(F5:F77,"MVP")-COUNTIF(G5:G77,"MVP") -> 33 | I1: Destination
A2: FACS | B2: TCS | C2: RM Table | E2: RM Column | F2: SaaS mapping/ timeline | G2: In Migration Import? | I2: Description | J2: Position | K2: Required? | L2: Instructions | M2: Data Type | N2: Length | O2: Oasis table | P2: Oasis Column | Q2: 10 | R2: Min | S2: Max | T2: Foreign Table | U2: Validation
F3: MVP | I3: Rec ID = ACCT | J3: 1 | K3: Yes | Y3: =";ACCT^"&J3&"^"&M3&"^"&N3 -> ;ACCT^1^^
A4: DBACCT | E4: ARACID | F4: MVP | I4: Account_ID | J4: 2 | K4: Yes | Y4: =";ACCT^"&J4&"^"&M4&"^"&N4 -> ;ACCT^2^^
A5: DBACCT | B5: ACCOUNT | C5: =IFERROR(VLOOKUP(E5,'Field Definitions'!$A$1:$S$31597,3),"") -> ARACCOUNT | E5: ARACID | F5: MVP | H5: Core | I5: Account_ID | J5: 3 | L5: Source account number | M5: =IFERROR(VLOOKUP($E5,'Field Definitions'!$A$1:$S$31597,4),"") -> NUMBER | N5: =IFERROR(VLOOKUP($E5,'Field Definitions'!$A$1:$S$31597,5),"") -> 9 | Q5: 1 | R5: =IF(IFERROR(VLOOKUP($E5,'Field Definitions'!$A$1:$S$31597,8),"")=0,"",IFERROR(VLOOKUP($E5,'Field Definitions'!$A$1:$S$31597,8),"")) | S5: =IF(IFERROR(VLOOKUP($E5,'Field Definitions'!$A$1:$S$31597,9),"")=0,"",IFERROR(VLOOKUP($E5,'Field Definitions'!$A$1:$S$31597,9),"")) | T5: =IF(IFERROR(VLOOKUP($E5,'Field Definitions'!$A$1:$S$31597,10),"")=0,"",IFERROR(VLOOKUP($E5,'Field Definitions'!$A$1:$S$31597,10),"")) | U5: =IF(IFERROR(VLOOKUP($E5,'Field Definitions'!$A$1:$S$31597,12),"")=0,"",IFERROR(VLOOKUP($E5,'Field Definitions'!$A$1:$S$31597,12),"")) | Y5: =";ACCT^"&J5&"^"&M5&"^"&N5 -> ;ACCT^3^NUMBER^9
C6: =IFERROR(VLOOKUP(E6,'Field Definitions'!$A$1:$S$31597,3),"") -> ARACCOUNT | E6: ARACCLTID | F6: MVP | I6: =IFERROR(VLOOKUP(E6,'Field Definitions'!$A$1:$S$31597,2),"") -> Client ID | J6: 4 | K6: Yes | L6: ContractID | M6: =IFERROR(VLOOKUP($E6,'Field Definitions'!$A$1:$S$31597,4),"") -> CHR | N6: 255 | Q6: ABC | R6: =IF(IFERROR(VLOOKUP($E6,'Field Definitions'!$A$1:$S$31597,8),"")=0,"",IFERROR(VLOOKUP($E6,'Field Definitions'!$A$1:$S$31597,8),"")) | S6: =IF(IFERROR(VLOOKUP($E6,'Field Definitions'!$A$1:$S$31597,9),"")=0,"",IFERROR(VLOOKUP($E6,'Field Definitions'!$A$1:$S$31597,9),"")) | T6: =IF(IFERROR(VLOOKUP($E6,'Field Definitions'!$A$1:$S$31597,10),"")=0,"",IFERROR(VLOOKUP($E6,'Field Definitions'!$A$1:$S$31597,10),"")) -> ARCLIENT | U6: =IF(IFERROR(VLOOKUP($E6,'Field Definitions'!$A$1:$S$31597,12),"")=0,"",IFERROR(VLOOKUP($E6,'Field Definitions'!$A$1:$S$31597,12),"")) | Y6: =";ACCT^"&J6&"^"&M6&"^"&N6 -> ;ACCT^4^CHR^255
A7: DBCLACCT | B7: ACCOUNT 11 | C7: =IFERROR(VLOOKUP(E7,'Field Definitions'!$A$1:$S$31597,3),"") -> ARACCOUNT | E7: ARACCLACCT | F7: MVP | I7: =IFERROR(VLOOKUP(E7,'Field Definitions'!$A$1:$S$31597,2),"") -> Client Reference Number | J7: 5 | K7: Yes | M7: =IFERROR(VLOOKUP($E7,'Field Definitions'!$A$1:$S$31597,4),"") -> CHR | N7: =IFERROR(VLOOKUP($E7,'Field Definitions'!$A$1:$S$31597,5),"") -> 30 | Q7: 1234111158 | R7: =IF(IFERROR(VLOOKUP($E7,'Field Definitions'!$A$1:$S$31597,8),"")=0,"",IFERROR(VLOOKUP($E7,'Field Definitions'!$A$1:$S$31597,8),"")) | S7: =IF(IFERROR(VLOOKUP($E7,'Field Definitions'!$A$1:$S$31597,9),"")=0,"",IFERROR(VLOOKUP($E7,'Field Definitions'!$A$1:$S$31597,9),"")) | T7: =IF(IFERROR(VLOOKUP($E7,'Field Definitions'!$A$1:$S$31597,10),"")=0,"",IFERROR(VLOOKUP($E7,'Field Definitions'!$A$1:$S$31597,10),"")) | U7: =IF(IFERROR(VLOOKUP($E7,'Field Definitions'!$A$1:$S$31597,12),"")=0,"",IFERROR(VLOOKUP($E7,'Field Definitions'!$A$1:$S$31597,12),"")) | Y7: =";ACCT^"&J7&"^"&M7&"^"&N7 -> ;ACCT^5^CHR^30
C8: =IFERROR(VLOOKUP(E8,'Field Definitions'!$A$1:$S$31597,3),"") -> ARACCOUNT | E8: ARACCLTFWDNAME | F8: NA | I8: =IFERROR(VLOOKUP(E8,'Field Definitions'!$A$1:$S$31597,2),"") -> Forward in client name | L8: Original creditor from forwarding agency | M8: =IFERROR(VLOOKUP($E8,'Field Definitions'!$A$1:$S$31597,4),"") -> CHR | N8: =IFERROR(VLOOKUP($E8,'Field Definitions'!$A$1:$S$31597,5),"") -> 60 | Q8: Ghost Busters Inc | R8: =IF(IFERROR(VLOOKUP($E8,'Field Definitions'!$A$1:$S$31597,8),"")=0,"",IFERROR(VLOOKUP($E8,'Field Definitions'!$A$1:$S$31597,8),"")) | S8: =IF(IFERROR(VLOOKUP($E8,'Field Definitions'!$A$1:$S$31597,9),"")=0,"",IFERROR(VLOOKUP($E8,'Field Definitions'!$A$1:$S$31597,9),"")) | T8: =IF(IFERROR(VLOOKUP($E8,'Field Definitions'!$A$1:$S$31597,10),"")=0,"",IFERROR(VLOOKUP($E8,'Field Definitions'!$A$1:$S$31597,10),"")) | U8: =IF(IFERROR(VLOOKUP($E8,'Field Definitions'!$A$1:$S$31597,12),"")=0,"",IFERROR(VLOOKUP($E8,'Field Definitions'!$A$1:$S$31597,12),"")) | Y8: =";ACCT^"&J8&"^"&M8&"^"&N8 -> ;ACCT^^CHR^60
A9: DBINCDTE | B9: ACCOUNT 12 | C9: =IFERROR(VLOOKUP(E9,'Field Definitions'!$A$1:$S$31597,3),"") -> ARACCOUNT | E9: ARACSRVDTE | F9: MVP | I9: =IFERROR(VLOOKUP(E9,'Field Definitions'!$A$1:$S$31597,2),"") -> Service Date | J9: 6 | M9: =IFERROR(VLOOKUP($E9,'Field Definitions'!$A$1:$S$31597,4),"") -> DATE | N9: =IFERROR(VLOOKUP($E9,'Field Definitions'!$A$1:$S$31597,5),"") -> 10 | Q9: 01/09/2010 | R9: =IF(IFERROR(VLOOKUP($E9,'Field Definitions'!$A$1:$S$31597,8),"")=0,"",IFERROR(VLOOKUP($E9,'Field Definitions'!$A$1:$S$31597,8),"")) | S9: =IF(IFERROR(VLOOKUP($E9,'Field Definitions'!$A$1:$S$31597,9),"")=0,"",IFERROR(VLOOKUP($E9,'Field Definitions'!$A$1:$S$31597,9),"")) | T9: =IF(IFERROR(VLOOKUP($E9,'Field Definitions'!$A$1:$S$31597,10),"")=0,"",IFERROR(VLOOKUP($E9,'Field Definitions'!$A$1:$S$31597,10),"")) | U9: =IF(IFERROR(VLOOKUP($E9,'Field Definitions'!$A$1:$S$31597,12),"")=0,"",IFERROR(VLOOKUP($E9,'Field Definitions'!$A$1:$S$31597,12),"")) | Y9: =";ACCT^"&J9&"^"&M9&"^"&N9 -> ;ACCT^6^DATE^10
A10: DBLSTDTE | B10: ACCOUNT 14 | C10: =IFERROR(VLOOKUP(E10,'Field Definitions'!$A$1:$S$31597,3),"") -> ARACCOUNT | E10: ARACLSTDTE | F10: MVP | I10: =IFERROR(VLOOKUP(E10,'Field Definitions'!$A$1:$S$31597,2),"") -> Listed Date | J10: 7 | K10: Yes | M10: =IFERROR(VLOOKUP($E10,'Field Definitions'!$A$1:$S$31597,4),"") -> DATE | N10: =IFERROR(VLOOKUP($E10,'Field Definitions'!$A$1:$S$31597,5),"") -> 10 | Q10: 01/13/2011 | R10: =IF(IFERROR(VLOOKUP($E10,'Field Definitions'!$A$1:$S$31597,8),"")=0,"",IFERROR(VLOOKUP($E10,'Field Definitions'!$A$1:$S$31597,8),"")) | S10: =IF(IFERROR(VLOOKUP($E10,'Field Definitions'!$A$1:$S$31597,9),"")=0,"",IFERROR(VLOOKUP($E10,'Field Definitions'!$A$1:$S$31597,9),"")) | T10: =IF(IFERROR(VLOOKUP($E10,'Field Definitions'!$A$1:$S$31597,10),"")=0,"",IFERROR(VLOOKUP($E10,'Field Definitions'!$A$1:$S$31597,10),"")) | U10: =IF(IFERROR(VLOOKUP($E10,'Field Definitions'!$A$1:$S$31597,12),"")=0,"",IFERROR(VLOOKUP($E10,'Field Definitions'!$A$1:$S$31597,12),"")) | Y10: =";ACCT^"&J10&"^"&M10&"^"&N10 -> ;ACCT^7^DATE^10
C11: =IFERROR(VLOOKUP(E11,'Field Definitions'!$A$1:$S$31597,3),"") -> ARRELATIONSHIP | E11: ARRELUSERID | F11: Later (assignment) | I11: =IFERROR(VLOOKUP(E11,'Field Definitions'!$A$1:$S$31597,2),"") -> Relationship user | L11: Assigned collector. This data will not be used on non-responsible parties | M11: =IFERROR(VLOOKUP($E11,'Field Definitions'!$A$1:$S$31597,4),"") -> CHR | N11: =IFERROR(VLOOKUP($E11,'Field Definitions'!$A$1:$S$31597,5),"") -> 4 | Q11: OSC | R11: =IF(IFERROR(VLOOKUP($E11,'Field Definitions'!$A$1:$S$31597,8),"")=0,"",IFERROR(VLOOKUP($E11,'Field Definitions'!$A$1:$S$31597,8),"")) | S11: =IF(IFERROR(VLOOKUP($E11,'Field Definitions'!$A$1:$S$31597,9),"")=0,"",IFERROR(VLOOKUP($E11,'Field Definitions'!$A$1:$S$31597,9),"")) | T11: =IF(IFERROR(VLOOKUP($E11,'Field Definitions'!$A$1:$S$31597,10),"")=0,"",IFERROR(VLOOKUP($E11,'Field Definitions'!$A$1:$S$31597,10),"")) -> STUSER | U11: =IF(IFERROR(VLOOKUP($E11,'Field Definitions'!$A$1:$S$31597,12),"")=0,"",IFERROR(VLOOKUP($E11,'Field Definitions'!$A$1:$S$31597,12),"")) | Y11: =";ACCT^"&J11&"^"&M11&"^"&N11 -> ;ACCT^^CHR^4
C12: =IFERROR(VLOOKUP(E12,'Field Definitions'!$A$1:$S$31597,3),"") -> ARACCOUNT | E12: FSACTYPE | F12: NA | I12: =IFERROR(VLOOKUP(E12,'Field Definitions'!$A$1:$S$31597,2),"") -> Account Type | M12: =IFERROR(VLOOKUP($E12,'Field Definitions'!$A$1:$S$31597,4),"") -> CHR | N12: =IFERROR(VLOOKUP($E12,'Field Definitions'!$A$1:$S$31597,5),"") -> 1 | Q12: R | R12: =IF(IFERROR(VLOOKUP($E12,'Field Definitions'!$A$1:$S$31597,8),"")=0,"",IFERROR(VLOOKUP($E12,'Field Definitions'!$A$1:$S$31597,8),"")) | S12: =IF(IFERROR(VLOOKUP($E12,'Field Definitions'!$A$1:$S$31597,9),"")=0,"",IFERROR(VLOOKUP($E12,'Field Definitions'!$A$1:$S$31597,9),"")) | T12: =IF(IFERROR(VLOOKUP($E12,'Field Definitions'!$A$1:$S$31597,10),"")=0,"",IFERROR(VLOOKUP($E12,'Field Definitions'!$A$1:$S$31597,10),"")) | U12: =IF(IFERROR(VLOOKUP($E12,'Field Definitions'!$A$1:$S$31597,12),"")=0,"",IFERROR(VLOOKUP($E12,'Field Definitions'!$A$1:$S$31597,12),"")) -> C|Collections|~R|Recovery| | Y12: =";ACCT^"&J12&"^"&M12&"^"&N12 -> ;ACCT^^CHR^1
C13: =IFERROR(VLOOKUP(E13,'Field Definitions'!$A$1:$S$31597,3),"") -> ARACCOUNT | E13: ARACCSNOTES | F13: NA | I13: =IFERROR(VLOOKUP(E13,'Field Definitions'!$A$1:$S$31597,2),"") -> Client Instructions | M13: =IFERROR(VLOOKUP($E13,'Field Definitions'!$A$1:$S$31597,4),"") -> CHR | N13: =IFERROR(VLOOKUP($E13,'Field Definitions'!$A$1:$S$31597,5),"") -> 60 | Q13: Client Instructions | R13: =IF(IFERROR(VLOOKUP($E13,'Field Definitions'!$A$1:$S$31597,8),"")=0,"",IFERROR(VLOOKUP($E13,'Field Definitions'!$A$1:$S$31597,8),"")) | S13: =IF(IFERROR(VLOOKUP($E13,'Field Definitions'!$A$1:$S$31597,9),"")=0,"",IFERROR(VLOOKUP($E13,'Field Definitions'!$A$1:$S$31597,9),"")) | T13: =IF(IFERROR(VLOOKUP($E13,'Field Definitions'!$A$1:$S$31597,10),"")=0,"",IFERROR(VLOOKUP($E13,'Field Definitions'!$A$1:$S$31597,10),"")) | U13: =IF(IFERROR(VLOOKUP($E13,'Field Definitions'!$A$1:$S$31597,12),"")=0,"",IFERROR(VLOOKUP($E13,'Field Definitions'!$A$1:$S$31597,12),"")) | Y13: =";ACCT^"&J13&"^"&M13&"^"&N13 -> ;ACCT^^CHR^60
C14: =IFERROR(VLOOKUP(E14,'Field Definitions'!$A$1:$S$31597,3),"") -> ARACCOUNT | E14: ARACSPNOTE | F14: NA | I14: NO LONGER USED | M14: =IFERROR(VLOOKUP($E14,'Field Definitions'!$A$1:$S$31597,4),"") -> EDITOR | N14: =IFERROR(VLOOKUP($E14,'Field Definitions'!$A$1:$S$31597,5),"") -> 78 | Q14: Special Note | R14: =IF(IFERROR(VLOOKUP($E14,'Field Definitions'!$A$1:$S$31597,8),"")=0,"",IFERROR(VLOOKUP($E14,'Field Definitions'!$A$1:$S$31597,8),"")) | S14: =IF(IFERROR(VLOOKUP($E14,'Field Definitions'!$A$1:$S$31597,9),"")=0,"",IFERROR(VLOOKUP($E14,'Field Definitions'!$A$1:$S$31597,9),"")) | T14: =IF(IFERROR(VLOOKUP($E14,'Field Definitions'!$A$1:$S$31597,10),"")=0,"",IFERROR(VLOOKUP($E14,'Field Definitions'!$A$1:$S$31597,10),"")) | U14: =IF(IFERROR(VLOOKUP($E14,'Field Definitions'!$A$1:$S$31597,12),"")=0,"",IFERROR(VLOOKUP($E14,'Field Definitions'!$A$1:$S$31597,12),"")) | Y14: =";ACCT^"&J14&"^"&M14&"^"&N14 -> ;ACCT^^EDITOR^78
C15: =IFERROR(VLOOKUP(E15,'Field Definitions'!$A$1:$S$31597,3),"") -> ARRELATIONSHIP | E15: ARRELSTATUSID | F15: NA | H15: Status | I15: =IFERROR(VLOOKUP(E15,'Field Definitions'!$A$1:$S$31597,2),"") -> Status | K15: Yes | M15: =IFERROR(VLOOKUP($E15,'Field Definitions'!$A$1:$S$31597,4),"") -> CHR | N15: =IFERROR(VLOOKUP($E15,'Field Definitions'!$A$1:$S$31597,5),"") -> 20 | Q15: NEWR | R15: =IF(IFERROR(VLOOKUP($E15,'Field Definitions'!$A$1:$S$31597,8),"")=0,"",IFERROR(VLOOKUP($E15,'Field Definitions'!$A$1:$S$31597,8),"")) | S15: =IF(IFERROR(VLOOKUP($E15,'Field Definitions'!$A$1:$S$31597,9),"")=0,"",IFERROR(VLOOKUP($E15,'Field Definitions'!$A$1:$S$31597,9),"")) | T15: =IF(IFERROR(VLOOKUP($E15,'Field Definitions'!$A$1:$S$31597,10),"")=0,"",IFERROR(VLOOKUP($E15,'Field Definitions'!$A$1:$S$31597,10),"")) -> ARSTATUS | U15: =IF(IFERROR(VLOOKUP($E15,'Field Definitions'!$A$1:$S$31597,12),"")=0,"",IFERROR(VLOOKUP($E15,'Field Definitions'!$A$1:$S$31597,12),"")) | Y15: =";ACCT^"&J15&"^"&M15&"^"&N15 -> ;ACCT^^CHR^20
C16: =IFERROR(VLOOKUP(E16,'Field Definitions'!$A$1:$S$31597,3),"") -> ARRELATIONSHIP | E16: ARRELPHSDTE | F16: NA | I16: =IFERROR(VLOOKUP(E16,'Field Definitions'!$A$1:$S$31597,2),"") -> Relationship phase chg date | L16: Status change date | M16: =IFERROR(VLOOKUP($E16,'Field Definitions'!$A$1:$S$31597,4),"") -> DATE | N16: =IFERROR(VLOOKUP($E16,'Field Definitions'!$A$1:$S$31597,5),"") -> 10 | Q16: 01/01/2013 | R16: =IF(IFERROR(VLOOKUP($E16,'Field Definitions'!$A$1:$S$31597,8),"")=0,"",IFERROR(VLOOKUP($E16,'Field Definitions'!$A$1:$S$31597,8),"")) | S16: =IF(IFERROR(VLOOKUP($E16,'Field Definitions'!$A$1:$S$31597,9),"")=0,"",IFERROR(VLOOKUP($E16,'Field Definitions'!$A$1:$S$31597,9),"")) | T16: =IF(IFERROR(VLOOKUP($E16,'Field Definitions'!$A$1:$S$31597,10),"")=0,"",IFERROR(VLOOKUP($E16,'Field Definitions'!$A$1:$S$31597,10),"")) | U16: =IF(IFERROR(VLOOKUP($E16,'Field Definitions'!$A$1:$S$31597,12),"")=0,"",IFERROR(VLOOKUP($E16,'Field Definitions'!$A$1:$S$31597,12),"")) | Y16: =";ACCT^"&J16&"^"&M16&"^"&N16 -> ;ACCT^^DATE^10
C17: =IFERROR(VLOOKUP(E17,'Field Definitions'!$A$1:$S$31597,3),"") -> ARRELATIONSHIP | E17: ARRELWAITDTE | F17: NA | I17: =IFERROR(VLOOKUP(E17,'Field Definitions'!$A$1:$S$31597,2),"") -> Follow-up Date | L17: This data will not be used for non-responsible parties. | M17: =IFERROR(VLOOKUP($E17,'Field Definitions'!$A$1:$S$31597,4),"") -> DATE | N17: =IFERROR(VLOOKUP($E17,'Field Definitions'!$A$1:$S$31597,5),"") -> 10 | Q17: 06/01/2013 | R17: =IF(IFERROR(VLOOKUP($E17,'Field Definitions'!$A$1:$S$31597,8),"")=0,"",IFERROR(VLOOKUP($E17,'Field Definitions'!$A$1:$S$31597,8),"")) | S17: =IF(IFERROR(VLOOKUP($E17,'Field Definitions'!$A$1:$S$31597,9),"")=0,"",IFERROR(VLOOKUP($E17,'Field Definitions'!$A$1:$S$31597,9),"")) | T17: =IF(IFERROR(VLOOKUP($E17,'Field Definitions'!$A$1:$S$31597,10),"")=0,"",IFERROR(VLOOKUP($E17,'Field Definitions'!$A$1:$S$31597,10),"")) | U17: =IF(IFERROR(VLOOKUP($E17,'Field Definitions'!$A$1:$S$31597,12),"")=0,"",IFERROR(VLOOKUP($E17,'Field Definitions'!$A$1:$S$31597,12),"")) | Y17: =";ACCT^"&J17&"^"&M17&"^"&N17 -> ;ACCT^^DATE^10
C18: =IFERROR(VLOOKUP(E18,'Field Definitions'!$A$1:$S$31597,3),"") -> ARACCOUNT | E18: ARACDISPUTE | F18: NA | I18: =IFERROR(VLOOKUP(E18,'Field Definitions'!$A$1:$S$31597,2),"") -> Disputed Status | M18: =IFERROR(VLOOKUP($E18,'Field Definitions'!$A$1:$S$31597,4),"") -> CHR | N18: =IFERROR(VLOOKUP($E18,'Field Definitions'!$A$1:$S$31597,5),"") -> 1 | Q18: R | R18: =IF(IFERROR(VLOOKUP($E18,'Field Definitions'!$A$1:$S$31597,8),"")=0,"",IFERROR(VLOOKUP($E18,'Field Definitions'!$A$1:$S$31597,8),"")) | S18: =IF(IFERROR(VLOOKUP($E18,'Field Definitions'!$A$1:$S$31597,9),"")=0,"",IFERROR(VLOOKUP($E18,'Field Definitions'!$A$1:$S$31597,9),"")) | T18: =IF(IFERROR(VLOOKUP($E18,'Field Definitions'!$A$1:$S$31597,10),"")=0,"",IFERROR(VLOOKUP($E18,'Field Definitions'!$A$1:$S$31597,10),"")) | U18: =IF(IFERROR(VLOOKUP($E18,'Field Definitions'!$A$1:$S$31597,12),"")=0,"",IFERROR(VLOOKUP($E18,'Field Definitions'!$A$1:$S$31597,12),"")) -> Y|Yes|~N|No|~R|Resolved| | Y18: =";ACCT^"&J18&"^"&M18&"^"&N18 -> ;ACCT^^CHR^1
C19: =IFERROR(VLOOKUP(E19,'Field Definitions'!$A$1:$S$31597,3),"") -> ARACCOUNT | E19: ARACLITIGATED | F19: NA | I19: =IFERROR(VLOOKUP(E19,'Field Definitions'!$A$1:$S$31597,2),"") -> Litigation Setting | M19: =IFERROR(VLOOKUP($E19,'Field Definitions'!$A$1:$S$31597,4),"") -> CHR | N19: =IFERROR(VLOOKUP($E19,'Field Definitions'!$A$1:$S$31597,5),"") -> 1 | Q19: N | R19: =IF(IFERROR(VLOOKUP($E19,'Field Definitions'!$A$1:$S$31597,8),"")=0,"",IFERROR(VLOOKUP($E19,'Field Definitions'!$A$1:$S$31597,8),"")) | S19: =IF(IFERROR(VLOOKUP($E19,'Field Definitions'!$A$1:$S$31597,9),"")=0,"",IFERROR(VLOOKUP($E19,'Field Definitions'!$A$1:$S$31597,9),"")) | T19: =IF(IFERROR(VLOOKUP($E19,'Field Definitions'!$A$1:$S$31597,10),"")=0,"",IFERROR(VLOOKUP($E19,'Field Definitions'!$A$1:$S$31597,10),"")) | U19: =IF(IFERROR(VLOOKUP($E19,'Field Definitions'!$A$1:$S$31597,12),"")=0,"",IFERROR(VLOOKUP($E19,'Field Definitions'!$A$1:$S$31597,12),"")) -> L||~N||~B|| | Y19: =";ACCT^"&J19&"^"&M19&"^"&N19 -> ;ACCT^^CHR^1
C20: =IFERROR(VLOOKUP(E20,'Field Definitions'!$A$1:$S$31597,3),"") -> ARACCOUNT | E20: ARACBANKRUPT | F20: NA | I20: =IFERROR(VLOOKUP(E20,'Field Definitions'!$A$1:$S$31597,2),"") -> Is Account Involved in a Bankruptcy | L20: Note 4 | M20: =IFERROR(VLOOKUP($E20,'Field Definitions'!$A$1:$S$31597,4),"") -> CHR | N20: =IFERROR(VLOOKUP($E20,'Field Definitions'!$A$1:$S$31597,5),"") -> 1 | Q20: Y | R20: =IF(IFERROR(VLOOKUP($E20,'Field Definitions'!$A$1:$S$31597,8),"")=0,"",IFERROR(VLOOKUP($E20,'Field Definitions'!$A$1:$S$31597,8),"")) | S20: =IF(IFERROR(VLOOKUP($E20,'Field Definitions'!$A$1:$S$31597,9),"")=0,"",IFERROR(VLOOKUP($E20,'Field Definitions'!$A$1:$S$31597,9),"")) | T20: =IF(IFERROR(VLOOKUP($E20,'Field Definitions'!$A$1:$S$31597,10),"")=0,"",IFERROR(VLOOKUP($E20,'Field Definitions'!$A$1:$S$31597,10),"")) | U20: =IF(IFERROR(VLOOKUP($E20,'Field Definitions'!$A$1:$S$31597,12),"")=0,"",IFERROR(VLOOKUP($E20,'Field Definitions'!$A$1:$S$31597,12),"")) -> Y|Yes|~N|No| | Y20: =";ACCT^"&J20&"^"&M20&"^"&N20 -> ;ACCT^^CHR^1
C21: =IFERROR(VLOOKUP(E21,'Field Definitions'!$A$1:$S$31597,3),"") -> ARACCOUNT | E21: FSACTSCLDTE | F21: NA | I21: =IFERROR(VLOOKUP(E21,'Field Definitions'!$A$1:$S$31597,2),"") -> Claim Date | M21: =IFERROR(VLOOKUP($E21,'Field Definitions'!$A$1:$S$31597,4),"") -> DATE | N21: =IFERROR(VLOOKUP($E21,'Field Definitions'!$A$1:$S$31597,5),"") -> 10 | Q21: 06/02/2011 | R21: =IF(IFERROR(VLOOKUP($E21,'Field Definitions'!$A$1:$S$31597,8),"")=0,"",IFERROR(VLOOKUP($E21,'Field Definitions'!$A$1:$S$31597,8),"")) | S21: =IF(IFERROR(VLOOKUP($E21,'Field Definitions'!$A$1:$S$31597,9),"")=0,"",IFERROR(VLOOKUP($E21,'Field Definitions'!$A$1:$S$31597,9),"")) | T21: =IF(IFERROR(VLOOKUP($E21,'Field Definitions'!$A$1:$S$31597,10),"")=0,"",IFERROR(VLOOKUP($E21,'Field Definitions'!$A$1:$S$31597,10),"")) | U21: =IF(IFERROR(VLOOKUP($E21,'Field Definitions'!$A$1:$S$31597,12),"")=0,"",IFERROR(VLOOKUP($E21,'Field Definitions'!$A$1:$S$31597,12),"")) | Y21: =";ACCT^"&J21&"^"&M21&"^"&N21 -> ;ACCT^^DATE^10
C22: =IFERROR(VLOOKUP(E22,'Field Definitions'!$A$1:$S$31597,3),"") -> ARACCOUNT | E22: ARACVIP | F22: NA | I22: =IFERROR(VLOOKUP(E22,'Field Definitions'!$A$1:$S$31597,2),"") -> VIP | M22: =IFERROR(VLOOKUP($E22,'Field Definitions'!$A$1:$S$31597,4),"") -> CHR | N22: =IFERROR(VLOOKUP($E22,'Field Definitions'!$A$1:$S$31597,5),"") -> 1 | Q22: N | R22: =IF(IFERROR(VLOOKUP($E22,'Field Definitions'!$A$1:$S$31597,8),"")=0,"",IFERROR(VLOOKUP($E22,'Field Definitions'!$A$1:$S$31597,8),"")) | S22: =IF(IFERROR(VLOOKUP($E22,'Field Definitions'!$A$1:$S$31597,9),"")=0,"",IFERROR(VLOOKUP($E22,'Field Definitions'!$A$1:$S$31597,9),"")) | T22: =IF(IFERROR(VLOOKUP($E22,'Field Definitions'!$A$1:$S$31597,10),"")=0,"",IFERROR(VLOOKUP($E22,'Field Definitions'!$A$1:$S$31597,10),"")) | U22: =IF(IFERROR(VLOOKUP($E22,'Field Definitions'!$A$1:$S$31597,12),"")=0,"",IFERROR(VLOOKUP($E22,'Field Definitions'!$A$1:$S$31597,12),"")) -> Y|Yes|~N|No| | Y22: =";ACCT^"&J22&"^"&M22&"^"&N22 -> ;ACCT^^CHR^1
C23: =IFERROR(VLOOKUP(E23,'Field Definitions'!$A$1:$S$31597,3),"") -> ARACCOUNT | E23: FSACEMPLOYEE | F23: NA | I23: =IFERROR(VLOOKUP(E23,'Field Definitions'!$A$1:$S$31597,2),"") -> Employee | M23: =IFERROR(VLOOKUP($E23,'Field Definitions'!$A$1:$S$31597,4),"") -> CHR | N23: =IFERROR(VLOOKUP($E23,'Field Definitions'!$A$1:$S$31597,5),"") -> 1 | Q23: N | R23: =IF(IFERROR(VLOOKUP($E23,'Field Definitions'!$A$1:$S$31597,8),"")=0,"",IFERROR(VLOOKUP($E23,'Field Definitions'!$A$1:$S$31597,8),"")) | S23: =IF(IFERROR(VLOOKUP($E23,'Field Definitions'!$A$1:$S$31597,9),"")=0,"",IFERROR(VLOOKUP($E23,'Field Definitions'!$A$1:$S$31597,9),"")) | T23: =IF(IFERROR(VLOOKUP($E23,'Field Definitions'!$A$1:$S$31597,10),"")=0,"",IFERROR(VLOOKUP($E23,'Field Definitions'!$A$1:$S$31597,10),"")) | U23: =IF(IFERROR(VLOOKUP($E23,'Field Definitions'!$A$1:$S$31597,12),"")=0,"",IFERROR(VLOOKUP($E23,'Field Definitions'!$A$1:$S$31597,12),"")) -> Y|Yes|~N|No| | Y23: =";ACCT^"&J23&"^"&M23&"^"&N23 -> ;ACCT^^CHR^1
C24: =IFERROR(VLOOKUP(E24,'Field Definitions'!$A$1:$S$31597,3),"") -> ARACCOUNT | E24: FSACSKIPTRACE | F24: NA | I24: =IFERROR(VLOOKUP(E24,'Field Definitions'!$A$1:$S$31597,2),"") -> Skiptrace Needed | M24: =IFERROR(VLOOKUP($E24,'Field Definitions'!$A$1:$S$31597,4),"") -> CHR | N24: =IFERROR(VLOOKUP($E24,'Field Definitions'!$A$1:$S$31597,5),"") -> 1 | Q24: N | R24: =IF(IFERROR(VLOOKUP($E24,'Field Definitions'!$A$1:$S$31597,8),"")=0,"",IFERROR(VLOOKUP($E24,'Field Definitions'!$A$1:$S$31597,8),"")) | S24: =IF(IFERROR(VLOOKUP($E24,'Field Definitions'!$A$1:$S$31597,9),"")=0,"",IFERROR(VLOOKUP($E24,'Field Definitions'!$A$1:$S$31597,9),"")) | T24: =IF(IFERROR(VLOOKUP($E24,'Field Definitions'!$A$1:$S$31597,10),"")=0,"",IFERROR(VLOOKUP($E24,'Field Definitions'!$A$1:$S$31597,10),"")) | U24: =IF(IFERROR(VLOOKUP($E24,'Field Definitions'!$A$1:$S$31597,12),"")=0,"",IFERROR(VLOOKUP($E24,'Field Definitions'!$A$1:$S$31597,12),"")) -> Y|Yes|~N|No| | Y24: =";ACCT^"&J24&"^"&M24&"^"&N24 -> ;ACCT^^CHR^1
C25: =IFERROR(VLOOKUP(E25,'Field Definitions'!$A$1:$S$31597,3),"") -> ARACCOUNT | E25: FSACSSCRA | F25: NA | I25: =IFERROR(VLOOKUP(E25,'Field Definitions'!$A$1:$S$31597,2),"") -> Soldiers and Sailors Flag | M25: =IFERROR(VLOOKUP($E25,'Field Definitions'!$A$1:$S$31597,4),"") -> CHR | N25: =IFERROR(VLOOKUP($E25,'Field Definitions'!$A$1:$S$31597,5),"") -> 1 | Q25: N | R25: =IF(IFERROR(VLOOKUP($E25,'Field Definitions'!$A$1:$S$31597,8),"")=0,"",IFERROR(VLOOKUP($E25,'Field Definitions'!$A$1:$S$31597,8),"")) | S25: =IF(IFERROR(VLOOKUP($E25,'Field Definitions'!$A$1:$S$31597,9),"")=0,"",IFERROR(VLOOKUP($E25,'Field Definitions'!$A$1:$S$31597,9),"")) | T25: =IF(IFERROR(VLOOKUP($E25,'Field Definitions'!$A$1:$S$31597,10),"")=0,"",IFERROR(VLOOKUP($E25,'Field Definitions'!$A$1:$S$31597,10),"")) | U25: =IF(IFERROR(VLOOKUP($E25,'Field Definitions'!$A$1:$S$31597,12),"")=0,"",IFERROR(VLOOKUP($E25,'Field Definitions'!$A$1:$S$31597,12),"")) -> Y|Yes|~N|No| | Y25: =";ACCT^"&J25&"^"&M25&"^"&N25 -> ;ACCT^^CHR^1
C26: =IFERROR(VLOOKUP(E26,'Field Definitions'!$A$1:$S$31597,3),"") -> ARACCOUNT | E26: ARACCANCID | F26: MVP | H26: Cancel information | I26: =IFERROR(VLOOKUP(E26,'Field Definitions'!$A$1:$S$31597,2),"") -> Cancel Code | J26: 8 | M26: =IFERROR(VLOOKUP($E26,'Field Definitions'!$A$1:$S$31597,4),"") -> CHR | N26: =IFERROR(VLOOKUP($E26,'Field Definitions'!$A$1:$S$31597,5),"") -> 10 | R26: =IF(IFERROR(VLOOKUP($E26,'Field Definitions'!$A$1:$S$31597,8),"")=0,"",IFERROR(VLOOKUP($E26,'Field Definitions'!$A$1:$S$31597,8),"")) | S26: =IF(IFERROR(VLOOKUP($E26,'Field Definitions'!$A$1:$S$31597,9),"")=0,"",IFERROR(VLOOKUP($E26,'Field Definitions'!$A$1:$S$31597,9),"")) | T26: =IF(IFERROR(VLOOKUP($E26,'Field Definitions'!$A$1:$S$31597,10),"")=0,"",IFERROR(VLOOKUP($E26,'Field Definitions'!$A$1:$S$31597,10),"")) -> ARCANCEL | U26: =IF(IFERROR(VLOOKUP($E26,'Field Definitions'!$A$1:$S$31597,12),"")=0,"",IFERROR(VLOOKUP($E26,'Field Definitions'!$A$1:$S$31597,12),"")) | Y26: =";ACCT^"&J26&"^"&M26&"^"&N26 -> ;ACCT^8^CHR^10
A27: DBCANDTE | C27: =IFERROR(VLOOKUP(E27,'Field Definitions'!$A$1:$S$31597,3),"") -> ARACCOUNT | E27: ARACCANCDTE | F27: MVP | I27: =IFERROR(VLOOKUP(E27,'Field Definitions'!$A$1:$S$31597,2),"") -> Cancel Date | J27: 9 | M27: =IFERROR(VLOOKUP($E27,'Field Definitions'!$A$1:$S$31597,4),"") -> DATE | N27: =IFERROR(VLOOKUP($E27,'Field Definitions'!$A$1:$S$31597,5),"") -> 10 | R27: =IF(IFERROR(VLOOKUP($E27,'Field Definitions'!$A$1:$S$31597,8),"")=0,"",IFERROR(VLOOKUP($E27,'Field Definitions'!$A$1:$S$31597,8),"")) | S27: =IF(IFERROR(VLOOKUP($E27,'Field Definitions'!$A$1:$S$31597,9),"")=0,"",IFERROR(VLOOKUP($E27,'Field Definitions'!$A$1:$S$31597,9),"")) | T27: =IF(IFERROR(VLOOKUP($E27,'Field Definitions'!$A$1:$S$31597,10),"")=0,"",IFERROR(VLOOKUP($E27,'Field Definitions'!$A$1:$S$31597,10),"")) | U27: =IF(IFERROR(VLOOKUP($E27,'Field Definitions'!$A$1:$S$31597,12),"")=0,"",IFERROR(VLOOKUP($E27,'Field Definitions'!$A$1:$S$31597,12),"")) | Y27: =";ACCT^"&J27&"^"&M27&"^"&N27 -> ;ACCT^9^DATE^10
C28: =IFERROR(VLOOKUP(E28,'Field Definitions'!$A$1:$S$31597,3),"") -> ARACCOUNT | E28: ARACCANCBAKAMT | F28: MVP | I28: =IFERROR(VLOOKUP(E28,'Field Definitions'!$A$1:$S$31597,2),"") -> Amount Canceled Back | J28: 10 | M28: =IFERROR(VLOOKUP($E28,'Field Definitions'!$A$1:$S$31597,4),"") -> AMT | N28: =IFERROR(VLOOKUP($E28,'Field Definitions'!$A$1:$S$31597,5),"") -> 16 | R28: =IF(IFERROR(VLOOKUP($E28,'Field Definitions'!$A$1:$S$31597,8),"")=0,"",IFERROR(VLOOKUP($E28,'Field Definitions'!$A$1:$S$31597,8),"")) | S28: =IF(IFERROR(VLOOKUP($E28,'Field Definitions'!$A$1:$S$31597,9),"")=0,"",IFERROR(VLOOKUP($E28,'Field Definitions'!$A$1:$S$31597,9),"")) | T28: =IF(IFERROR(VLOOKUP($E28,'Field Definitions'!$A$1:$S$31597,10),"")=0,"",IFERROR(VLOOKUP($E28,'Field Definitions'!$A$1:$S$31597,10),"")) | U28: =IF(IFERROR(VLOOKUP($E28,'Field Definitions'!$A$1:$S$31597,12),"")=0,"",IFERROR(VLOOKUP($E28,'Field Definitions'!$A$1:$S$31597,12),"")) | Y28: =";ACCT^"&J28&"^"&M28&"^"&N28 -> ;ACCT^10^AMT^16
C29: =IFERROR(VLOOKUP(E29,'Field Definitions'!$A$1:$S$31597,3),"") -> ARACCOUNT | E29: ARACCANCCOL | F29: MVP | I29: =IFERROR(VLOOKUP(E29,'Field Definitions'!$A$1:$S$31597,2),"") -> Canceling user | J29: 11 | M29: =IFERROR(VLOOKUP($E29,'Field Definitions'!$A$1:$S$31597,4),"") -> CHR | N29: =IFERROR(VLOOKUP($E29,'Field Definitions'!$A$1:$S$31597,5),"") -> 4 | R29: =IF(IFERROR(VLOOKUP($E29,'Field Definitions'!$A$1:$S$31597,8),"")=0,"",IFERROR(VLOOKUP($E29,'Field Definitions'!$A$1:$S$31597,8),"")) | S29: =IF(IFERROR(VLOOKUP($E29,'Field Definitions'!$A$1:$S$31597,9),"")=0,"",IFERROR(VLOOKUP($E29,'Field Definitions'!$A$1:$S$31597,9),"")) | T29: =IF(IFERROR(VLOOKUP($E29,'Field Definitions'!$A$1:$S$31597,10),"")=0,"",IFERROR(VLOOKUP($E29,'Field Definitions'!$A$1:$S$31597,10),"")) | U29: =IF(IFERROR(VLOOKUP($E29,'Field Definitions'!$A$1:$S$31597,12),"")=0,"",IFERROR(VLOOKUP($E29,'Field Definitions'!$A$1:$S$31597,12),"")) | Y29: =";ACCT^"&J29&"^"&M29&"^"&N29 -> ;ACCT^11^CHR^4
C30: =IFERROR(VLOOKUP(E30,'Field Definitions'!$A$1:$S$31597,3),"") -> ARACCOUNT | E30: ARACCONTACTS | F30: MVP | H30: Contact information | I30: =IFERROR(VLOOKUP(E30,'Field Definitions'!$A$1:$S$31597,2),"") -> The number of contacts | J30: 12 | M30: =IFERROR(VLOOKUP($E30,'Field Definitions'!$A$1:$S$31597,4),"") -> NUMBER | N30: =IFERROR(VLOOKUP($E30,'Field Definitions'!$A$1:$S$31597,5),"") -> 3 | Q30: 1 | R30: =IF(IFERROR(VLOOKUP($E30,'Field Definitions'!$A$1:$S$31597,8),"")=0,"",IFERROR(VLOOKUP($E30,'Field Definitions'!$A$1:$S$31597,8),"")) | S30: =IF(IFERROR(VLOOKUP($E30,'Field Definitions'!$A$1:$S$31597,9),"")=0,"",IFERROR(VLOOKUP($E30,'Field Definitions'!$A$1:$S$31597,9),"")) | T30: =IF(IFERROR(VLOOKUP($E30,'Field Definitions'!$A$1:$S$31597,10),"")=0,"",IFERROR(VLOOKUP($E30,'Field Definitions'!$A$1:$S$31597,10),"")) | U30: =IF(IFERROR(VLOOKUP($E30,'Field Definitions'!$A$1:$S$31597,12),"")=0,"",IFERROR(VLOOKUP($E30,'Field Definitions'!$A$1:$S$31597,12),"")) | Y30: =";ACCT^"&J30&"^"&M30&"^"&N30 -> ;ACCT^12^NUMBER^3
C31: =IFERROR(VLOOKUP(E31,'Field Definitions'!$A$1:$S$31597,3),"") -> ARACCOUNT | E31: ARACCALLS | F31: MVP | I31: =IFERROR(VLOOKUP(E31,'Field Definitions'!$A$1:$S$31597,2),"") -> Number of phone calls dialed | J31: 13 | M31: =IFERROR(VLOOKUP($E31,'Field Definitions'!$A$1:$S$31597,4),"") -> NUMBER | N31: =IFERROR(VLOOKUP($E31,'Field Definitions'!$A$1:$S$31597,5),"") -> 3 | Q31: 3 | R31: =IF(IFERROR(VLOOKUP($E31,'Field Definitions'!$A$1:$S$31597,8),"")=0,"",IFERROR(VLOOKUP($E31,'Field Definitions'!$A$1:$S$31597,8),"")) | S31: =IF(IFERROR(VLOOKUP($E31,'Field Definitions'!$A$1:$S$31597,9),"")=0,"",IFERROR(VLOOKUP($E31,'Field Definitions'!$A$1:$S$31597,9),"")) | T31: =IF(IFERROR(VLOOKUP($E31,'Field Definitions'!$A$1:$S$31597,10),"")=0,"",IFERROR(VLOOKUP($E31,'Field Definitions'!$A$1:$S$31597,10),"")) | U31: =IF(IFERROR(VLOOKUP($E31,'Field Definitions'!$A$1:$S$31597,12),"")=0,"",IFERROR(VLOOKUP($E31,'Field Definitions'!$A$1:$S$31597,12),"")) | Y31: =";ACCT^"&J31&"^"&M31&"^"&N31 -> ;ACCT^13^NUMBER^3
C32: =IFERROR(VLOOKUP(E32,'Field Definitions'!$A$1:$S$31597,3),"") -> ARACCOUNT | E32: ARACLTRS | F32: MVP | I32: =IFERROR(VLOOKUP(E32,'Field Definitions'!$A$1:$S$31597,2),"") -> Number of letters sent | J32: 14 | M32: =IFERROR(VLOOKUP($E32,'Field Definitions'!$A$1:$S$31597,4),"") -> NUMBER | N32: =IFERROR(VLOOKUP($E32,'Field Definitions'!$A$1:$S$31597,5),"") -> 3 | Q32: 10 | R32: =IF(IFERROR(VLOOKUP($E32,'Field Definitions'!$A$1:$S$31597,8),"")=0,"",IFERROR(VLOOKUP($E32,'Field Definitions'!$A$1:$S$31597,8),"")) | S32: =IF(IFERROR(VLOOKUP($E32,'Field Definitions'!$A$1:$S$31597,9),"")=0,"",IFERROR(VLOOKUP($E32,'Field Definitions'!$A$1:$S$31597,9),"")) | T32: =IF(IFERROR(VLOOKUP($E32,'Field Definitions'!$A$1:$S$31597,10),"")=0,"",IFERROR(VLOOKUP($E32,'Field Definitions'!$A$1:$S$31597,10),"")) | U32: =IF(IFERROR(VLOOKUP($E32,'Field Definitions'!$A$1:$S$31597,12),"")=0,"",IFERROR(VLOOKUP($E32,'Field Definitions'!$A$1:$S$31597,12),"")) | Y32: =";ACCT^"&J32&"^"&M32&"^"&N32 -> ;ACCT^14^NUMBER^3
C33: =IFERROR(VLOOKUP(E33,'Field Definitions'!$A$1:$S$31597,3),"") -> ARACCOUNT | E33: ARACLSTLTR | F33: MVP | I33: =IFERROR(VLOOKUP(E33,'Field Definitions'!$A$1:$S$31597,2),"") -> Last Letter Code | J33: 15 | M33: =IFERROR(VLOOKUP($E33,'Field Definitions'!$A$1:$S$31597,4),"") -> CHR | N33: =IFERROR(VLOOKUP($E33,'Field Definitions'!$A$1:$S$31597,5),"") -> 8 | Q33: LTR | R33: =IF(IFERROR(VLOOKUP($E33,'Field Definitions'!$A$1:$S$31597,8),"")=0,"",IFERROR(VLOOKUP($E33,'Field Definitions'!$A$1:$S$31597,8),"")) | S33: =IF(IFERROR(VLOOKUP($E33,'Field Definitions'!$A$1:$S$31597,9),"")=0,"",IFERROR(VLOOKUP($E33,'Field Definitions'!$A$1:$S$31597,9),"")) | T33: =IF(IFERROR(VLOOKUP($E33,'Field Definitions'!$A$1:$S$31597,10),"")=0,"",IFERROR(VLOOKUP($E33,'Field Definitions'!$A$1:$S$31597,10),"")) -> STLETTER | U33: =IF(IFERROR(VLOOKUP($E33,'Field Definitions'!$A$1:$S$31597,12),"")=0,"",IFERROR(VLOOKUP($E33,'Field Definitions'!$A$1:$S$31597,12),"")) | Y33: =";ACCT^"&J33&"^"&M33&"^"&N33 -> ;ACCT^15^CHR^8
C34: =IFERROR(VLOOKUP(E34,'Field Definitions'!$A$1:$S$31597,3),"") -> ARACCOUNT | E34: ARACLTRDTE | F34: MVP | I34: =IFERROR(VLOOKUP(E34,'Field Definitions'!$A$1:$S$31597,2),"") -> Last Letter Sent Date | J34: 16 | M34: =IFERROR(VLOOKUP($E34,'Field Definitions'!$A$1:$S$31597,4),"") -> DATE | N34: =IFERROR(VLOOKUP($E34,'Field Definitions'!$A$1:$S$31597,5),"") -> 10 | Q34: 01/01/2013 | R34: =IF(IFERROR(VLOOKUP($E34,'Field Definitions'!$A$1:$S$31597,8),"")=0,"",IFERROR(VLOOKUP($E34,'Field Definitions'!$A$1:$S$31597,8),"")) | S34: =IF(IFERROR(VLOOKUP($E34,'Field Definitions'!$A$1:$S$31597,9),"")=0,"",IFERROR(VLOOKUP($E34,'Field Definitions'!$A$1:$S$31597,9),"")) | T34: =IF(IFERROR(VLOOKUP($E34,'Field Definitions'!$A$1:$S$31597,10),"")=0,"",IFERROR(VLOOKUP($E34,'Field Definitions'!$A$1:$S$31597,10),"")) | U34: =IF(IFERROR(VLOOKUP($E34,'Field Definitions'!$A$1:$S$31597,12),"")=0,"",IFERROR(VLOOKUP($E34,'Field Definitions'!$A$1:$S$31597,12),"")) | Y34: =";ACCT^"&J34&"^"&M34&"^"&N34 -> ;ACCT^16^DATE^10
C35: =IFERROR(VLOOKUP(E35,'Field Definitions'!$A$1:$S$31597,3),"") -> ARACCOUNT | E35: ARACRETMAIL | F35: MVP | I35: =IFERROR(VLOOKUP(E35,'Field Definitions'!$A$1:$S$31597,2),"") -> Returned Mail | J35: 17 | M35: =IFERROR(VLOOKUP($E35,'Field Definitions'!$A$1:$S$31597,4),"") -> NUMBER | N35: =IFERROR(VLOOKUP($E35,'Field Definitions'!$A$1:$S$31597,5),"") -> 3 | Q35: 2 | R35: =IF(IFERROR(VLOOKUP($E35,'Field Definitions'!$A$1:$S$31597,8),"")=0,"",IFERROR(VLOOKUP($E35,'Field Definitions'!$A$1:$S$31597,8),"")) | S35: =IF(IFERROR(VLOOKUP($E35,'Field Definitions'!$A$1:$S$31597,9),"")=0,"",IFERROR(VLOOKUP($E35,'Field Definitions'!$A$1:$S$31597,9),"")) -> 999 | T35: =IF(IFERROR(VLOOKUP($E35,'Field Definitions'!$A$1:$S$31597,10),"")=0,"",IFERROR(VLOOKUP($E35,'Field Definitions'!$A$1:$S$31597,10),"")) | U35: =IF(IFERROR(VLOOKUP($E35,'Field Definitions'!$A$1:$S$31597,12),"")=0,"",IFERROR(VLOOKUP($E35,'Field Definitions'!$A$1:$S$31597,12),"")) | Y35: =";ACCT^"&J35&"^"&M35&"^"&N35 -> ;ACCT^17^NUMBER^3
C36: =IFERROR(VLOOKUP(E36,'Field Definitions'!$A$1:$S$31597,3),"") -> A3RELATIONSHIP | E36: A3RELPL95LTR | F36: MVP | I36: Initial PL95 Letter Code | J36: 18 | M36: =IFERROR(VLOOKUP($E36,'Field Definitions'!$A$1:$S$31597,4),"") -> CHR | N36: =IFERROR(VLOOKUP($E36,'Field Definitions'!$A$1:$S$31597,5),"") -> 8 | Q36: PL95 | R36: =IF(IFERROR(VLOOKUP($E36,'Field Definitions'!$A$1:$S$31597,8),"")=0,"",IFERROR(VLOOKUP($E36,'Field Definitions'!$A$1:$S$31597,8),"")) | S36: =IF(IFERROR(VLOOKUP($E36,'Field Definitions'!$A$1:$S$31597,9),"")=0,"",IFERROR(VLOOKUP($E36,'Field Definitions'!$A$1:$S$31597,9),"")) | T36: =IF(IFERROR(VLOOKUP($E36,'Field Definitions'!$A$1:$S$31597,10),"")=0,"",IFERROR(VLOOKUP($E36,'Field Definitions'!$A$1:$S$31597,10),"")) -> STLETTER | U36: =IF(IFERROR(VLOOKUP($E36,'Field Definitions'!$A$1:$S$31597,12),"")=0,"",IFERROR(VLOOKUP($E36,'Field Definitions'!$A$1:$S$31597,12),"")) | Y36: =";ACCT^"&J36&"^"&M36&"^"&N36 -> ;ACCT^18^CHR^8
C37: =IFERROR(VLOOKUP(E37,'Field Definitions'!$A$1:$S$31597,3),"") -> A3RELATIONSHIP | E37: A3RELPL95DTE | F37: MVP | I37: Initial PL95 Letter Date | J37: 19 | M37: =IFERROR(VLOOKUP($E37,'Field Definitions'!$A$1:$S$31597,4),"") -> DATE | N37: =IFERROR(VLOOKUP($E37,'Field Definitions'!$A$1:$S$31597,5),"") -> 10 | Q37: 01/01/2012 | R37: =IF(IFERROR(VLOOKUP($E37,'Field Definitions'!$A$1:$S$31597,8),"")=0,"",IFERROR(VLOOKUP($E37,'Field Definitions'!$A$1:$S$31597,8),"")) | S37: =IF(IFERROR(VLOOKUP($E37,'Field Definitions'!$A$1:$S$31597,9),"")=0,"",IFERROR(VLOOKUP($E37,'Field Definitions'!$A$1:$S$31597,9),"")) | T37: =IF(IFERROR(VLOOKUP($E37,'Field Definitions'!$A$1:$S$31597,10),"")=0,"",IFERROR(VLOOKUP($E37,'Field Definitions'!$A$1:$S$31597,10),"")) | U37: =IF(IFERROR(VLOOKUP($E37,'Field Definitions'!$A$1:$S$31597,12),"")=0,"",IFERROR(VLOOKUP($E37,'Field Definitions'!$A$1:$S$31597,12),"")) | Y37: =";ACCT^"&J37&"^"&M37&"^"&N37 -> ;ACCT^19^DATE^10
C38: =IFERROR(VLOOKUP(E38,'Field Definitions'!$A$1:$S$31597,3),"") -> AFACCOUNT | E38: AFACRATEID | F38: MVP | H38: Payments | I38: =IFERROR(VLOOKUP(E38,'Field Definitions'!$A$1:$S$31597,2),"") -> Rate schedule | J38: 20 | K38: Yes | M38: =IFERROR(VLOOKUP($E38,'Field Definitions'!$A$1:$S$31597,4),"") -> CHR | N38: =IFERROR(VLOOKUP($E38,'Field Definitions'!$A$1:$S$31597,5),"") -> 10 | Q38: 10 | R38: =IF(IFERROR(VLOOKUP($E38,'Field Definitions'!$A$1:$S$31597,8),"")=0,"",IFERROR(VLOOKUP($E38,'Field Definitions'!$A$1:$S$31597,8),"")) | S38: =IF(IFERROR(VLOOKUP($E38,'Field Definitions'!$A$1:$S$31597,9),"")=0,"",IFERROR(VLOOKUP($E38,'Field Definitions'!$A$1:$S$31597,9),"")) | T38: =IF(IFERROR(VLOOKUP($E38,'Field Definitions'!$A$1:$S$31597,10),"")=0,"",IFERROR(VLOOKUP($E38,'Field Definitions'!$A$1:$S$31597,10),"")) -> ARRATE | U38: =IF(IFERROR(VLOOKUP($E38,'Field Definitions'!$A$1:$S$31597,12),"")=0,"",IFERROR(VLOOKUP($E38,'Field Definitions'!$A$1:$S$31597,12),"")) | Y38: =";ACCT^"&J38&"^"&M38&"^"&N38 -> ;ACCT^20^CHR^10
C39: =IFERROR(VLOOKUP(E39,'Field Definitions'!$A$1:$S$31597,3),"") -> AFACCOUNT | E39: AFACCASHNOTE | F39: MVP | I39: =IFERROR(VLOOKUP(E39,'Field Definitions'!$A$1:$S$31597,2),"") -> Cashier's notes | J39: 21 | M39: =IFERROR(VLOOKUP($E39,'Field Definitions'!$A$1:$S$31597,4),"") -> EDITOR | N39: =IFERROR(VLOOKUP($E39,'Field Definitions'!$A$1:$S$31597,5),"") -> 68 | Q39: Cashier's note | R39: =IF(IFERROR(VLOOKUP($E39,'Field Definitions'!$A$1:$S$31597,8),"")=0,"",IFERROR(VLOOKUP($E39,'Field Definitions'!$A$1:$S$31597,8),"")) | S39: =IF(IFERROR(VLOOKUP($E39,'Field Definitions'!$A$1:$S$31597,9),"")=0,"",IFERROR(VLOOKUP($E39,'Field Definitions'!$A$1:$S$31597,9),"")) | T39: =IF(IFERROR(VLOOKUP($E39,'Field Definitions'!$A$1:$S$31597,10),"")=0,"",IFERROR(VLOOKUP($E39,'Field Definitions'!$A$1:$S$31597,10),"")) | U39: =IF(IFERROR(VLOOKUP($E39,'Field Definitions'!$A$1:$S$31597,12),"")=0,"",IFERROR(VLOOKUP($E39,'Field Definitions'!$A$1:$S$31597,12),"")) | Y39: =";ACCT^"&J39&"^"&M39&"^"&N39 -> ;ACCT^21^EDITOR^68
C40: =IFERROR(VLOOKUP(E40,'Field Definitions'!$A$1:$S$31597,3),"") -> AFACCOUNT | E40: AFACHOLDDAYS | F40: MVP | I40: =IFERROR(VLOOKUP(E40,'Field Definitions'!$A$1:$S$31597,2),"") -> Transaction Hold Days | J40: 22 | M40: =IFERROR(VLOOKUP($E40,'Field Definitions'!$A$1:$S$31597,4),"") -> NUMBER | N40: =IFERROR(VLOOKUP($E40,'Field Definitions'!$A$1:$S$31597,5),"") -> 3 | Q40: 7 | R40: =IF(IFERROR(VLOOKUP($E40,'Field Definitions'!$A$1:$S$31597,8),"")=0,"",IFERROR(VLOOKUP($E40,'Field Definitions'!$A$1:$S$31597,8),"")) | S40: =IF(IFERROR(VLOOKUP($E40,'Field Definitions'!$A$1:$S$31597,9),"")=0,"",IFERROR(VLOOKUP($E40,'Field Definitions'!$A$1:$S$31597,9),"")) -> 999 | T40: =IF(IFERROR(VLOOKUP($E40,'Field Definitions'!$A$1:$S$31597,10),"")=0,"",IFERROR(VLOOKUP($E40,'Field Definitions'!$A$1:$S$31597,10),"")) | U40: =IF(IFERROR(VLOOKUP($E40,'Field Definitions'!$A$1:$S$31597,12),"")=0,"",IFERROR(VLOOKUP($E40,'Field Definitions'!$A$1:$S$31597,12),"")) | Y40: =";ACCT^"&J40&"^"&M40&"^"&N40 -> ;ACCT^22^NUMBER^3
A41: DSLPYDTE | C41: =IFERROR(VLOOKUP(E41,'Field Definitions'!$A$1:$S$31597,3),"") -> ARACCOUNT | E41: ARACCNVLPYDTE | F41: MVP | I41: =IFERROR(VLOOKUP(E41,'Field Definitions'!$A$1:$S$31597,2),"") -> Converted last payment date | J41: 23 | M41: =IFERROR(VLOOKUP($E41,'Field Definitions'!$A$1:$S$31597,4),"") -> DATE | N41: =IFERROR(VLOOKUP($E41,'Field Definitions'!$A$1:$S$31597,5),"") -> 10 | Q41: 06/13/2012 | R41: =IF(IFERROR(VLOOKUP($E41,'Field Definitions'!$A$1:$S$31597,8),"")=0,"",IFERROR(VLOOKUP($E41,'Field Definitions'!$A$1:$S$31597,8),"")) | S41: =IF(IFERROR(VLOOKUP($E41,'Field Definitions'!$A$1:$S$31597,9),"")=0,"",IFERROR(VLOOKUP($E41,'Field Definitions'!$A$1:$S$31597,9),"")) | T41: =IF(IFERROR(VLOOKUP($E41,'Field Definitions'!$A$1:$S$31597,10),"")=0,"",IFERROR(VLOOKUP($E41,'Field Definitions'!$A$1:$S$31597,10),"")) | U41: =IF(IFERROR(VLOOKUP($E41,'Field Definitions'!$A$1:$S$31597,12),"")=0,"",IFERROR(VLOOKUP($E41,'Field Definitions'!$A$1:$S$31597,12),"")) | Y41: =";ACCT^"&J41&"^"&M41&"^"&N41 -> ;ACCT^23^DATE^10
C42: =IFERROR(VLOOKUP(E42,'Field Definitions'!$A$1:$S$31597,3),"") -> ARACCOUNT | E42: ARACCNVLPYAMT | F42: MVP | I42: =IFERROR(VLOOKUP(E42,'Field Definitions'!$A$1:$S$31597,2),"") -> Converted last payment amount | J42: 24 | M42: =IFERROR(VLOOKUP($E42,'Field Definitions'!$A$1:$S$31597,4),"") -> AMT | N42: =IFERROR(VLOOKUP($E42,'Field Definitions'!$A$1:$S$31597,5),"") -> 12 | Q42: 100.01 | R42: =IF(IFERROR(VLOOKUP($E42,'Field Definitions'!$A$1:$S$31597,8),"")=0,"",IFERROR(VLOOKUP($E42,'Field Definitions'!$A$1:$S$31597,8),"")) | S42: =IF(IFERROR(VLOOKUP($E42,'Field Definitions'!$A$1:$S$31597,9),"")=0,"",IFERROR(VLOOKUP($E42,'Field Definitions'!$A$1:$S$31597,9),"")) | T42: =IF(IFERROR(VLOOKUP($E42,'Field Definitions'!$A$1:$S$31597,10),"")=0,"",IFERROR(VLOOKUP($E42,'Field Definitions'!$A$1:$S$31597,10),"")) | U42: =IF(IFERROR(VLOOKUP($E42,'Field Definitions'!$A$1:$S$31597,12),"")=0,"",IFERROR(VLOOKUP($E42,'Field Definitions'!$A$1:$S$31597,12),"")) | Y42: =";ACCT^"&J42&"^"&M42&"^"&N42 -> ;ACCT^24^AMT^12
C43: =IFERROR(VLOOKUP(E43,'Field Definitions'!$A$1:$S$31597,3),"") -> AFACCOUNT | E43: AFACINBASE | F43: MVP | H43: Interest | I43: =IFERROR(VLOOKUP(E43,'Field Definitions'!$A$1:$S$31597,2),"") -> Int: Interest Base | J43: 25 | M43: =IFERROR(VLOOKUP($E43,'Field Definitions'!$A$1:$S$31597,4),"") -> CHR | N43: =IFERROR(VLOOKUP($E43,'Field Definitions'!$A$1:$S$31597,5),"") -> 8 | Q43: DEFAULT | R43: =IF(IFERROR(VLOOKUP($E43,'Field Definitions'!$A$1:$S$31597,8),"")=0,"",IFERROR(VLOOKUP($E43,'Field Definitions'!$A$1:$S$31597,8),"")) | S43: =IF(IFERROR(VLOOKUP($E43,'Field Definitions'!$A$1:$S$31597,9),"")=0,"",IFERROR(VLOOKUP($E43,'Field Definitions'!$A$1:$S$31597,9),"")) | T43: =IF(IFERROR(VLOOKUP($E43,'Field Definitions'!$A$1:$S$31597,10),"")=0,"",IFERROR(VLOOKUP($E43,'Field Definitions'!$A$1:$S$31597,10),"")) -> ARINBASE | U43: =IF(IFERROR(VLOOKUP($E43,'Field Definitions'!$A$1:$S$31597,12),"")=0,"",IFERROR(VLOOKUP($E43,'Field Definitions'!$A$1:$S$31597,12),"")) | Y43: =";ACCT^"&J43&"^"&M43&"^"&N43 -> ;ACCT^25^CHR^8
C44: =IFERROR(VLOOKUP(E44,'Field Definitions'!$A$1:$S$31597,3),"") -> AFACCOUNT | E44: AFACINTRATE | F44: MVP | I44: =IFERROR(VLOOKUP(E44,'Field Definitions'!$A$1:$S$31597,2),"") -> Int: Interest Rate | J44: 26 | M44: =IFERROR(VLOOKUP($E44,'Field Definitions'!$A$1:$S$31597,4),"") -> AMT | N44: =IFERROR(VLOOKUP($E44,'Field Definitions'!$A$1:$S$31597,5),"") -> 7 | Q44: 25 | R44: =IF(IFERROR(VLOOKUP($E44,'Field Definitions'!$A$1:$S$31597,8),"")=0,"",IFERROR(VLOOKUP($E44,'Field Definitions'!$A$1:$S$31597,8),"")) | S44: =IF(IFERROR(VLOOKUP($E44,'Field Definitions'!$A$1:$S$31597,9),"")=0,"",IFERROR(VLOOKUP($E44,'Field Definitions'!$A$1:$S$31597,9),"")) | T44: =IF(IFERROR(VLOOKUP($E44,'Field Definitions'!$A$1:$S$31597,10),"")=0,"",IFERROR(VLOOKUP($E44,'Field Definitions'!$A$1:$S$31597,10),"")) | U44: =IF(IFERROR(VLOOKUP($E44,'Field Definitions'!$A$1:$S$31597,12),"")=0,"",IFERROR(VLOOKUP($E44,'Field Definitions'!$A$1:$S$31597,12),"")) | Y44: =";ACCT^"&J44&"^"&M44&"^"&N44 -> ;ACCT^26^AMT^7
C45: =IFERROR(VLOOKUP(E45,'Field Definitions'!$A$1:$S$31597,3),"") -> AFACCOUNT | E45: AFACINTHRUDT | F45: MVP | I45: =IFERROR(VLOOKUP(E45,'Field Definitions'!$A$1:$S$31597,2),"") -> Int: Interest Thru Date | J45: 27 | M45: =IFERROR(VLOOKUP($E45,'Field Definitions'!$A$1:$S$31597,4),"") -> DATE | N45: =IFERROR(VLOOKUP($E45,'Field Definitions'!$A$1:$S$31597,5),"") -> 10 | Q45: 01/15/2013 | R45: =IF(IFERROR(VLOOKUP($E45,'Field Definitions'!$A$1:$S$31597,8),"")=0,"",IFERROR(VLOOKUP($E45,'Field Definitions'!$A$1:$S$31597,8),"")) | S45: =IF(IFERROR(VLOOKUP($E45,'Field Definitions'!$A$1:$S$31597,9),"")=0,"",IFERROR(VLOOKUP($E45,'Field Definitions'!$A$1:$S$31597,9),"")) | T45: =IF(IFERROR(VLOOKUP($E45,'Field Definitions'!$A$1:$S$31597,10),"")=0,"",IFERROR(VLOOKUP($E45,'Field Definitions'!$A$1:$S$31597,10),"")) | U45: =IF(IFERROR(VLOOKUP($E45,'Field Definitions'!$A$1:$S$31597,12),"")=0,"",IFERROR(VLOOKUP($E45,'Field Definitions'!$A$1:$S$31597,12),"")) | Y45: =";ACCT^"&J45&"^"&M45&"^"&N45 -> ;ACCT^27^DATE^10
C46: =IFERROR(VLOOKUP(E46,'Field Definitions'!$A$1:$S$31597,3),"") -> AFACCOUNT | E46: AFACINPRATE | F46: MVP | I46: =IFERROR(VLOOKUP(E46,'Field Definitions'!$A$1:$S$31597,2),"") -> Int:Postjudgment Interest Rate | J46: 28 | M46: =IFERROR(VLOOKUP($E46,'Field Definitions'!$A$1:$S$31597,4),"") -> AMT | N46: =IFERROR(VLOOKUP($E46,'Field Definitions'!$A$1:$S$31597,5),"") -> 7 | Q46: 30 | R46: =IF(IFERROR(VLOOKUP($E46,'Field Definitions'!$A$1:$S$31597,8),"")=0,"",IFERROR(VLOOKUP($E46,'Field Definitions'!$A$1:$S$31597,8),"")) | S46: =IF(IFERROR(VLOOKUP($E46,'Field Definitions'!$A$1:$S$31597,9),"")=0,"",IFERROR(VLOOKUP($E46,'Field Definitions'!$A$1:$S$31597,9),"")) | T46: =IF(IFERROR(VLOOKUP($E46,'Field Definitions'!$A$1:$S$31597,10),"")=0,"",IFERROR(VLOOKUP($E46,'Field Definitions'!$A$1:$S$31597,10),"")) | U46: =IF(IFERROR(VLOOKUP($E46,'Field Definitions'!$A$1:$S$31597,12),"")=0,"",IFERROR(VLOOKUP($E46,'Field Definitions'!$A$1:$S$31597,12),"")) | Y46: =";ACCT^"&J46&"^"&M46&"^"&N46 -> ;ACCT^28^AMT^7
C47: =IFERROR(VLOOKUP(E47,'Field Definitions'!$A$1:$S$31597,3),"") -> ARACCOUNT | E47: ARACVENDID | F47: GA | H47: Placement | I47: =IFERROR(VLOOKUP(E47,'Field Definitions'!$A$1:$S$31597,2),"") -> Account vendor | K47: Note 5 | L47: Use the placement status fields if vendors have been migrated prior to the migration. | M47: =IFERROR(VLOOKUP($E47,'Field Definitions'!$A$1:$S$31597,4),"") -> CHR | N47: =IFERROR(VLOOKUP($E47,'Field Definitions'!$A$1:$S$31597,5),"") -> 20 | Q47: BOA | R47: =IF(IFERROR(VLOOKUP($E47,'Field Definitions'!$A$1:$S$31597,8),"")=0,"",IFERROR(VLOOKUP($E47,'Field Definitions'!$A$1:$S$31597,8),"")) | S47: =IF(IFERROR(VLOOKUP($E47,'Field Definitions'!$A$1:$S$31597,9),"")=0,"",IFERROR(VLOOKUP($E47,'Field Definitions'!$A$1:$S$31597,9),"")) | T47: =IF(IFERROR(VLOOKUP($E47,'Field Definitions'!$A$1:$S$31597,10),"")=0,"",IFERROR(VLOOKUP($E47,'Field Definitions'!$A$1:$S$31597,10),"")) -> ARVENDOR | U47: =IF(IFERROR(VLOOKUP($E47,'Field Definitions'!$A$1:$S$31597,12),"")=0,"",IFERROR(VLOOKUP($E47,'Field Definitions'!$A$1:$S$31597,12),"")) | Y47: =";ACCT^"&J47&"^"&M47&"^"&N47 -> ;ACCT^^CHR^20
C48: =IFERROR(VLOOKUP(E48,'Field Definitions'!$A$1:$S$31597,3),"") -> FSVECONTRACT | E48: FSVECNAME | I48: =IFERROR(VLOOKUP(E48,'Field Definitions'!$A$1:$S$31597,2),"") -> Name | M48: =IFERROR(VLOOKUP($E48,'Field Definitions'!$A$1:$S$31597,4),"") -> CHR | N48: =IFERROR(VLOOKUP($E48,'Field Definitions'!$A$1:$S$31597,5),"") -> 20 | Q48: ATTY | R48: =IF(IFERROR(VLOOKUP($E48,'Field Definitions'!$A$1:$S$31597,8),"")=0,"",IFERROR(VLOOKUP($E48,'Field Definitions'!$A$1:$S$31597,8),"")) | S48: =IF(IFERROR(VLOOKUP($E48,'Field Definitions'!$A$1:$S$31597,9),"")=0,"",IFERROR(VLOOKUP($E48,'Field Definitions'!$A$1:$S$31597,9),"")) | T48: =IF(IFERROR(VLOOKUP($E48,'Field Definitions'!$A$1:$S$31597,10),"")=0,"",IFERROR(VLOOKUP($E48,'Field Definitions'!$A$1:$S$31597,10),"")) | U48: =IF(IFERROR(VLOOKUP($E48,'Field Definitions'!$A$1:$S$31597,12),"")=0,"",IFERROR(VLOOKUP($E48,'Field Definitions'!$A$1:$S$31597,12),"")) | Y48: =";ACCT^"&J48&"^"&M48&"^"&N48 -> ;ACCT^^CHR^20
C49: =IFERROR(VLOOKUP(E49,'Field Definitions'!$A$1:$S$31597,3),"") -> FSVECONTPLACE | E49: FSVECPPHSID | I49: Placement Level | M49: =IFERROR(VLOOKUP($E49,'Field Definitions'!$A$1:$S$31597,4),"") -> CHR | N49: =IFERROR(VLOOKUP($E49,'Field Definitions'!$A$1:$S$31597,5),"") -> 20 | Q49: PRIMARY | R49: =IF(IFERROR(VLOOKUP($E49,'Field Definitions'!$A$1:$S$31597,8),"")=0,"",IFERROR(VLOOKUP($E49,'Field Definitions'!$A$1:$S$31597,8),"")) | S49: =IF(IFERROR(VLOOKUP($E49,'Field Definitions'!$A$1:$S$31597,9),"")=0,"",IFERROR(VLOOKUP($E49,'Field Definitions'!$A$1:$S$31597,9),"")) | T49: =IF(IFERROR(VLOOKUP($E49,'Field Definitions'!$A$1:$S$31597,10),"")=0,"",IFERROR(VLOOKUP($E49,'Field Definitions'!$A$1:$S$31597,10),"")) | U49: =IF(IFERROR(VLOOKUP($E49,'Field Definitions'!$A$1:$S$31597,12),"")=0,"",IFERROR(VLOOKUP($E49,'Field Definitions'!$A$1:$S$31597,12),"")) | Y49: =";ACCT^"&J49&"^"&M49&"^"&N49 -> ;ACCT^^CHR^20
C50: =IFERROR(VLOOKUP(E50,'Field Definitions'!$A$1:$S$31597,3),"") -> ARACCOUNT | E50: ARACVENPLACEDTE | I50: =IFERROR(VLOOKUP(E50,'Field Definitions'!$A$1:$S$31597,2),"") -> Vendor Placement Date | M50: =IFERROR(VLOOKUP($E50,'Field Definitions'!$A$1:$S$31597,4),"") -> DATE | N50: =IFERROR(VLOOKUP($E50,'Field Definitions'!$A$1:$S$31597,5),"") -> 10 | Q50: 01/15/2013 | R50: =IF(IFERROR(VLOOKUP($E50,'Field Definitions'!$A$1:$S$31597,8),"")=0,"",IFERROR(VLOOKUP($E50,'Field Definitions'!$A$1:$S$31597,8),"")) | S50: =IF(IFERROR(VLOOKUP($E50,'Field Definitions'!$A$1:$S$31597,9),"")=0,"",IFERROR(VLOOKUP($E50,'Field Definitions'!$A$1:$S$31597,9),"")) | T50: =IF(IFERROR(VLOOKUP($E50,'Field Definitions'!$A$1:$S$31597,10),"")=0,"",IFERROR(VLOOKUP($E50,'Field Definitions'!$A$1:$S$31597,10),"")) | U50: =IF(IFERROR(VLOOKUP($E50,'Field Definitions'!$A$1:$S$31597,12),"")=0,"",IFERROR(VLOOKUP($E50,'Field Definitions'!$A$1:$S$31597,12),"")) | Y50: =";ACCT^"&J50&"^"&M50&"^"&N50 -> ;ACCT^^DATE^10
C51: =IFERROR(VLOOKUP(E51,'Field Definitions'!$A$1:$S$31597,3),"") -> ARACCOUNT | E51: FSACVELAWLIST | I51: =IFERROR(VLOOKUP(E51,'Field Definitions'!$A$1:$S$31597,2),"") -> Vendor Law List | M51: =IFERROR(VLOOKUP($E51,'Field Definitions'!$A$1:$S$31597,4),"") -> CHR | N51: =IFERROR(VLOOKUP($E51,'Field Definitions'!$A$1:$S$31597,5),"") -> 10 | Q51: DEF | R51: =IF(IFERROR(VLOOKUP($E51,'Field Definitions'!$A$1:$S$31597,8),"")=0,"",IFERROR(VLOOKUP($E51,'Field Definitions'!$A$1:$S$31597,8),"")) | S51: =IF(IFERROR(VLOOKUP($E51,'Field Definitions'!$A$1:$S$31597,9),"")=0,"",IFERROR(VLOOKUP($E51,'Field Definitions'!$A$1:$S$31597,9),"")) | T51: =IF(IFERROR(VLOOKUP($E51,'Field Definitions'!$A$1:$S$31597,10),"")=0,"",IFERROR(VLOOKUP($E51,'Field Definitions'!$A$1:$S$31597,10),"")) | U51: =IF(IFERROR(VLOOKUP($E51,'Field Definitions'!$A$1:$S$31597,12),"")=0,"",IFERROR(VLOOKUP($E51,'Field Definitions'!$A$1:$S$31597,12),"")) | Y51: =";ACCT^"&J51&"^"&M51&"^"&N51 -> ;ACCT^^CHR^10
C52: =IFERROR(VLOOKUP(E52,'Field Definitions'!$A$1:$S$31597,3),"") -> ARACCOUNT | E52: ARACVENSTATID | I52: =IFERROR(VLOOKUP(E52,'Field Definitions'!$A$1:$S$31597,2),"") -> Current Vendor Status | M52: =IFERROR(VLOOKUP($E52,'Field Definitions'!$A$1:$S$31597,4),"") -> CHR | N52: =IFERROR(VLOOKUP($E52,'Field Definitions'!$A$1:$S$31597,5),"") -> 20 | Q52: ACTIVE | R52: =IF(IFERROR(VLOOKUP($E52,'Field Definitions'!$A$1:$S$31597,8),"")=0,"",IFERROR(VLOOKUP($E52,'Field Definitions'!$A$1:$S$31597,8),"")) | S52: =IF(IFERROR(VLOOKUP($E52,'Field Definitions'!$A$1:$S$31597,9),"")=0,"",IFERROR(VLOOKUP($E52,'Field Definitions'!$A$1:$S$31597,9),"")) | T52: ARVESTATCD | U52: =IF(IFERROR(VLOOKUP($E52,'Field Definitions'!$A$1:$S$31597,12),"")=0,"",IFERROR(VLOOKUP($E52,'Field Definitions'!$A$1:$S$31597,12),"")) | Y52: =";ACCT^"&J52&"^"&M52&"^"&N52 -> ;ACCT^^CHR^20
C53: =IFERROR(VLOOKUP(E53,'Field Definitions'!$A$1:$S$31597,3),"") -> ARACCOUNT | E53: ARACCHGOFFDTE | F53: MVP | H53: Charge Off | I53: =IFERROR(VLOOKUP(E53,'Field Definitions'!$A$1:$S$31597,2),"") -> Charge off date | J53: 29 | M53: =IFERROR(VLOOKUP($E53,'Field Definitions'!$A$1:$S$31597,4),"") -> DATE | N53: =IFERROR(VLOOKUP($E53,'Field Definitions'!$A$1:$S$31597,5),"") -> 10 | Q53: 07/28/2012 | R53: =IF(IFERROR(VLOOKUP($E53,'Field Definitions'!$A$1:$S$31597,8),"")=0,"",IFERROR(VLOOKUP($E53,'Field Definitions'!$A$1:$S$31597,8),"")) | S53: =IF(IFERROR(VLOOKUP($E53,'Field Definitions'!$A$1:$S$31597,9),"")=0,"",IFERROR(VLOOKUP($E53,'Field Definitions'!$A$1:$S$31597,9),"")) | T53: =IF(IFERROR(VLOOKUP($E53,'Field Definitions'!$A$1:$S$31597,10),"")=0,"",IFERROR(VLOOKUP($E53,'Field Definitions'!$A$1:$S$31597,10),"")) | U53: =IF(IFERROR(VLOOKUP($E53,'Field Definitions'!$A$1:$S$31597,12),"")=0,"",IFERROR(VLOOKUP($E53,'Field Definitions'!$A$1:$S$31597,12),"")) | Y53: =";ACCT^"&J53&"^"&M53&"^"&N53 -> ;ACCT^29^DATE^10
C54: =IFERROR(VLOOKUP(E54,'Field Definitions'!$A$1:$S$31597,3),"") -> ARACCOUNT | E54: ARACCHGOFFAMT | F54: MVP | I54: =IFERROR(VLOOKUP(E54,'Field Definitions'!$A$1:$S$31597,2),"") -> Charge-Off Amount | J54: 30 | M54: =IFERROR(VLOOKUP($E54,'Field Definitions'!$A$1:$S$31597,4),"") -> AMT | N54: =IFERROR(VLOOKUP($E54,'Field Definitions'!$A$1:$S$31597,5),"") -> 16 | Q54: 1143.74 | R54: =IF(IFERROR(VLOOKUP($E54,'Field Definitions'!$A$1:$S$31597,8),"")=0,"",IFERROR(VLOOKUP($E54,'Field Definitions'!$A$1:$S$31597,8),"")) | S54: =IF(IFERROR(VLOOKUP($E54,'Field Definitions'!$A$1:$S$31597,9),"")=0,"",IFERROR(VLOOKUP($E54,'Field Definitions'!$A$1:$S$31597,9),"")) | T54: =IF(IFERROR(VLOOKUP($E54,'Field Definitions'!$A$1:$S$31597,10),"")=0,"",IFERROR(VLOOKUP($E54,'Field Definitions'!$A$1:$S$31597,10),"")) | U54: =IF(IFERROR(VLOOKUP($E54,'Field Definitions'!$A$1:$S$31597,12),"")=0,"",IFERROR(VLOOKUP($E54,'Field Definitions'!$A$1:$S$31597,12),"")) | Y54: =";ACCT^"&J54&"^"&M54&"^"&N54 -> ;ACCT^30^AMT^16
C55: =IFERROR(VLOOKUP(E55,'Field Definitions'!$A$1:$S$31597,3),"") -> ARACCOUNT | E55: ARACCHGOFFRSN | F55: GA | I55: =IFERROR(VLOOKUP(E55,'Field Definitions'!$A$1:$S$31597,2),"") -> Charge off reason | M55: =IFERROR(VLOOKUP($E55,'Field Definitions'!$A$1:$S$31597,4),"") -> CHR | N55: =IFERROR(VLOOKUP($E55,'Field Definitions'!$A$1:$S$31597,5),"") -> 10 | Q55: EE | R55: =IF(IFERROR(VLOOKUP($E55,'Field Definitions'!$A$1:$S$31597,8),"")=0,"",IFERROR(VLOOKUP($E55,'Field Definitions'!$A$1:$S$31597,8),"")) | S55: =IF(IFERROR(VLOOKUP($E55,'Field Definitions'!$A$1:$S$31597,9),"")=0,"",IFERROR(VLOOKUP($E55,'Field Definitions'!$A$1:$S$31597,9),"")) | T55: =IF(IFERROR(VLOOKUP($E55,'Field Definitions'!$A$1:$S$31597,10),"")=0,"",IFERROR(VLOOKUP($E55,'Field Definitions'!$A$1:$S$31597,10),"")) -> ARREFCHGOFFRSN | U55: =IF(IFERROR(VLOOKUP($E55,'Field Definitions'!$A$1:$S$31597,12),"")=0,"",IFERROR(VLOOKUP($E55,'Field Definitions'!$A$1:$S$31597,12),"")) | Y55: =";ACCT^"&J55&"^"&M55&"^"&N55 -> ;ACCT^^CHR^10
C56: =IFERROR(VLOOKUP(E56,'Field Definitions'!$A$1:$S$31597,3),"") -> ARACCOUNT | E56: FSACCHGOFFPRN | F56: GA | I56: =IFERROR(VLOOKUP(E56,'Field Definitions'!$A$1:$S$31597,2),"") -> Charge Off Principal | M56: =IFERROR(VLOOKUP($E56,'Field Definitions'!$A$1:$S$31597,4),"") -> AMT | N56: =IFERROR(VLOOKUP($E56,'Field Definitions'!$A$1:$S$31597,5),"") -> 18 | Q56: 1000.00 | R56: =IF(IFERROR(VLOOKUP($E56,'Field Definitions'!$A$1:$S$31597,8),"")=0,"",IFERROR(VLOOKUP($E56,'Field Definitions'!$A$1:$S$31597,8),"")) | S56: =IF(IFERROR(VLOOKUP($E56,'Field Definitions'!$A$1:$S$31597,9),"")=0,"",IFERROR(VLOOKUP($E56,'Field Definitions'!$A$1:$S$31597,9),"")) | T56: =IF(IFERROR(VLOOKUP($E56,'Field Definitions'!$A$1:$S$31597,10),"")=0,"",IFERROR(VLOOKUP($E56,'Field Definitions'!$A$1:$S$31597,10),"")) | U56: =IF(IFERROR(VLOOKUP($E56,'Field Definitions'!$A$1:$S$31597,12),"")=0,"",IFERROR(VLOOKUP($E56,'Field Definitions'!$A$1:$S$31597,12),"")) | Y56: =";ACCT^"&J56&"^"&M56&"^"&N56 -> ;ACCT^^AMT^18
C57: =IFERROR(VLOOKUP(E57,'Field Definitions'!$A$1:$S$31597,3),"") -> ARACCOUNT | E57: ARACDISPRSNID | F57: Later | H57: Dispute | I57: =IFERROR(VLOOKUP(E57,'Field Definitions'!$A$1:$S$31597,2),"") -> Dispute Reason ID | M57: =IFERROR(VLOOKUP($E57,'Field Definitions'!$A$1:$S$31597,4),"") -> CHR | N57: =IFERROR(VLOOKUP($E57,'Field Definitions'!$A$1:$S$31597,5),"") -> 6 | Q57: BECAUSE | R57: =IF(IFERROR(VLOOKUP($E57,'Field Definitions'!$A$1:$S$31597,8),"")=0,"",IFERROR(VLOOKUP($E57,'Field Definitions'!$A$1:$S$31597,8),"")) | S57: =IF(IFERROR(VLOOKUP($E57,'Field Definitions'!$A$1:$S$31597,9),"")=0,"",IFERROR(VLOOKUP($E57,'Field Definitions'!$A$1:$S$31597,9),"")) | T57: =IF(IFERROR(VLOOKUP($E57,'Field Definitions'!$A$1:$S$31597,10),"")=0,"",IFERROR(VLOOKUP($E57,'Field Definitions'!$A$1:$S$31597,10),"")) -> ARDISPRSN | U57: =IF(IFERROR(VLOOKUP($E57,'Field Definitions'!$A$1:$S$31597,12),"")=0,"",IFERROR(VLOOKUP($E57,'Field Definitions'!$A$1:$S$31597,12),"")) | Y57: =";ACCT^"&J57&"^"&M57&"^"&N57 -> ;ACCT^^CHR^6
C58: =IFERROR(VLOOKUP(E58,'Field Definitions'!$A$1:$S$31597,3),"") -> ARACCOUNT | E58: ARACDISPDTE | I58: =IFERROR(VLOOKUP(E58,'Field Definitions'!$A$1:$S$31597,2),"") -> Dispute Date | M58: =IFERROR(VLOOKUP($E58,'Field Definitions'!$A$1:$S$31597,4),"") -> DATE | N58: =IFERROR(VLOOKUP($E58,'Field Definitions'!$A$1:$S$31597,5),"") -> 10 | Q58: 01/20/2013 | R58: =IF(IFERROR(VLOOKUP($E58,'Field Definitions'!$A$1:$S$31597,8),"")=0,"",IFERROR(VLOOKUP($E58,'Field Definitions'!$A$1:$S$31597,8),"")) | S58: =IF(IFERROR(VLOOKUP($E58,'Field Definitions'!$A$1:$S$31597,9),"")=0,"",IFERROR(VLOOKUP($E58,'Field Definitions'!$A$1:$S$31597,9),"")) | T58: =IF(IFERROR(VLOOKUP($E58,'Field Definitions'!$A$1:$S$31597,10),"")=0,"",IFERROR(VLOOKUP($E58,'Field Definitions'!$A$1:$S$31597,10),"")) | U58: =IF(IFERROR(VLOOKUP($E58,'Field Definitions'!$A$1:$S$31597,12),"")=0,"",IFERROR(VLOOKUP($E58,'Field Definitions'!$A$1:$S$31597,12),"")) | Y58: =";ACCT^"&J58&"^"&M58&"^"&N58 -> ;ACCT^^DATE^10
C59: =IFERROR(VLOOKUP(E59,'Field Definitions'!$A$1:$S$31597,3),"") -> ARACCOUNT | E59: ARACEXTSCORE | F59: Later | H59: Score | I59: =IFERROR(VLOOKUP(E59,'Field Definitions'!$A$1:$S$31597,2),"") -> External Score | M59: =IFERROR(VLOOKUP($E59,'Field Definitions'!$A$1:$S$31597,4),"") -> AMT | N59: =IFERROR(VLOOKUP($E59,'Field Definitions'!$A$1:$S$31597,5),"") -> 12 | Q59: 42 | R59: =IF(IFERROR(VLOOKUP($E59,'Field Definitions'!$A$1:$S$31597,8),"")=0,"",IFERROR(VLOOKUP($E59,'Field Definitions'!$A$1:$S$31597,8),"")) | S59: =IF(IFERROR(VLOOKUP($E59,'Field Definitions'!$A$1:$S$31597,9),"")=0,"",IFERROR(VLOOKUP($E59,'Field Definitions'!$A$1:$S$31597,9),"")) | T59: =IF(IFERROR(VLOOKUP($E59,'Field Definitions'!$A$1:$S$31597,10),"")=0,"",IFERROR(VLOOKUP($E59,'Field Definitions'!$A$1:$S$31597,10),"")) | U59: =IF(IFERROR(VLOOKUP($E59,'Field Definitions'!$A$1:$S$31597,12),"")=0,"",IFERROR(VLOOKUP($E59,'Field Definitions'!$A$1:$S$31597,12),"")) | Y59: =";ACCT^"&J59&"^"&M59&"^"&N59 -> ;ACCT^^AMT^12
C60: =IFERROR(VLOOKUP(E60,'Field Definitions'!$A$1:$S$31597,3),"") -> ARACCOUNT | E60: FSACAPPLCRSCORE | I60: =IFERROR(VLOOKUP(E60,'Field Definitions'!$A$1:$S$31597,2),"") -> Credit Score At Application | M60: =IFERROR(VLOOKUP($E60,'Field Definitions'!$A$1:$S$31597,4),"") -> NUMBER | N60: =IFERROR(VLOOKUP($E60,'Field Definitions'!$A$1:$S$31597,5),"") -> 5 | Q60: 500 | R60: =IF(IFERROR(VLOOKUP($E60,'Field Definitions'!$A$1:$S$31597,8),"")=0,"",IFERROR(VLOOKUP($E60,'Field Definitions'!$A$1:$S$31597,8),"")) | S60: =IF(IFERROR(VLOOKUP($E60,'Field Definitions'!$A$1:$S$31597,9),"")=0,"",IFERROR(VLOOKUP($E60,'Field Definitions'!$A$1:$S$31597,9),"")) | T60: =IF(IFERROR(VLOOKUP($E60,'Field Definitions'!$A$1:$S$31597,10),"")=0,"",IFERROR(VLOOKUP($E60,'Field Definitions'!$A$1:$S$31597,10),"")) | U60: =IF(IFERROR(VLOOKUP($E60,'Field Definitions'!$A$1:$S$31597,12),"")=0,"",IFERROR(VLOOKUP($E60,'Field Definitions'!$A$1:$S$31597,12),"")) | Y60: =";ACCT^"&J60&"^"&M60&"^"&N60 -> ;ACCT^^NUMBER^5
C61: =IFERROR(VLOOKUP(E61,'Field Definitions'!$A$1:$S$31597,3),"") -> ARACCOUNT | E61: FSACPRSCORE | I61: =IFERROR(VLOOKUP(E61,'Field Definitions'!$A$1:$S$31597,2),"") -> Credit Score | M61: =IFERROR(VLOOKUP($E61,'Field Definitions'!$A$1:$S$31597,4),"") -> NUMBER | N61: =IFERROR(VLOOKUP($E61,'Field Definitions'!$A$1:$S$31597,5),"") -> 5 | Q61: 450 | R61: =IF(IFERROR(VLOOKUP($E61,'Field Definitions'!$A$1:$S$31597,8),"")=0,"",IFERROR(VLOOKUP($E61,'Field Definitions'!$A$1:$S$31597,8),"")) | S61: =IF(IFERROR(VLOOKUP($E61,'Field Definitions'!$A$1:$S$31597,9),"")=0,"",IFERROR(VLOOKUP($E61,'Field Definitions'!$A$1:$S$31597,9),"")) | T61: =IF(IFERROR(VLOOKUP($E61,'Field Definitions'!$A$1:$S$31597,10),"")=0,"",IFERROR(VLOOKUP($E61,'Field Definitions'!$A$1:$S$31597,10),"")) | U61: =IF(IFERROR(VLOOKUP($E61,'Field Definitions'!$A$1:$S$31597,12),"")=0,"",IFERROR(VLOOKUP($E61,'Field Definitions'!$A$1:$S$31597,12),"")) | Y61: =";ACCT^"&J61&"^"&M61&"^"&N61 -> ;ACCT^^NUMBER^5
C62: =IFERROR(VLOOKUP(E62,'Field Definitions'!$A$1:$S$31597,3),"") -> ARACCOUNT | E62: FSACMISCCRSCORE | I62: =IFERROR(VLOOKUP(E62,'Field Definitions'!$A$1:$S$31597,2),"") -> Bankruptcy Credit Score | M62: =IFERROR(VLOOKUP($E62,'Field Definitions'!$A$1:$S$31597,4),"") -> NUMBER | N62: =IFERROR(VLOOKUP($E62,'Field Definitions'!$A$1:$S$31597,5),"") -> 5 | Q62: 375 | R62: =IF(IFERROR(VLOOKUP($E62,'Field Definitions'!$A$1:$S$31597,8),"")=0,"",IFERROR(VLOOKUP($E62,'Field Definitions'!$A$1:$S$31597,8),"")) | S62: =IF(IFERROR(VLOOKUP($E62,'Field Definitions'!$A$1:$S$31597,9),"")=0,"",IFERROR(VLOOKUP($E62,'Field Definitions'!$A$1:$S$31597,9),"")) | T62: =IF(IFERROR(VLOOKUP($E62,'Field Definitions'!$A$1:$S$31597,10),"")=0,"",IFERROR(VLOOKUP($E62,'Field Definitions'!$A$1:$S$31597,10),"")) | U62: =IF(IFERROR(VLOOKUP($E62,'Field Definitions'!$A$1:$S$31597,12),"")=0,"",IFERROR(VLOOKUP($E62,'Field Definitions'!$A$1:$S$31597,12),"")) | Y62: =";ACCT^"&J62&"^"&M62&"^"&N62 -> ;ACCT^^NUMBER^5
C63: =IFERROR(VLOOKUP(E63,'Field Definitions'!$A$1:$S$31597,3),"") -> ARACCOUNT | E63: FSACPRRISKGRADE | I63: =IFERROR(VLOOKUP(E63,'Field Definitions'!$A$1:$S$31597,2),"") -> Risk Grade | M63: =IFERROR(VLOOKUP($E63,'Field Definitions'!$A$1:$S$31597,4),"") -> CHR | N63: =IFERROR(VLOOKUP($E63,'Field Definitions'!$A$1:$S$31597,5),"") -> 2 | Q63: 5 | R63: =IF(IFERROR(VLOOKUP($E63,'Field Definitions'!$A$1:$S$31597,8),"")=0,"",IFERROR(VLOOKUP($E63,'Field Definitions'!$A$1:$S$31597,8),"")) | S63: =IF(IFERROR(VLOOKUP($E63,'Field Definitions'!$A$1:$S$31597,9),"")=0,"",IFERROR(VLOOKUP($E63,'Field Definitions'!$A$1:$S$31597,9),"")) | T63: =IF(IFERROR(VLOOKUP($E63,'Field Definitions'!$A$1:$S$31597,10),"")=0,"",IFERROR(VLOOKUP($E63,'Field Definitions'!$A$1:$S$31597,10),"")) | U63: =IF(IFERROR(VLOOKUP($E63,'Field Definitions'!$A$1:$S$31597,12),"")=0,"",IFERROR(VLOOKUP($E63,'Field Definitions'!$A$1:$S$31597,12),"")) | Y63: =";ACCT^"&J63&"^"&M63&"^"&N63 -> ;ACCT^^CHR^2
C64: =IFERROR(VLOOKUP(E64,'Field Definitions'!$A$1:$S$31597,3),"") -> ARACCOUNT | E64: ARACSTATUTETYPEID | F64: MVP | H64: Statute of Limitations | I64: =IFERROR(VLOOKUP(E64,'Field Definitions'!$A$1:$S$31597,2),"") -> Statute agreement type ID | J64: 31 | M64: =IFERROR(VLOOKUP($E64,'Field Definitions'!$A$1:$S$31597,4),"") -> CHR | N64: =IFERROR(VLOOKUP($E64,'Field Definitions'!$A$1:$S$31597,5),"") -> 20 | Q64: JUDGMENT | R64: =IF(IFERROR(VLOOKUP($E64,'Field Definitions'!$A$1:$S$31597,8),"")=0,"",IFERROR(VLOOKUP($E64,'Field Definitions'!$A$1:$S$31597,8),"")) | S64: =IF(IFERROR(VLOOKUP($E64,'Field Definitions'!$A$1:$S$31597,9),"")=0,"",IFERROR(VLOOKUP($E64,'Field Definitions'!$A$1:$S$31597,9),"")) | T64: =IF(IFERROR(VLOOKUP($E64,'Field Definitions'!$A$1:$S$31597,10),"")=0,"",IFERROR(VLOOKUP($E64,'Field Definitions'!$A$1:$S$31597,10),"")) -> ARSTATUTETYPE | U64: =IF(IFERROR(VLOOKUP($E64,'Field Definitions'!$A$1:$S$31597,12),"")=0,"",IFERROR(VLOOKUP($E64,'Field Definitions'!$A$1:$S$31597,12),"")) | Y64: =";ACCT^"&J64&"^"&M64&"^"&N64 -> ;ACCT^31^CHR^20
C65: =IFERROR(VLOOKUP(E65,'Field Definitions'!$A$1:$S$31597,3),"") -> ARACCOUNT | E65: ARACSTATUTESTATEID | F65: MVP | I65: =IFERROR(VLOOKUP(E65,'Field Definitions'!$A$1:$S$31597,2),"") -> Statute of limitation state ID | J65: 32 | M65: =IFERROR(VLOOKUP($E65,'Field Definitions'!$A$1:$S$31597,4),"") -> CHR | N65: =IFERROR(VLOOKUP($E65,'Field Definitions'!$A$1:$S$31597,5),"") -> 2 | Q65: IN | R65: =IF(IFERROR(VLOOKUP($E65,'Field Definitions'!$A$1:$S$31597,8),"")=0,"",IFERROR(VLOOKUP($E65,'Field Definitions'!$A$1:$S$31597,8),"")) | S65: =IF(IFERROR(VLOOKUP($E65,'Field Definitions'!$A$1:$S$31597,9),"")=0,"",IFERROR(VLOOKUP($E65,'Field Definitions'!$A$1:$S$31597,9),"")) | T65: =IF(IFERROR(VLOOKUP($E65,'Field Definitions'!$A$1:$S$31597,10),"")=0,"",IFERROR(VLOOKUP($E65,'Field Definitions'!$A$1:$S$31597,10),"")) -> STATES | U65: =IF(IFERROR(VLOOKUP($E65,'Field Definitions'!$A$1:$S$31597,12),"")=0,"",IFERROR(VLOOKUP($E65,'Field Definitions'!$A$1:$S$31597,12),"")) | Y65: =";ACCT^"&J65&"^"&M65&"^"&N65 -> ;ACCT^32^CHR^2
C66: =IFERROR(VLOOKUP(E66,'Field Definitions'!$A$1:$S$31597,3),"") -> ARACCOUNT | E66: ARACSTATUTEEXPDTE | F66: MVP | I66: =IFERROR(VLOOKUP(E66,'Field Definitions'!$A$1:$S$31597,2),"") -> Statute expiration date | J66: 33 | M66: =IFERROR(VLOOKUP($E66,'Field Definitions'!$A$1:$S$31597,4),"") -> DATE | N66: =IFERROR(VLOOKUP($E66,'Field Definitions'!$A$1:$S$31597,5),"") -> 10 | Q66: 01/01/2014 | R66: =IF(IFERROR(VLOOKUP($E66,'Field Definitions'!$A$1:$S$31597,8),"")=0,"",IFERROR(VLOOKUP($E66,'Field Definitions'!$A$1:$S$31597,8),"")) | S66: =IF(IFERROR(VLOOKUP($E66,'Field Definitions'!$A$1:$S$31597,9),"")=0,"",IFERROR(VLOOKUP($E66,'Field Definitions'!$A$1:$S$31597,9),"")) | T66: =IF(IFERROR(VLOOKUP($E66,'Field Definitions'!$A$1:$S$31597,10),"")=0,"",IFERROR(VLOOKUP($E66,'Field Definitions'!$A$1:$S$31597,10),"")) | U66: =IF(IFERROR(VLOOKUP($E66,'Field Definitions'!$A$1:$S$31597,12),"")=0,"",IFERROR(VLOOKUP($E66,'Field Definitions'!$A$1:$S$31597,12),"")) | Y66: =";ACCT^"&J66&"^"&M66&"^"&N66 -> ;ACCT^33^DATE^10
C67: =IFERROR(VLOOKUP(E67,'Field Definitions'!$A$1:$S$31597,3),"") -> ARACCOUNT | E67: ARACSTATUTEBASEDTE | F67: MVP | I67: Delinquency Date | J67: 34 | M67: =IFERROR(VLOOKUP($E67,'Field Definitions'!$A$1:$S$31597,4),"") -> DATE | N67: =IFERROR(VLOOKUP($E67,'Field Definitions'!$A$1:$S$31597,5),"") -> 10 | Q67: 01/01/2013 | R67: =IF(IFERROR(VLOOKUP($E67,'Field Definitions'!$A$1:$S$31597,8),"")=0,"",IFERROR(VLOOKUP($E67,'Field Definitions'!$A$1:$S$31597,8),"")) | S67: =IF(IFERROR(VLOOKUP($E67,'Field Definitions'!$A$1:$S$31597,9),"")=0,"",IFERROR(VLOOKUP($E67,'Field Definitions'!$A$1:$S$31597,9),"")) | T67: =IF(IFERROR(VLOOKUP($E67,'Field Definitions'!$A$1:$S$31597,10),"")=0,"",IFERROR(VLOOKUP($E67,'Field Definitions'!$A$1:$S$31597,10),"")) | U67: =IF(IFERROR(VLOOKUP($E67,'Field Definitions'!$A$1:$S$31597,12),"")=0,"",IFERROR(VLOOKUP($E67,'Field Definitions'!$A$1:$S$31597,12),"")) | Y67: =";ACCT^"&J67&"^"&M67&"^"&N67 -> ;ACCT^34^DATE^10
C68: =IFERROR(VLOOKUP(E68,'Field Definitions'!$A$1:$S$31597,3),"") -> ARACCOUNT | E68: ARACSTATUTEBASEFLD | F68: MVP | I68: =IFERROR(VLOOKUP(E68,'Field Definitions'!$A$1:$S$31597,2),"") -> Statute base date field name | J68: 35 | L68: Values: Account Last Payment Date, Delinquency Date, Consumer Validated | M68: =IFERROR(VLOOKUP($E68,'Field Definitions'!$A$1:$S$31597,4),"") -> CHR | N68: =IFERROR(VLOOKUP($E68,'Field Definitions'!$A$1:$S$31597,5),"") -> 25 | Q68: ARACSRVDTE | R68: =IF(IFERROR(VLOOKUP($E68,'Field Definitions'!$A$1:$S$31597,8),"")=0,"",IFERROR(VLOOKUP($E68,'Field Definitions'!$A$1:$S$31597,8),"")) | S68: =IF(IFERROR(VLOOKUP($E68,'Field Definitions'!$A$1:$S$31597,9),"")=0,"",IFERROR(VLOOKUP($E68,'Field Definitions'!$A$1:$S$31597,9),"")) | T68: =IF(IFERROR(VLOOKUP($E68,'Field Definitions'!$A$1:$S$31597,10),"")=0,"",IFERROR(VLOOKUP($E68,'Field Definitions'!$A$1:$S$31597,10),"")) | U68: ARACLSTDTE|Listed Date|~ARACSRVDTE|Service Date|~ARACDELQDTE|Delinquency Date|~ARACCRDOPNDTE|Open Date|~ARRELPHSDTE|Relationship phse chg date| | Y68: =";ACCT^"&J68&"^"&M68&"^"&N68 -> ;ACCT^35^CHR^25
C69: =IFERROR(VLOOKUP(E69,'Field Definitions'!$A$1:$S$31597,3),"") -> ARACCOUNT | E69: ARACTYP | F69: GA | H69: Debt Buyer | I69: =IFERROR(VLOOKUP(E69,'Field Definitions'!$A$1:$S$31597,2),"") -> Account Type | M69: =IFERROR(VLOOKUP($E69,'Field Definitions'!$A$1:$S$31597,4),"") -> CHR | N69: =IFERROR(VLOOKUP($E69,'Field Definitions'!$A$1:$S$31597,5),"") -> 20 | Q69: PURCHASED | R69: =IF(IFERROR(VLOOKUP($E69,'Field Definitions'!$A$1:$S$31597,8),"")=0,"",IFERROR(VLOOKUP($E69,'Field Definitions'!$A$1:$S$31597,8),"")) | S69: =IF(IFERROR(VLOOKUP($E69,'Field Definitions'!$A$1:$S$31597,9),"")=0,"",IFERROR(VLOOKUP($E69,'Field Definitions'!$A$1:$S$31597,9),"")) | T69: =IF(IFERROR(VLOOKUP($E69,'Field Definitions'!$A$1:$S$31597,10),"")=0,"",IFERROR(VLOOKUP($E69,'Field Definitions'!$A$1:$S$31597,10),"")) -> ARACCTTYPE | U69: =IF(IFERROR(VLOOKUP($E69,'Field Definitions'!$A$1:$S$31597,12),"")=0,"",IFERROR(VLOOKUP($E69,'Field Definitions'!$A$1:$S$31597,12),""))
C70: =IFERROR(VLOOKUP(E70,'Field Definitions'!$A$1:$S$31597,3),"") -> ARACCOUNT | E70: ARACCOLTYP | I70: =IFERROR(VLOOKUP(E70,'Field Definitions'!$A$1:$S$31597,2),"") -> Collection Type | M70: =IFERROR(VLOOKUP($E70,'Field Definitions'!$A$1:$S$31597,4),"") -> CHR | N70: =IFERROR(VLOOKUP($E70,'Field Definitions'!$A$1:$S$31597,5),"") -> 20 | Q70: INSTALLMENT | R70: =IF(IFERROR(VLOOKUP($E70,'Field Definitions'!$A$1:$S$31597,8),"")=0,"",IFERROR(VLOOKUP($E70,'Field Definitions'!$A$1:$S$31597,8),"")) | S70: =IF(IFERROR(VLOOKUP($E70,'Field Definitions'!$A$1:$S$31597,9),"")=0,"",IFERROR(VLOOKUP($E70,'Field Definitions'!$A$1:$S$31597,9),"")) | T70: =IF(IFERROR(VLOOKUP($E70,'Field Definitions'!$A$1:$S$31597,10),"")=0,"",IFERROR(VLOOKUP($E70,'Field Definitions'!$A$1:$S$31597,10),"")) -> ARACCOLLTYPE | U70: =IF(IFERROR(VLOOKUP($E70,'Field Definitions'!$A$1:$S$31597,12),"")=0,"",IFERROR(VLOOKUP($E70,'Field Definitions'!$A$1:$S$31597,12),""))
C71: =IFERROR(VLOOKUP(E71,'Field Definitions'!$A$1:$S$31597,3),"") -> ARACCOUNT | E71: ALACCLCRID | I71: =IFERROR(VLOOKUP(E71,'Field Definitions'!$A$1:$S$31597,2),"") -> Creditor ID | L71: Send the creditor name and the system will find the Id or create a new entry in the ALCREDITOR table | M71: CHR | N71: 100 | Q71: Creditor Inc | R71: =IF(IFERROR(VLOOKUP($E71,'Field Definitions'!$A$1:$S$31597,8),"")=0,"",IFERROR(VLOOKUP($E71,'Field Definitions'!$A$1:$S$31597,8),"")) | S71: =IF(IFERROR(VLOOKUP($E71,'Field Definitions'!$A$1:$S$31597,9),"")=0,"",IFERROR(VLOOKUP($E71,'Field Definitions'!$A$1:$S$31597,9),"")) | T71: =IF(IFERROR(VLOOKUP($E71,'Field Definitions'!$A$1:$S$31597,10),"")=0,"",IFERROR(VLOOKUP($E71,'Field Definitions'!$A$1:$S$31597,10),"")) -> ALCREDITOR | U71: =IF(IFERROR(VLOOKUP($E71,'Field Definitions'!$A$1:$S$31597,12),"")=0,"",IFERROR(VLOOKUP($E71,'Field Definitions'!$A$1:$S$31597,12),""))
C72: =IFERROR(VLOOKUP(E72,'Field Definitions'!$A$1:$S$31597,3),"") -> ARACCOUNT | E72: ARACCLCRINT | I72: =IFERROR(VLOOKUP(E72,'Field Definitions'!$A$1:$S$31597,2),"") -> Creditor Interest Rate | M72: =IFERROR(VLOOKUP($E72,'Field Definitions'!$A$1:$S$31597,4),"") -> AMT | N72: =IFERROR(VLOOKUP($E72,'Field Definitions'!$A$1:$S$31597,5),"") -> 7 | Q72: 13 | R72: =IF(IFERROR(VLOOKUP($E72,'Field Definitions'!$A$1:$S$31597,8),"")=0,"",IFERROR(VLOOKUP($E72,'Field Definitions'!$A$1:$S$31597,8),"")) | S72: =IF(IFERROR(VLOOKUP($E72,'Field Definitions'!$A$1:$S$31597,9),"")=0,"",IFERROR(VLOOKUP($E72,'Field Definitions'!$A$1:$S$31597,9),"")) -> 100 | T72: =IF(IFERROR(VLOOKUP($E72,'Field Definitions'!$A$1:$S$31597,10),"")=0,"",IFERROR(VLOOKUP($E72,'Field Definitions'!$A$1:$S$31597,10),"")) | U72: =IF(IFERROR(VLOOKUP($E72,'Field Definitions'!$A$1:$S$31597,12),"")=0,"",IFERROR(VLOOKUP($E72,'Field Definitions'!$A$1:$S$31597,12),""))
C73: =IFERROR(VLOOKUP(E73,'Field Definitions'!$A$1:$S$31597,3),"") -> ARACCOUNT | E73: ARACCLCRLPYPDTE | I73: =IFERROR(VLOOKUP(E73,'Field Definitions'!$A$1:$S$31597,2),"") -> Creditor Last Payment Date | M73: =IFERROR(VLOOKUP($E73,'Field Definitions'!$A$1:$S$31597,4),"") -> DATE | N73: =IFERROR(VLOOKUP($E73,'Field Definitions'!$A$1:$S$31597,5),"") -> 10 | Q73: 06/13/2012 | R73: =IF(IFERROR(VLOOKUP($E73,'Field Definitions'!$A$1:$S$31597,8),"")=0,"",IFERROR(VLOOKUP($E73,'Field Definitions'!$A$1:$S$31597,8),"")) | S73: =IF(IFERROR(VLOOKUP($E73,'Field Definitions'!$A$1:$S$31597,9),"")=0,"",IFERROR(VLOOKUP($E73,'Field Definitions'!$A$1:$S$31597,9),"")) | T73: =IF(IFERROR(VLOOKUP($E73,'Field Definitions'!$A$1:$S$31597,10),"")=0,"",IFERROR(VLOOKUP($E73,'Field Definitions'!$A$1:$S$31597,10),"")) | U73: =IF(IFERROR(VLOOKUP($E73,'Field Definitions'!$A$1:$S$31597,12),"")=0,"",IFERROR(VLOOKUP($E73,'Field Definitions'!$A$1:$S$31597,12),""))
C74: =IFERROR(VLOOKUP(E74,'Field Definitions'!$A$1:$S$31597,3),"") -> ARACCOUNT | E74: ARACCLCRLPYAMT | I74: =IFERROR(VLOOKUP(E74,'Field Definitions'!$A$1:$S$31597,2),"") -> Creditor Last Payment Amount | M74: =IFERROR(VLOOKUP($E74,'Field Definitions'!$A$1:$S$31597,4),"") -> AMT | N74: =IFERROR(VLOOKUP($E74,'Field Definitions'!$A$1:$S$31597,5),"") -> 12 | Q74: 100.01 | R74: =IF(IFERROR(VLOOKUP($E74,'Field Definitions'!$A$1:$S$31597,8),"")=0,"",IFERROR(VLOOKUP($E74,'Field Definitions'!$A$1:$S$31597,8),"")) | S74: =IF(IFERROR(VLOOKUP($E74,'Field Definitions'!$A$1:$S$31597,9),"")=0,"",IFERROR(VLOOKUP($E74,'Field Definitions'!$A$1:$S$31597,9),"")) | T74: =IF(IFERROR(VLOOKUP($E74,'Field Definitions'!$A$1:$S$31597,10),"")=0,"",IFERROR(VLOOKUP($E74,'Field Definitions'!$A$1:$S$31597,10),"")) | U74: =IF(IFERROR(VLOOKUP($E74,'Field Definitions'!$A$1:$S$31597,12),"")=0,"",IFERROR(VLOOKUP($E74,'Field Definitions'!$A$1:$S$31597,12),""))
C75: =IFERROR(VLOOKUP(E75,'Field Definitions'!$A$1:$S$31597,3),"") -> ARACCOUNT | E75: ARACORGCRDNUM | I75: =IFERROR(VLOOKUP(E75,'Field Definitions'!$A$1:$S$31597,2),"") -> Original Creditor Account Num | M75: =IFERROR(VLOOKUP($E75,'Field Definitions'!$A$1:$S$31597,4),"") -> CHR | N75: =IFERROR(VLOOKUP($E75,'Field Definitions'!$A$1:$S$31597,5),"") -> 30 | Q75: 2 | R75: =IF(IFERROR(VLOOKUP($E75,'Field Definitions'!$A$1:$S$31597,8),"")=0,"",IFERROR(VLOOKUP($E75,'Field Definitions'!$A$1:$S$31597,8),"")) | S75: =IF(IFERROR(VLOOKUP($E75,'Field Definitions'!$A$1:$S$31597,9),"")=0,"",IFERROR(VLOOKUP($E75,'Field Definitions'!$A$1:$S$31597,9),"")) | T75: =IF(IFERROR(VLOOKUP($E75,'Field Definitions'!$A$1:$S$31597,10),"")=0,"",IFERROR(VLOOKUP($E75,'Field Definitions'!$A$1:$S$31597,10),""))
C76: ARRELATIONSHIP | E76: ARRELSLACCTTYPE | F76: GA | H76: Student Loan | I76: =IFERROR(VLOOKUP(E76,'Field Definitions'!$A$1:$S$31597,2),"") -> SL Account Type | M76: =IFERROR(VLOOKUP($E76,'Field Definitions'!$A$1:$S$31597,4),"") -> CHR | N76: =IFERROR(VLOOKUP($E76,'Field Definitions'!$A$1:$S$31597,5),"") -> 5
C77: ARRELATIONSHIP | E77: ARRELSLCONTSTATUS | I77: =IFERROR(VLOOKUP(E77,'Field Definitions'!$A$1:$S$31597,2),"") -> SL Contact Status | M77: =IFERROR(VLOOKUP($E77,'Field Definitions'!$A$1:$S$31597,4),"") -> CHR | N77: =IFERROR(VLOOKUP($E77,'Field Definitions'!$A$1:$S$31597,5),"") -> 5
I78: Is disputed? | J78: 36 | L78: Values: Y, N | M78: CHR | N78: 1
I79: Last scrub date | J79: 37 | M79: DATE | N79: 10
I80: Last skip date | J80: 38 | M80: DATE | N80: 10
E81: IS_DISPUTED | F81: MVP | I81: IS_DISPUTED | J81: 36 | M81: CHR | N81: 1
E82: LASTSCRUBDTE | F82: MVP | I82: LASTSCRUBDTE | J82: 37 | M82: DATE | N82: 10
E83: LASTSKIPDTE | F83: MVP | I83: LASTSKIPDTE | J83: 38 | M83: DATE | N83: 10
E84: DISPUTE_REASON | F84: MVP | I84: DISPUTE_REASON | J84: 39 | M84: CHR | N84: 25
E85: DISPUTE_INVESTIGATOR | F85: MVP | I85: DISPUTE_INVESTIGATOR | J85: 40 | M85: CHR | N85: 25
E86: DISPUTE_STATUS | F86: MVP | I86: DISPUTE_STATUS | J86: 41 | M86: CHR | N86: 25
E87: LASTCONTACTDATE | F87: MVP | I87: Last Contact Date | J87: 42 | M87: DATE | N87: 10
I88: External_Status_Code | J88: 43 | M88: CHR | N88: 6
H92: Cancel Codes
H93: Code | I93: Description
H94: ATY | I94: Attorney
H95: BANK | I95: Bankruptcy
H96: CAD | I96: Cease and Desist
H97: CER | I97: Cost Exceeds Recovery
H98: COMPLAINT | I98: Valid Complaint
H99: DECEASED | I99: Deceased
H100: DISPUTED | I100: Valid Dispute
H101: DUP | I101: Duplicate Listing
H102: EXHAUSTED | I102: All Efforts Exhausted
H103: FRD | I103: Fraud
...

Sheet BAL
A1: Source | D1: SaaS mapping/ timeline | E1: =COUNTIF(D5:D77,"MVP")-COUNTIF(E5:E77,"MVP") -> 27 | G1: Destination
A2: FACS | B2: TCS | E2: In Account Import? | G2: Table | H2: Column | I2: Description | J2: Position | K2: Required? | L2: Instructions | M2: Data Type | N2: Length | O2: 11 | P2: Min | Q2: Max | R2: Foreign Table | S2: Validation
D3: MVP | I3: Rec ID = BAL | J3: 1 | K3: Yes
D4: MVP | I4: Account_ID | J4: 2 | K4: Yes
D5: MVP | F5: Listed at New Business | H5: PRN_InitialBalance | I5: Principal Initial Balance | J5: 3 | K5: Yes | M5: AMT | N5: 10 | O5: 2234.42
D6: MVP | H6: INT_InitialBalance | I6: Interest Initial Balance | J6: 4 | M6: AMT | N6: 10 | O6: 100.23
D7: MVP | H7: LI3_InitialBalance | I7: List 3 Balance Initial Balance | J7: 5 | M7: AMT | N7: 10 | O7: 7
D8: MVP | H8: LI4_InitialBalance | I8: List 4 Balance Initial Balance | J8: 6 | M8: AMT | N8: 10 | O8: 9
D9: MVP | H9: ATYLS_InitialBalance | I9: Attorney List for NB Initial Balance | J9: 7 | M9: AMT | N9: 10 | O9: 23
D10: MVP | H10: CCLIS_InitialBalance | I10: Court Cost list for NB Initial Balance | J10: 8 | M10: AMT | N10: 10 | O10: 19
D11: MVP | F11: Current Balance | H11: PRN_CurrentBalance | I11: Principal Current Balance | J11: 9 | K11: Yes | M11: AMT | N11: 10 | O11: 1001.32
D12: MVP | H12: INT_CurrentBalance | I12: Interest Current Balance | J12: 10 | M12: AMT | N12: 10 | O12: 142.42
D13: MVP | H13: LI3_CurrentBalance | I13: List 3 Balance Current Balance | J13: 11 | M13: AMT | N13: 10 | O13: 6
D14: MVP | H14: LI4_CurrentBalance | I14: List 4 Balance Current Balance | J14: 12 | M14: AMT | N14: 10 | O14: 8
D15: MVP | H15: ATYLS_CurrentBalance | I15: Attorney List for NB Current Balance | J15: 13 | M15: AMT | N15: 10 | O15: 22
D16: MVP | H16: CCLIS_CurrentBalance | I16: Court Cost list for NB Current Balance | J16: 14 | M16: AMT | N16: 10 | O16: 18
D17: MVP | H17: AIN_CurrentBalance | I17: Agency Interest Current Balance | J17: 15 | M17: AMT | N17: 10 | O17: 10
D18: MVP | H18: PJI_CurrentBalance | I18: Postjudgment Interest Current Balance | J18: 16 | M18: AMT | N18: 10 | O18: 12
D19: MVP | H19: CCAGY_CurrentBalance | I19: Court Costs expensed to agency Current Balance | J19: 17 | M19: AMT | N19: 10 | O19: 14
D20: MVP | H20: CCCLT_CurrentBalance | I20: Court Costs billed to client Current Balance | J20: 18 | M20: AMT | N20: 10 | O20: 16
D21: MVP | H21: ATY_CurrentBalance | I21: Attorney Fees Current Balance | J21: 19 | M21: AMT | N21: 10 | O21: 20
D22: MVP | H22: CKFEE_CurrentBalance | I22: Courtesy check fee Current Balance | J22: 20 | M22: AMT | N22: 10 | O22: 24
D23: MVP | H23: MS1_CurrentBalance | I23: Miscellaneous 1 Current Balance | J23: 21 | M23: AMT | N23: 10 | O23: 26
... D29: MVP | H29: REFRC_CurrentBalance | I29: Refund Recovery Current Balance | J29: 27 | M29: AMT | N29: 10 | O29: 38
D30: NA | F30: User Define Balances | H30: UD1_CurrentBalance | I30: User Defined 1 Current Balance | M30: AMT | N30: 10 | O30: 40
D31: NA | H31: UD1_InitialBalance | I31: User Defined 1 Initial Balance | M31: AMT | N31: 10 | O31: 41
D32: NA | H32: UD2_CurrentBalance | I32: User Defined 2 Current Balance | M32: AMT | N32: 10 | O32: 42
D33: NA | H33: UD2_InitialBalance | I33: User Defined 2 Initial Balance | M33: AMT | N33: 10 | O33: 43
D34: NA | H34: UD3_CurrentBalance | I34: User Defined 3 Current Balance | M34: AMT | N34: 10 | O34: 44
D35: NA | H35: UD3_InitialBalance | I35: User Defined 3 Initial Balance | M35: AMT | N35: 10 | O35: 45
D36: NA | H36: UD4_CurrentBalance | I36: User Defined 4 Current Balance | M36: AMT | N36: 10 | O36: 46
D37: NA | H37: UD4_InitialBalance | I37: User Defined 4 Initial Balance | M37: AMT | N37: 10 | O37: 47
D38: NA | H38: UD5_CurrentBalance | I38: User Defined 5 Current Balance | M38: AMT | N38: 10 | O38: 48
D39: NA | H39: UD5_InitialBalance | I39: User Defined 5 Initial Balance | M39: AMT | N39: 10 | O39: 49
D40: NA | H40: UD6_CurrentBalance | I40: User Defined 6 Current Balance | M40: AMT | N40: 10 | O40: 50
D41: MVP | H41: UD6_InitialBalance | I41: User Defined 6 Initial Balance | J41: 28 | M41: AMT | N41: 10 | O41: 51
D42: MVP | H42: UD7_CurrentBalance | I42: User Defined 7 Current Balance | J42: 29 | M42: AMT | N42: 10 | O42: 52
D43: NA | H43: UD7_InitialBalance | I43: User Defined 7 Initial Balance | M43: AMT | N43: 10 | O43: 53
D44: NA | H44: UD8_CurrentBalance | I44: User Defined 8 Current Balance | M44: AMT | N44: 10 | O44: 54
D45: NA | H45: UD8_InitialBalance | I45: User Defined 8 Initial Balance | M45: AMT | N45: 10 | O45: 55
D46: NA | H46: UD9_CurrentBalance | I46: User Defined 9 Current Balance | M46: AMT | N46: 10 | O46: 56
D47: NA | H47: UD9_InitialBalance | I47: User Defined 9 Initial Balance | M47: AMT | N47: 10 | O47: 57
M48: =IFERROR(VLOOKUP($H48,'Field Definitions'!$A$1:$S$31597,4),"") | N48: =IFERROR(VLOOKUP($H48,'Field Definitions'!$A$1:$S$31597,5),"") | P48: =IF(IFERROR(VLOOKUP($H48,'Field Definitions'!$A$1:$S$31597,8),"")=0,"",IFERROR(VLOOKUP($H48,'Field Definitions'!$A$1:$S$31597,8),"")) | Q48: =IF(IFERROR(VLOOKUP($H48,'Field Definitions'!$A$1:$S$31597,9),"")=0,"",IFERROR(VLOOKUP($H48,'Field Definitions'!$A$1:$S$31597,9),"")) | R48: =IF(IFERROR(VLOOKUP($H48,'Field Definitions'!$A$1:$S$31597,10),"")=0,"",IFERROR(VLOOKUP($H48,'Field Definitions'!$A$1:$S$31597,10),""))
M49: =IFERROR(VLOOKUP($H49,'Field Definitions'!$A$1:$S$31597,4),"") | N49: =IFERROR(VLOOKUP($H49,'Field Definitions'!$A$1:$S$31597,5),"") | P49: =IF(IFERROR(VLOOKUP($H49,'Field Definitions'!$A$1:$S$31597,8),"")=0,"",IFERROR(VLOOKUP($H49,'Field Definitions'!$A$1:$S$31597,8),"")) | Q49: =IF(IFERROR(VLOOKUP($H49,'Field Definitions'!$A$1:$S$31597,9),"")=0,"",IFERROR(VLOOKUP($H49,'Field Definitions'!$A$1:$S$31597,9),"")) | R49: =IF(IFERROR(VLOOKUP($H49,'Field Definitions'!$A$1:$S$31597,10),"")=0,"",IFERROR(VLOOKUP($H49,'Field Definitions'!$A$1:$S$31597,10),""))
M50: =IFERROR(VLOOKUP($H50,'Field Definitions'!$A$1:$S$31597,4),"") | N50: =IFERROR(VLOOKUP($H50,'Field Definitions'!$A$1:$S$31597,5),"") | P50: =IF(IFERROR(VLOOKUP($H50,'Field Definitions'!$A$1:$S$31597,8),"")=0,"",IFERROR(VLOOKUP($H50,'Field Definitions'!$A$1:$S$31597,8),"")) | Q50: =IF(IFERROR(VLOOKUP($H50,'Field Definitions'!$A$1:$S$31597,9),"")=0,"",IFERROR(VLOOKUP($H50,'Field Definitions'!$A$1:$S$31597,9),"")) | R50: =IF(IFERROR(VLOOKUP($H50,'Field Definitions'!$A$1:$S$31597,10),"")=0,"",IFERROR(VLOOKUP($H50,'Field Definitions'!$A$1:$S$31597,10),""))
M51: =IFERROR(VLOOKUP($H51,'Field Definitions'!$A$1:$S$31597,4),"") | N51: =IFERROR(VLOOKUP($H51,'Field Definitions'!$A$1:$S$31597,5),"") | P51: =IF(IFERROR(VLOOKUP($H51,'Field Definitions'!$A$1:$S$31597,8),"")=0,"",IFERROR(VLOOKUP($H51,'Field Definitions'!$A$1:$S$31597,8),"")) | Q51: =IF(IFERROR(VLOOKUP($H51,'Field Definitions'!$A$1:$S$31597,9),"")=0,"",IFERROR(VLOOKUP($H51,'Field Definitions'!$A$1:$S$31597,9),"")) | R51: =IF(IFERROR(VLOOKUP($H51,'Field Definitions'!$A$1:$S$31597,10),"")=0,"",IFERROR(VLOOKUP($H51,'Field Definitions'!$A$1:$S$31597,10),""))
M52: =IFERROR(VLOOKUP($H52,'Field Definitions'!$A$1:$S$31597,4),"") | N52: =IFERROR(VLOOKUP($H52,'Field Definitions'!$A$1:$S$31597,5),"") | P52: =IF(IFERROR(VLOOKUP($H52,'Field Definitions'!$A$1:$S$31597,8),"")=0,"",IFERROR(VLOOKUP($H52,'Field Definitions'!$A$1:$S$31597,8),"")) | Q52: =IF(IFERROR(VLOOKUP($H52,'Field Definitions'!$A$1:$S$31597,9),"")=0,"",IFERROR(VLOOKUP($H52,'Field Definitions'!$A$1:$S$31597,9),"")) | R52: =IF(IFERROR(VLOOKUP($H52,'Field Definitions'!$A$1:$S$31597,10),"")=0,"",IFERROR(VLOOKUP($H52,'Field Definitions'!$A$1:$S$31597,10),""))
M53: =IFERROR(VLOOKUP($H53,'Field Definitions'!$A$1:$S$31597,4),"") | N53: =IFERROR(VLOOKUP($H53,'Field Definitions'!$A$1:$S$31597,5),"") | P53: =IF(IFERROR(VLOOKUP($H53,'Field Definitions'!$A$1:$S$31597,8),"")=0,"",IFERROR(VLOOKUP($H53,'Field Definitions'!$A$1:$S$31597,8),"")) | Q53: =IF(IFERROR(VLOOKUP($H53,'Field Definitions'!$A$1:$S$31597,9),"")=0,"",IFERROR(VLOOKUP($H53,'Field Definitions'!$A$1:$S$31597,9),"")) | R53: =IF(IFERROR(VLOOKUP($H53,'Field Definitions'!$A$1:$S$31597,10),"")=0,"",IFERROR(VLOOKUP($H53,'Field Definitions'!$A$1:$S$31597,10),""))
M54: =IFERROR(VLOOKUP($H54,'Field Definitions'!$A$1:$S$31597,4),"") | N54: =IFERROR(VLOOKUP($H54,'Field Definitions'!$A$1:$S$31597,5),"") | P54: =IF(IFERROR(VLOOKUP($H54,'Field Definitions'!$A$1:$S$31597,8),"")=0,"",IFERROR(VLOOKUP($H54,'Field Definitions'!$A$1:$S$31597,8),"")) | Q54: =IF(IFERROR(VLOOKUP($H54,'Field Definitions'!$A$1:$S$31597,9),"")=0,"",IFERROR(VLOOKUP($H54,'Field Definitions'!$A$1:$S$31597,9),"")) | R54: =IF(IFERROR(VLOOKUP($H54,'Field Definitions'!$A$1:$S$31597,10),"")=0,"",IFERROR(VLOOKUP($H54,'Field Definitions'!$A$1:$S$31597,10),""))
M55: =IFERROR(VLOOKUP($H55,'Field Definitions'!$A$1:$S$31597,4),"") | N55: =IFERROR(VLOOKUP($H55,'Field Definitions'!$A$1:$S$31597,5),"") | P55: =IF(IFERROR(VLOOKUP($H55,'Field Definitions'!$A$1:$S$31597,8),"")=0,"",IFERROR(VLOOKUP($H55,'Field Definitions'!$A$1:$S$31597,8),"")) | Q55: =IF(IFERROR(VLOOKUP($H55,'Field Definitions'!$A$1:$S$31597,9),"")=0,"",IFERROR(VLOOKUP($H55,'Field Definitions'!$A$1:$S$31597,9),"")) | R55: =IF(IFERROR(VLOOKUP($H55,'Field Definitions'!$A$1:$S$31597,10),"")=0,"",IFERROR(VLOOKUP($H55,'Field Definitions'!$A$1:$S$31597,10),""))
M56: =IFERROR(VLOOKUP($H56,'Field Definitions'!$A$1:$S$31597,4),"") | N56: =IFERROR(VLOOKUP($H56,'Field Definitions'!$A$1:$S$31597,5),"") | P56: =IF(IFERROR(VLOOKUP($H56,'Field Definitions'!$A$1:$S$31597,8),"")=0,"",IFERROR(VLOOKUP($H56,'Field Definitions'!$A$1:$S$31597,8),"")) | Q56: =IF(IFERROR(VLOOKUP($H56,'Field Definitions'!$A$1:$S$31597,9),"")=0,"",IFERROR(VLOOKUP($H56,'Field Definitions'!$A$1:$S$31597,9),"")) | R56: =IF(IFERROR(VLOOKUP($H56,'Field Definitions'!$A$1:$S$31597,10),"")=0,"",IFERROR(VLOOKUP($H56,'Field Definitions'!$A$1:$S$31597,10),""))
M57: =IFERROR(VLOOKUP($H57,'Field Definitions'!$A$1:$S$31597,4),"") | N57: =IFERROR(VLOOKUP($H57,'Field Definitions'!$A$1:$S$31597,5),"") | P57: =IF(IFERROR(VLOOKUP($H57,'Field Definitions'!$A$1:$S$31597,8),"")=0,"",IFERROR(VLOOKUP($H57,'Field Definitions'!$A$1:$S$31597,8),"")) | Q57: =IF(IFERROR(VLOOKUP($H57,'Field Definitions'!$A$1:$S$31597,9),"")=0,"",IFERROR(VLOOKUP($H57,'Field Definitions'!$A$1:$S$31597,9),"")) | R57: =IF(IFERROR(VLOOKUP($H57,'Field Definitions'!$A$1:$S$31597,10),"")=0,"",IFERROR(VLOOKUP($H57,'Field Definitions'!$A$1:$S$31597,10),""))
M58: =IFERROR(VLOOKUP($H58,'Field Definitions'!$A$1:$S$31597,4),"") | N58: =IFERROR(VLOOKUP($H58,'Field Definitions'!$A$1:$S$31597,5),"") | P58: =IF(IFERROR(VLOOKUP($H58,'Field Definitions'!$A$1:$S$31597,8),"")=0,"",IFERROR(VLOOKUP($H58,'Field Definitions'!$A$1:$S$31597,8),"")) | Q58: =IF(IFERROR(VLOOKUP($H58,'Field Definitions'!$A$1:$S$31597,9),"")=0,"",IFERROR(VLOOKUP($H58,'Field Definitions'!$A$1:$S$31597,9),"")) | R58: =IF(IFERROR(VLOOKUP($H58,'Field Definitions'!$A$1:$S$31597,10),"")=0,"",IFERROR(VLOOKUP($H58,'Field Definitions'!$A$1:$S$31597,10),""))

Sheet PRTY
A1: Source | D1: SaaS mapping/ timeline | E1: =COUNTIF(D6:D79,"MVP")-COUNTIF(E6:E79,"MVP") -> 0 | G1: Destination
A2: FACS | B2: TCS | G2: Table | H2: Column | I2: Description | J2: Position | K2: Required? | L2: Instructions | M2: Data Type | N2: Length | O2: 20 | P2: 20 | Q2: 20 | R2: Min | S2: Max | T2: Foreign Table | U2: Validation
D3: MVP | E3: MVP | I3: Rec ID = PRTY | J3: 1 | K3: Yes
A4: DBACCT | D4: MVP | E4: MVP | G4: ARACCOUNT | H4: ARACID | I4: Account_ID | J4: 2 | K4: Yes
A5: DBCLNT_"PSC" | D5: MVP | E5: MVP | I5: Consumer_ID | J5: 3 | K5: Yes | L5: Values: P, SE, S, C, G, PA, PR, D, E, N, A
D6: MVP | E6: MVP | F6: Core | G6: =IFERROR(VLOOKUP(H6,'Field Definitions'!$A$1:$S$31597,3),"") -> ARRELATIONSHIP | H6: ARRELTYPID | I6: =IFERROR(VLOOKUP(H6,'Field Definitions'!$A$1:$S$31597,2),"") -> Relationship type key | J6: 4 | K6: Yes | L6: Should have at least 1 record with Primary. For multiple co-makers use CoMaker_1, CoMaker_2, etc. See values below | M6: =IFERROR(VLOOKUP($H6,'Field Definitions'!$A$1:$S$31597,4),"") -> CHR | N6: =IFERROR(VLOOKUP($H6,'Field Definitions'!$A$1:$S$31597,5),"") -> 10 | O6: PRIM | P6: COMAK_1 | Q6: SPOUSE | R6: =IF(IFERROR(VLOOKUP($H6,'Field Definitions'!$A$1:$S$31597,8),"")=0,"",IFERROR(VLOOKUP($H6,'Field Definitions'!$A$1:$S$31597,8),"")) | S6: =IF(IFERROR(VLOOKUP($H6,'Field Definitions'!$A$1:$S$31597,9),"")=0,"",IFERROR(VLOOKUP($H6,'Field Definitions'!$A$1:$S$31597,9),"")) | T6: =IF(IFERROR(VLOOKUP($H6,'Field Definitions'!$A$1:$S$31597,10),"")=0,"",IFERROR(VLOOKUP($H6,'Field Definitions'!$A$1:$S$31597,10),"")) -> ARRELTYPE | U6: AUTH|Authorized User|~BUSINESS|Business|AR43360~COMAK|Comaker|AR13409~DEPEND|Dependent|AR13410~EXEC|Executor|AR43575~GUAR|Guarantor|AR43574~OWNER|Business Owner|AR43359~PRIM|Primary Responsible Party|AR13411~SPOUSE|Spouse|AR13412~ | X6: =";PRTY^"&J6&"^"&M6&"^"&N6 -> ;PRTY^4^CHR^10
D7: MVP | E7: MVP | G7: =IFERROR(VLOOKUP(H7,'Field Definitions'!$A$1:$S$31597,3),"") -> ARRELATIONSHIP | H7: ARRELRESP | I7: =IFERROR(VLOOKUP(H7,'Field Definitions'!$A$1:$S$31597,2),"") -> Responsible | J7: 5 | K7: Yes | L7: Values: Y, N | M7: =IFERROR(VLOOKUP($H7,'Field Definitions'!$A$1:$S$31597,4),"") -> CHR | N7: =IFERROR(VLOOKUP($H7,'Field Definitions'!$A$1:$S$31597,5),"") -> 1 | O7: Y | P7: Y | Q7: N | R7: =IF(IFERROR(VLOOKUP($H7,'Field Definitions'!$A$1:$S$31597,8),"")=0,"",IFERROR(VLOOKUP($H7,'Field Definitions'!$A$1:$S$31597,8),"")) | S7: =IF(IFERROR(VLOOKUP($H7,'Field Definitions'!$A$1:$S$31597,9),"")=0,"",IFERROR(VLOOKUP($H7,'Field Definitions'!$A$1:$S$31597,9),"")) | T7: =IF(IFERROR(VLOOKUP($H7,'Field Definitions'!$A$1:$S$31597,10),"")=0,"",IFERROR(VLOOKUP($H7,'Field Definitions'!$A$1:$S$31597,10),"")) | U7: =IF(IFERROR(VLOOKUP($H7,'Field Definitions'!$A$1:$S$31597,12),"")=0,"",IFERROR(VLOOKUP($H7,'Field Definitions'!$A$1:$S$31597,12),"")) -> Y|Yes|~N|No| | X7: =";PRTY^"&J7&"^"&M7&"^"&N7 -> ;PRTY^5^CHR^1
D8: MVP | E8: MVP | G8: =IFERROR(VLOOKUP(H8,'Field Definitions'!$A$1:$S$31597,3),"") -> ARENTITY | H8: ARENFNM | I8: =IFERROR(VLOOKUP(H8,'Field Definitions'!$A$1:$S$31597,2),"") -> First Name | J8: 6 | M8: =IFERROR(VLOOKUP($H8,'Field Definitions'!$A$1:$S$31597,4),"") -> CHR | N8: =IFERROR(VLOOKUP($H8,'Field Definitions'!$A$1:$S$31597,5),"") -> 40 | O8: First name | P8: Firstname | Q8: First name | R8: =IF(IFERROR(VLOOKUP($H8,'Field Definitions'!$A$1:$S$31597,8),"")=0,"",IFERROR(VLOOKUP($H8,'Field Definitions'!$A$1:$S$31597,8),"")) | S8: =IF(IFERROR(VLOOKUP($H8,'Field Definitions'!$A$1:$S$31597,9),"")=0,"",IFERROR(VLOOKUP($H8,'Field Definitions'!$A$1:$S$31597,9),"")) | T8: =IF(IFERROR(VLOOKUP($H8,'Field Definitions'!$A$1:$S$31597,10),"")=0,"",IFERROR(VLOOKUP($H8,'Field Definitions'!$A$1:$S$31597,10),"")) | U8: =IF(IFERROR(VLOOKUP($H8,'Field Definitions'!$A$1:$S$31597,12),"")=0,"",IFERROR(VLOOKUP($H8,'Field Definitions'!$A$1:$S$31597,12),"")) | X8: =";PRTY^"&J8&"^"&M8&"^"&N8 -> ;PRTY^6^CHR^40
D9: MVP | E9: MVP | G9: ARENTITY | H9: ARENMNM | I9: Middle Name | J9: 7 | M9: CHR | N9: 45 | P9: Y | X9: =";PRTY^"&J9&"^"&M9&"^"&N9 -> ;PRTY^7^CHR^45
D10: MVP | E10: MVP | G10: =IFERROR(VLOOKUP(H10,'Field Definitions'!$A$1:$S$31597,3),"") -> ARENTITY | H10: ARENLNM | I10: =IFERROR(VLOOKUP(H10,'Field Definitions'!$A$1:$S$31597,2),"") -> Last Name | J10: 8 | K10: Yes | M10: =IFERROR(VLOOKUP($H10,'Field Definitions'!$A$1:$S$31597,4),"") -> CHR | N10: =IFERROR(VLOOKUP($H10,'Field Definitions'!$A$1:$S$31597,5),"") -> 100 | O10: of Primary | P10: ofComak | Q10: of Spouse | R10: =IF(IFERROR(VLOOKUP($H10,'Field Definitions'!$A$1:$S$31597,8),"")=0,"",IFERROR(VLOOKUP($H10,'Field Definitions'!$A$1:$S$31597,8),"")) | S10: =IF(IFERROR(VLOOKUP($H10,'Field Definitions'!$A$1:$S$31597,9),"")=0,"",IFERROR(VLOOKUP($H10,'Field Definitions'!$A$1:$S$31597,9),"")) | T10: =IF(IFERROR(VLOOKUP($H10,'Field Definitions'!$A$1:$S$31597,10),"")=0,"",IFERROR(VLOOKUP($H10,'Field Definitions'!$A$1:$S$31597,10),"")) | U10: =IF(IFERROR(VLOOKUP($H10,'Field Definitions'!$A$1:$S$31597,12),"")=0,"",IFERROR(VLOOKUP($H10,'Field Definitions'!$A$1:$S$31597,12),"")) | X10: =";PRTY^"&J10&"^"&M10&"^"&N10 -> ;PRTY^8^CHR^100
D11: MVP | E11: MVP | G11: =IFERROR(VLOOKUP(H11,'Field Definitions'!$A$1:$S$31597,3),"") -> ARENTITY | H11: ARENADR | I11: =IFERROR(VLOOKUP(H11,'Field Definitions'!$A$1:$S$31597,2),"") -> Address Line | J11: 9 | M11: =IFERROR(VLOOKUP($H11,'Field Definitions'!$A$1:$S$31597,4),"") -> CHR | N11: 150 | O11: 123 Someplace St | P11: 123 Someplace St | Q11: 123 Someplace St | R11: =IF(IFERROR(VLOOKUP($H11,'Field Definitions'!$A$1:$S$31597,8),"")=0,"",IFERROR(VLOOKUP($H11,'Field Definitions'!$A$1:$S$31597,8),"")) | S11: =IF(IFERROR(VLOOKUP($H11,'Field Definitions'!$A$1:$S$31597,9),"")=0,"",IFERROR(VLOOKUP($H11,'Field Definitions'!$A$1:$S$31597,9),"")) | T11: =IF(IFERROR(VLOOKUP($H11,'Field Definitions'!$A$1:$S$31597,10),"")=0,"",IFERROR(VLOOKUP($H11,'Field Definitions'!$A$1:$S$31597,10),"")) | U11: =IF(IFERROR(VLOOKUP($H11,'Field Definitions'!$A$1:$S$31597,12),"")=0,"",IFERROR(VLOOKUP($H11,'Field Definitions'!$A$1:$S$31597,12),"")) | X11: =";PRTY^"&J11&"^"&M11&"^"&N11 -> ;PRTY^9^CHR^150
D12: MVP | E12: MVP | G12: =IFERROR(VLOOKUP(H12,'Field Definitions'!$A$1:$S$31597,3),"") -> ARENTITY | H12: ARENUNT | I12: =IFERROR(VLOOKUP(H12,'Field Definitions'!$A$1:$S$31597,2),"") -> Address Unit (Apt#, POBox #) | J12: 10 | M12: =IFERROR(VLOOKUP($H12,'Field Definitions'!$A$1:$S$31597,4),"") -> CHR | N12: 150 | O12: Apt 123 | P12: ,Apt 123 | Q12: Apt 123 | R12: =IF(IFERROR(VLOOKUP($H12,'Field Definitions'!$A$1:$S$31597,8),"")=0,"",IFERROR(VLOOKUP($H12,'Field Definitions'!$A$1:$S$31597,8),"")) | S12: =IF(IFERROR(VLOOKUP($H12,'Field Definitions'!$A$1:$S$31597,9),"")=0,"",IFERROR(VLOOKUP($H12,'Field Definitions'!$A$1:$S$31597,9),"")) | T12: =IF(IFERROR(VLOOKUP($H12,'Field Definitions'!$A$1:$S$31597,10),"")=0,"",IFERROR(VLOOKUP($H12,'Field Definitions'!$A$1:$S$31597,10),"")) | U12: =IF(IFERROR(VLOOKUP($H12,'Field Definitions'!$A$1:$S$31597,12),"")=0,"",IFERROR(VLOOKUP($H12,'Field Definitions'!$A$1:$S$31597,12),"")) | X12: =";PRTY^"&J12&"^"&M12&"^"&N12 -> ;PRTY^10^CHR^150
D13: MVP | E13: MVP | G13: =IFERROR(VLOOKUP(H13,'Field Definitions'!$A$1:$S$31597,3),"") -> ARENTITY | H13: ARENCTY | I13: =IFERROR(VLOOKUP(H13,'Field Definitions'!$A$1:$S$31597,2),"") -> City | J13: 11 | M13: =IFERROR(VLOOKUP($H13,'Field Definitions'!$A$1:$S$31597,4),"") -> CHR | N13: 50 | O13: Somecity | P13: Somecity | Q13: Somecity | R13: =IF(IFERROR(VLOOKUP($H13,'Field Definitions'!$A$1:$S$31597,8),"")=0,"",IFERROR(VLOOKUP($H13,'Field Definitions'!$A$1:$S$31597,8),"")) | S13: =IF(IFERROR(VLOOKUP($H13,'Field Definitions'!$A$1:$S$31597,9),"")=0,"",IFERROR(VLOOKUP($H13,'Field Definitions'!$A$1:$S$31597,9),"")) | T13: =IF(IFERROR(VLOOKUP($H13,'Field Definitions'!$A$1:$S$31597,10),"")=0,"",IFERROR(VLOOKUP($H13,'Field Definitions'!$A$1:$S$31597,10),"")) | U13: =IF(IFERROR(VLOOKUP($H13,'Field Definitions'!$A$1:$S$31597,12),"")=0,"",IFERROR(VLOOKUP($H13,'Field Definitions'!$A$1:$S$31597,12),"")) | X13: =";PRTY^"&J13&"^"&M13&"^"&N13 -> ;PRTY^11^CHR^50
D14: MVP | E14: MVP | G14: =IFERROR(VLOOKUP(H14,'Field Definitions'!$A$1:$S$31597,3),"") -> ARENTITY | H14: ARENST | I14: =IFERROR(VLOOKUP(H14,'Field Definitions'!$A$1:$S$31597,2),"") -> State | J14: 12 | M14: =IFERROR(VLOOKUP($H14,'Field Definitions'!$A$1:$S$31597,4),"") -> CHR | N14: =IFERROR(VLOOKUP($H14,'Field Definitions'!$A$1:$S$31597,5),"") -> 2 | O14: IN | P14: IN | Q14: IN | R14: =IF(IFERROR(VLOOKUP($H14,'Field Definitions'!$A$1:$S$31597,8),"")=0,"",IFERROR(VLOOKUP($H14,'Field Definitions'!$A$1:$S$31597,8),"")) | S14: =IF(IFERROR(VLOOKUP($H14,'Field Definitions'!$A$1:$S$31597,9),"")=0,"",IFERROR(VLOOKUP($H14,'Field Definitions'!$A$1:$S$31597,9),"")) | T14: =IF(IFERROR(VLOOKUP($H14,'Field Definitions'!$A$1:$S$31597,10),"")=0,"",IFERROR(VLOOKUP($H14,'Field Definitions'!$A$1:$S$31597,10),"")) -> STATES | U14: =IF(IFERROR(VLOOKUP($H14,'Field Definitions'!$A$1:$S$31597,12),"")=0,"",IFERROR(VLOOKUP($H14,'Field Definitions'!$A$1:$S$31597,12),"")) | X14: =";PRTY^"&J14&"^"&M14&"^"&N14 -> ;PRTY^12^CHR^2
D15: MVP | E15: MVP | G15: =IFERROR(VLOOKUP(H15,'Field Definitions'!$A$1:$S$31597,3),"") -> ARENTITY | H15: ARENZIP | I15: =IFERROR(VLOOKUP(H15,'Field Definitions'!$A$1:$S$31597,2),"") -> Postal Code | J15: 13 | M15: =IFERROR(VLOOKUP($H15,'Field Definitions'!$A$1:$S$31597,4),"") -> ZIP | N15: =IFERROR(VLOOKUP($H15,'Field Definitions'!$A$1:$S$31597,5),"") -> 10 | O15: 47304 | P15: 47304 | Q15: 47304 | R15: =IF(IFERROR(VLOOKUP($H15,'Field Definitions'!$A$1:$S$31597,8),"")=0,"",IFERROR(VLOOKUP($H15,'Field Definitions'!$A$1:$S$31597,8),"")) | S15: =IF(IFERROR(VLOOKUP($H15,'Field Definitions'!$A$1:$S$31597,9),"")=0,"",IFERROR(VLOOKUP($H15,'Field Definitions'!$A$1:$S$31597,9),"")) | T15: =IF(IFERROR(VLOOKUP($H15,'Field Definitions'!$A$1:$S$31597,10),"")=0,"",IFERROR(VLOOKUP($H15,'Field Definitions'!$A$1:$S$31597,10),"")) | U15: =IF(IFERROR(VLOOKUP($H15,'Field Definitions'!$A$1:$S$31597,12),"")=0,"",IFERROR(VLOOKUP($H15,'Field Definitions'!$A$1:$S$31597,12),"")) | X15: =";PRTY^"&J15&"^"&M15&"^"&N15 -> ;PRTY^13^ZIP^10
D16: MVP | E16: MVP | G16: =IFERROR(VLOOKUP(H16,'Field Definitions'!$A$1:$S$31597,3),"") -> ARENTITY | H16: ARENCNTY | I16: =IFERROR(VLOOKUP(H16,'Field Definitions'!$A$1:$S$31597,2),"") -> County | J16: 14 | M16: =IFERROR(VLOOKUP($H16,'Field Definitions'!$A$1:$S$31597,4),"") -> CHR | N16: =IFERROR(VLOOKUP($H16,'Field Definitions'!$A$1:$S$31597,5),"") -> 30 | O16: Delaware | P16: Delaware | Q16: Delaware | R16: =IF(IFERROR(VLOOKUP($H16,'Field Definitions'!$A$1:$S$31597,8),"")=0,"",IFERROR(VLOOKUP($H16,'Field Definitions'!$A$1:$S$31597,8),"")) | S16: =IF(IFERROR(VLOOKUP($H16,'Field Definitions'!$A$1:$S$31597,9),"")=0,"",IFERROR(VLOOKUP($H16,'Field Definitions'!$A$1:$S$31597,9),"")) | T16: =IF(IFERROR(VLOOKUP($H16,'Field Definitions'!$A$1:$S$31597,10),"")=0,"",IFERROR(VLOOKUP($H16,'Field Definitions'!$A$1:$S$31597,10),"")) | U16: =IF(IFERROR(VLOOKUP($H16,'Field Definitions'!$A$1:$S$31597,12),"")=0,"",IFERROR(VLOOKUP($H16,'Field Definitions'!$A$1:$S$31597,12),"")) | X16: =";PRTY^"&J16&"^"&M16&"^"&N16 -> ;PRTY^14^CHR^30
D17: MVP | E17: MVP | G17: =IFERROR(VLOOKUP(H17,'Field Definitions'!$A$1:$S$31597,3),"") -> ARENTITY | H17: ARENCNTRY | I17: =IFERROR(VLOOKUP(H17,'Field Definitions'!$A$1:$S$31597,2),"") -> Country | J17: 15 | M17: =IFERROR(VLOOKUP($H17,'Field Definitions'!$A$1:$S$31597,4),"") -> CHR | N17: =IFERROR(VLOOKUP($H17,'Field Definitions'!$A$1:$S$31597,5),"") -> 35 | O17: USA | P17: USA | Q17: USA | R17: =IF(IFERROR(VLOOKUP($H17,'Field Definitions'!$A$1:$S$31597,8),"")=0,"",IFERROR(VLOOKUP($H17,'Field Definitions'!$A$1:$S$31597,8),"")) | S17: =IF(IFERROR(VLOOKUP($H17,'Field Definitions'!$A$1:$S$31597,9),"")=0,"",IFERROR(VLOOKUP($H17,'Field Definitions'!$A$1:$S$31597,9),"")) | T17: =IF(IFERROR(VLOOKUP($H17,'Field Definitions'!$A$1:$S$31597,10),"")=0,"",IFERROR(VLOOKUP($H17,'Field Definitions'!$A$1:$S$31597,10),"")) | U17: =IF(IFERROR(VLOOKUP($H17,'Field Definitions'!$A$1:$S$31597,12),"")=0,"",IFERROR(VLOOKUP($H17,'Field Definitions'!$A$1:$S$31597,12),"")) | X17: =";PRTY^"&J17&"^"&M17&"^"&N17 -> ;PRTY^15^CHR^35
D18: MVP | E18: MVP | G18: =IFERROR(VLOOKUP(H18,'Field Definitions'!$A$1:$S$31597,3),"") -> ARENTITY | H18: ARENBTHDTE | I18: =IFERROR(VLOOKUP(H18,'Field Definitions'!$A$1:$S$31597,2),"") -> Date of Birth | J18: 16 | M18: =IFERROR(VLOOKUP($H18,'Field Definitions'!$A$1:$S$31597,4),"") -> DATE | N18: =IFERROR(VLOOKUP($H18,'Field Definitions'!$A$1:$S$31597,5),"") -> 10 | O18: 01/01/1990 | P18: 06/24/1993 | Q18: 06/24/1993 | R18: =IF(IFERROR(VLOOKUP($H18,'Field Definitions'!$A$1:$S$31597,8),"")=0,"",IFERROR(VLOOKUP($H18,'Field Definitions'!$A$1:$S$31597,8),"")) | S18: =IF(IFERROR(VLOOKUP($H18,'Field Definitions'!$A$1:$S$31597,9),"")=0,"",IFERROR(VLOOKUP($H18,'Field Definitions'!$A$1:$S$31597,9),"")) | T18: =IF(IFERROR(VLOOKUP($H18,'Field Definitions'!$A$1:$S$31597,10),"")=0,"",IFERROR(VLOOKUP($H18,'Field Definitions'!$A$1:$S$31597,10),"")) | U18: =IF(IFERROR(VLOOKUP($H18,'Field Definitions'!$A$1:$S$31597,12),"")=0,"",IFERROR(VLOOKUP($H18,'Field Definitions'!$A$1:$S$31597,12),"")) | X18: =";PRTY^"&J18&"^"&M18&"^"&N18 -> ;PRTY^16^DATE^10
D19: MVP | E19: MVP | G19: =IFERROR(VLOOKUP(H19,'Field Definitions'!$A$1:$S$31597,3),"") -> ARENTITY | H19: ARENPH | I19: =IFERROR(VLOOKUP(H19,'Field Definitions'!$A$1:$S$31597,2),"") -> Primary Phone # | J19: 17 | L19: Use only if UsePhoneable option not enabled. Else use record 21 | M19: =IFERROR(VLOOKUP($H19,'Field Definitions'!$A$1:$S$31597,4),"") -> PHONE | N19: 12 | O19: 7657517000 | P19: 7657517000 | Q19: 7657517000 | R19: =IF(IFERROR(VLOOKUP($H19,'Field Definitions'!$A$1:$S$31597,8),"")=0,"",IFERROR(VLOOKUP($H19,'Field Definitions'!$A$1:$S$31597,8),"")) | S19: =IF(IFERROR(VLOOKUP($H19,'Field Definitions'!$A$1:$S$31597,9),"")=0,"",IFERROR(VLOOKUP($H19,'Field Definitions'!$A$1:$S$31597,9),"")) | T19: =IF(IFERROR(VLOOKUP($H19,'Field Definitions'!$A$1:$S$31597,10),"")=0,"",IFERROR(VLOOKUP($H19,'Field Definitions'!$A$1:$S$31597,10),"")) | U19: =IF(IFERROR(VLOOKUP($H19,'Field Definitions'!$A$1:$S$31597,12),"")=0,"",IFERROR(VLOOKUP($H19,'Field Definitions'!$A$1:$S$31597,12),"")) | X19: =";PRTY^"&J19&"^"&M19&"^"&N19 -> ;PRTY^17^PHONE^12
D20: MVP | E20: MVP | G20: =IFERROR(VLOOKUP(H20,'Field Definitions'!$A$1:$S$31597,3),"") -> ARENTITY | H20: ARENPF | I20: =IFERROR(VLOOKUP(H20,'Field Definitions'!$A$1:$S$31597,2),"") -> Primary Phone Flag | J20: 18 | L20: Use only if UsePhoneable option not enabled. Else use record 21 | M20: =IFERROR(VLOOKUP($H20,'Field Definitions'!$A$1:$S$31597,4),"") -> CHR | N20: =IFERROR(VLOOKUP($H20,'Field Definitions'!$A$1:$S$31597,5),"") -> 1 | O20: G | P20: G | Q20: G | R20: =IF(IFERROR(VLOOKUP($H20,'Field Definitions'!$A$1:$S$31597,8),"")=0,"",IFERROR(VLOOKUP($H20,'Field Definitions'!$A$1:$S$31597,8),"")) | S20: =IF(IFERROR(VLOOKUP($H20,'Field Definitions'!$A$1:$S$31597,9),"")=0,"",IFERROR(VLOOKUP($H20,'Field Definitions'!$A$1:$S$31597,9),"")) | T20: =IF(IFERROR(VLOOKUP($H20,'Field Definitions'!$A$1:$S$31597,10),"")=0,"",IFERROR(VLOOKUP($H20,'Field Definitions'!$A$1:$S$31597,10),"")) | U20: =IF(IFERROR(VLOOKUP($H20,'Field Definitions'!$A$1:$S$31597,12),"")=0,"",IFERROR(VLOOKUP($H20,'Field Definitions'!$A$1:$S$31597,12),"")) | X20: =";PRTY^"&J20&"^"&M20&"^"&N20 -> ;PRTY^18^CHR^1
D21: MVP | E21: MVP | G21: =IFERROR(VLOOKUP(H21,'Field Definitions'!$A$1:$S$31597,3),"") -> ARENTITY | H21: ARENPH2 | I21: =IFERROR(VLOOKUP(H21,'Field Definitions'!$A$1:$S$31597,2),"") -> Alternate Phone | J21: 19 | L21: Use only if UsePhoneable option not enabled. Else use record 21 | M21: =IFERROR(VLOOKUP($H21,'Field Definitions'!$A$1:$S$31597,4),"") -> PHONE | N21: 12 | O21: 7657517100 | P21: 7657517100 | Q21: 7657517100 | R21: =IF(IFERROR(VLOOKUP($H21,'Field Definitions'!$A$1:$S$31597,8),"")=0,"",IFERROR(VLOOKUP($H21,'Field Definitions'!$A$1:$S$31597,8),"")) | S21: =IF(IFERROR(VLOOKUP($H21,'Field Definitions'!$A$1:$S$31597,9),"")=0,"",IFERROR(VLOOKUP($H21,'Field Definitions'!$A$1:$S$31597,9),"")) | T21: =IF(IFERROR(VLOOKUP($H21,'Field Definitions'!$A$1:$S$31597,10),"")=0,"",IFERROR(VLOOKUP($H21,'Field Definitions'!$A$1:$S$31597,10),"")) | U21: =IF(IFERROR(VLOOKUP($H21,'Field Definitions'!$A$1:$S$31597,12),"")=0,"",IFERROR(VLOOKUP($H21,'Field Definitions'!$A$1:$S$31597,12),"")) | X21: =";PRTY^"&J21&"^"&M21&"^"&N21 -> ;PRTY^19^PHONE^12
D22: MVP | E22: MVP | G22: =IFERROR(VLOOKUP(H22,'Field Definitions'!$A$1:$S$31597,3),"") -> ARENTITY | H22: ARENPF2 | I22: =IFERROR(VLOOKUP(H22,'Field Definitions'!$A$1:$S$31597,2),"") -> Alternate Phone Flag | J22: 20 | L22: Use only if UsePhoneable option not enabled. Else use record 21 | M22: =IFERROR(VLOOKUP($H22,'Field Definitions'!$A$1:$S$31597,4),"") -> CHR | N22: =IFERROR(VLOOKUP($H22,'Field Definitions'!$A$1:$S$31597,5),"") -> 1 | O22: G | P22: G | Q22: G | R22: =IF(IFERROR(VLOOKUP($H22,'Field Definitions'!$A$1:$S$31597,8),"")=0,"",IFERROR(VLOOKUP($H22,'Field Definitions'!$A$1:$S$31597,8),"")) | S22: =IF(IFERROR(VLOOKUP($H22,'Field Definitions'!$A$1:$S$31597,9),"")=0,"",IFERROR(VLOOKUP($H22,'Field Definitions'!$A$1:$S$31597,9),"")) | T22: =IF(IFERROR(VLOOKUP($H22,'Field Definitions'!$A$1:$S$31597,10),"")=0,"",IFERROR(VLOOKUP($H22,'Field Definitions'!$A$1:$S$31597,10),"")) | U22: =IF(IFERROR(VLOOKUP($H22,'Field Definitions'!$A$1:$S$31597,12),"")=0,"",IFERROR(VLOOKUP($H22,'Field Definitions'!$A$1:$S$31597,12),"")) | X22: =";PRTY^"&J22&"^"&M22&"^"&N22 -> ;PRTY^20^CHR^1
D23: MVP | E23: MVP | G23: =IFERROR(VLOOKUP(H23,'Field Definitions'!$A$1:$S$31597,3),"") -> ARENTITY | H23: ARENFAX | I23: =IFERROR(VLOOKUP(H23,'Field Definitions'!$A$1:$S$31597,2),"") -> FAX machine number | J23: 21 | M23: =IFERROR(VLOOKUP($H23,'Field Definitions'!$A$1:$S$31597,4),"") -> PHONE | N23: 12 | O23: 7657517199 | P23: 7657517199 | Q23: 7657517199 | R23: =IF(IFERROR(VLOOKUP($H23,'Field Definitions'!$A$1:$S$31597,8),"")=0,"",IFERROR(VLOOKUP($H23,'Field Definitions'!$A$1:$S$31597,8),"")) | S23: =IF(IFERROR(VLOOKUP($H23,'Field Definitions'!$A$1:$S$31597,9),"")=0,"",IFERROR(VLOOKUP($H23,'Field Definitions'!$A$1:$S$31597,9),"")) | T23: =IF(IFERROR(VLOOKUP($H23,'Field Definitions'!$A$1:$S$31597,10),"")=0,"",IFERROR(VLOOKUP($H23,'Field Definitions'!$A$1:$S$31597,10),"")) | U23: =IF(IFERROR(VLOOKUP($H23,'Field Definitions'!$A$1:$S$31597,12),"")=0,"",IFERROR(VLOOKUP($H23,'Field Definitions'!$A$1:$S$31597,12),"")) | X23: =";PRTY^"&J23&"^"&M23&"^"&N23 -> ;PRTY^21^PHONE^12
D24: MVP | E24: MVP | G24: =IFERROR(VLOOKUP(H24,'Field Definitions'!$A$1:$S$31597,3),"") -> ARENTITY | H24: ARENSSN | I24: =IFERROR(VLOOKUP(H24,'Field Definitions'!$A$1:$S$31597,2),"") -> Social Security Number | J24: 22 | M24: =IFERROR(VLOOKUP($H24,'Field Definitions'!$A$1:$S$31597,4),"") -> SSN | N24: 9 | O24: 123121234 | P24: 123125679 | Q24: 123125678 | R24: =IF(IFERROR(VLOOKUP($H24,'Field Definitions'!$A$1:$S$31597,8),"")=0,"",IFERROR(VLOOKUP($H24,'Field Definitions'!$A$1:$S$31597,8),"")) | S24: =IF(IFERROR(VLOOKUP($H24,'Field Definitions'!$A$1:$S$31597,9),"")=0,"",IFERROR(VLOOKUP($H24,'Field Definitions'!$A$1:$S$31597,9),"")) | T24: =IF(IFERROR(VLOOKUP($H24,'Field Definitions'!$A$1:$S$31597,10),"")=0,"",IFERROR(VLOOKUP($H24,'Field Definitions'!$A$1:$S$31597,10),"")) | U24: =IF(IFERROR(VLOOKUP($H24,'Field Definitions'!$A$1:$S$31597,12),"")=0,"",IFERROR(VLOOKUP($H24,'Field Definitions'!$A$1:$S$31597,12),"")) | X24: =";PRTY^"&J24&"^"&M24&"^"&N24 -> ;PRTY^22^SSN^9
D25: MVP | E25: MVP | G25: =IFERROR(VLOOKUP(H25,'Field Definitions'!$A$1:$S$31597,3),"") -> ARENTITY | H25: ARENGENDER | I25: =IFERROR(VLOOKUP(H25,'Field Definitions'!$A$1:$S$31597,2),"") -> Gender | J25: 23 | M25: =IFERROR(VLOOKUP($H25,'Field Definitions'!$A$1:$S$31597,4),"") -> CHR | N25: =IFERROR(VLOOKUP($H25,'Field Definitions'!$A$1:$S$31597,5),"") -> 1 | O25: M | P25: F | Q25: F | R25: =IF(IFERROR(VLOOKUP($H25,'Field Definitions'!$A$1:$S$31597,8),"")=0,"",IFERROR(VLOOKUP($H25,'Field Definitions'!$A$1:$S$31597,8),"")) | S25: =IF(IFERROR(VLOOKUP($H25,'Field Definitions'!$A$1:$S$31597,9),"")=0,"",IFERROR(VLOOKUP($H25,'Field Definitions'!$A$1:$S$31597,9),"")) | T25: =IF(IFERROR(VLOOKUP($H25,'Field Definitions'!$A$1:$S$31597,10),"")=0,"",IFERROR(VLOOKUP($H25,'Field Definitions'!$A$1:$S$31597,10),"")) | U25: =IF(IFERROR(VLOOKUP($H25,'Field Definitions'!$A$1:$S$31597,12),"")=0,"",IFERROR(VLOOKUP($H25,'Field Definitions'!$A$1:$S$31597,12),"")) -> M||~F||~U|| | X25: =";PRTY^"&J25&"^"&M25&"^"&N25 -> ;PRTY^23^CHR^1
D26: MVP | E26: MVP | G26: =IFERROR(VLOOKUP(H26,'Field Definitions'!$A$1:$S$31597,3),"") -> ARENTITY | H26: ARENMARITAL | I26: =IFERROR(VLOOKUP(H26,'Field Definitions'!$A$1:$S$31597,2),"") -> Marital Status | J26: 24 | M26: =IFERROR(VLOOKUP($H26,'Field Definitions'!$A$1:$S$31597,4),"") -> CHR | N26: =IFERROR(VLOOKUP($H26,'Field Definitions'!$A$1:$S$31597,5),"") -> 1 | O26: M | P26: M | Q26: M | R26: =IF(IFERROR(VLOOKUP($H26,'Field Definitions'!$A$1:$S$31597,8),"")=0,"",IFERROR(VLOOKUP($H26,'Field Definitions'!$A$1:$S$31597,8),"")) | S26: =IF(IFERROR(VLOOKUP($H26,'Field Definitions'!$A$1:$S$31597,9),"")=0,"",IFERROR(VLOOKUP($H26,'Field Definitions'!$A$1:$S$31597,9),"")) | T26: =IF(IFERROR(VLOOKUP($H26,'Field Definitions'!$A$1:$S$31597,10),"")=0,"",IFERROR(VLOOKUP($H26,'Field Definitions'!$A$1:$S$31597,10),"")) | U26: =IF(IFERROR(VLOOKUP($H26,'Field Definitions'!$A$1:$S$31597,12),"")=0,"",IFERROR(VLOOKUP($H26,'Field Definitions'!$A$1:$S$31597,12),"")) | X26: =";PRTY^"&J26&"^"&M26&"^"&N26 -> ;PRTY^24^CHR^1
D27: MVP | E27: MVP | G27: =IFERROR(VLOOKUP(H27,'Field Definitions'!$A$1:$S$31597,3),"") -> ARENTITY | H27: ARENDRVLIC | I27: =IFERROR(VLOOKUP(H27,'Field Definitions'!$A$1:$S$31597,2),"") -> Driver's License Number | J27: 25 | M27: =IFERROR(VLOOKUP($H27,'Field Definitions'!$A$1:$S$31597,4),"") -> CHR | N27: =IFERROR(VLOOKUP($H27,'Field Definitions'!$A$1:$S$31597,5),"") -> 20 | O27: IN123412342322 | P27: IN123412346790 | Q27: IN123412346789 | R27: =IF(IFERROR(VLOOKUP($H27,'Field Definitions'!$A$1:$S$31597,8),"")=0,"",IFERROR(VLOOKUP($H27,'Field Definitions'!$A$1:$S$31597,8),"")) | S27: =IF(IFERROR(VLOOKUP($H27,'Field Definitions'!$A$1:$S$31597,9),"")=0,"",IFERROR(VLOOKUP($H27,'Field Definitions'!$A$1:$S$31597,9),"")) | T27: =IF(IFERROR(VLOOKUP($H27,'Field Definitions'!$A$1:$S$31597,10),"")=0,"",IFERROR(VLOOKUP($H27,'Field Definitions'!$A$1:$S$31597,10),"")) | U27: =IF(IFERROR(VLOOKUP($H27,'Field Definitions'!$A$1:$S$31597,12),"")=0,"",IFERROR(VLOOKUP($H27,'Field Definitions'!$A$1:$S$31597,12),"")) | X27: =";PRTY^"&J27&"^"&M27&"^"&N27 -> ;PRTY^25^CHR^20
D28: MVP | E28: MVP | G28: =IFERROR(VLOOKUP(H28,'Field Definitions'!$A$1:$S$31597,3),"") -> ARENTITY | H28: ARENDRVLICST | I28: =IFERROR(VLOOKUP(H28,'Field Definitions'!$A$1:$S$31597,2),"") -> Driver's License State | J28: 26 | M28: =IFERROR(VLOOKUP($H28,'Field Definitions'!$A$1:$S$31597,4),"") -> CHR | N28: =IFERROR(VLOOKUP($H28,'Field Definitions'!$A$1:$S$31597,5),"") -> 2 | O28: IN | P28: IN | Q28: IN | R28: =IF(IFERROR(VLOOKUP($H28,'Field Definitions'!$A$1:$S$31597,8),"")=0,"",IFERROR(VLOOKUP($H28,'Field Definitions'!$A$1:$S$31597,8),"")) | S28: =IF(IFERROR(VLOOKUP($H28,'Field Definitions'!$A$1:$S$31597,9),"")=0,"",IFERROR(VLOOKUP($H28,'Field Definitions'!$A$1:$S$31597,9),"")) | T28: =IF(IFERROR(VLOOKUP($H28,'Field Definitions'!$A$1:$S$31597,10),"")=0,"",IFERROR(VLOOKUP($H28,'Field Definitions'!$A$1:$S$31597,10),"")) -> STATES | U28: =IF(IFERROR(VLOOKUP($H28,'Field Definitions'!$A$1:$S$31597,12),"")=0,"",IFERROR(VLOOKUP($H28,'Field Definitions'!$A$1:$S$31597,12),"")) | X28: =";PRTY^"&J28&"^"&M28&"^"&N28 -> ;PRTY^26^CHR^2
D29: MVP | E29: MVP | G29: =IFERROR(VLOOKUP(H29,'Field Definitions'!$A$1:$S$31597,3),"") -> ARENTITY | H29: ARENEMAIL | I29: =IFERROR(VLOOKUP(H29,'Field Definitions'!$A$1:$S$31597,2),"") -> Email Address | J29: 27 | L29: Don't use if placing email in EMAIL record | M29: =IFERROR(VLOOKUP($H29,'Field Definitions'!$A$1:$S$31597,4),"") -> CHR | N29: =IFERROR(VLOOKUP($H29,'Field Definitions'!$A$1:$S$31597,5),"") -> 40 | O29: primary@email.com | P29: comaker@email.com | Q29: spouse@email.com | R29: =IF(IFERROR(VLOOKUP($H29,'Field Definitions'!$A$1:$S$31597,8),"")=0,"",IFERROR(VLOOKUP($H29,'Field Definitions'!$A$1:$S$31597,8),"")) | S29: =IF(IFERROR(VLOOKUP($H29,'Field Definitions'!$A$1:$S$31597,9),"")=0,"",IFERROR(VLOOKUP($H29,'Field Definitions'!$A$1:$S$31597,9),"")) | T29: =IF(IFERROR(VLOOKUP($H29,'Field Definitions'!$A$1:$S$31597,10),"")=0,"",IFERROR(VLOOKUP($H29,'Field Definitions'!$A$1:$S$31597,10),"")) | U29: =IF(IFERROR(VLOOKUP($H29,'Field Definitions'!$A$1:$S$31597,12),"")=0,"",IFERROR(VLOOKUP($H29,'Field Definitions'!$A$1:$S$31597,12),"")) | X29: =";PRTY^"&J29&"^"&M29&"^"&N29 -> ;PRTY^27^CHR^40
D30: MVP | E30: MVP | G30: =IFERROR(VLOOKUP(H30,'Field Definitions'!$A$1:$S$31597,3),"") -> ARENTITY | H30: ARENDECDTE | I30: =IFERROR(VLOOKUP(H30,'Field Definitions'!$A$1:$S$31597,2),"") -> Date of Decease | J30: 28 | M30: =IFERROR(VLOOKUP($H30,'Field Definitions'!$A$1:$S$31597,4),"") -> DATE | N30: =IFERROR(VLOOKUP($H30,'Field Definitions'!$A$1:$S$31597,5),"") -> 10 | Q30: 01/01/2011 | R30: =IF(IFERROR(VLOOKUP($H30,'Field Definitions'!$A$1:$S$31597,8),"")=0,"",IFERROR(VLOOKUP($H30,'Field Definitions'!$A$1:$S$31597,8),"")) | S30: =IF(IFERROR(VLOOKUP($H30,'Field Definitions'!$A$1:$S$31597,9),"")=0,"",IFERROR(VLOOKUP($H30,'Field Definitions'!$A$1:$S$31597,9),"")) | T30: =IF(IFERROR(VLOOKUP($H30,'Field Definitions'!$A$1:$S$31597,10),"")=0,"",IFERROR(VLOOKUP($H30,'Field Definitions'!$A$1:$S$31597,10),"")) | U30: =IF(IFERROR(VLOOKUP($H30,'Field Definitions'!$A$1:$S$31597,12),"")=0,"",IFERROR(VLOOKUP($H30,'Field Definitions'!$A$1:$S$31597,12),"")) | X30: =";PRTY^"&J30&"^"&M30&"^"&N30 -> ;PRTY^28^DATE^10
D31: MVP | E31: MVP | G31: =IFERROR(VLOOKUP(H31,'Field Definitions'!$A$1:$S$31597,3),"") -> ARENTITY | H31: ARENDECEASED | I31: =IFERROR(VLOOKUP(H31,'Field Definitions'!$A$1:$S$31597,2),"") -> Deceased Flag | J31: 29 | M31: =IFERROR(VLOOKUP($H31,'Field Definitions'!$A$1:$S$31597,4),"") -> CHR | N31: =IFERROR(VLOOKUP($H31,'Field Definitions'!$A$1:$S$31597,5),"") -> 1 | O31: N | P31: N | Q31: Y | R31: =IF(IFERROR(VLOOKUP($H31,'Field Definitions'!$A$1:$S$31597,8),"")=0,"",IFERROR(VLOOKUP($H31,'Field Definitions'!$A$1:$S$31597,8),"")) | S31: =IF(IFERROR(VLOOKUP($H31,'Field Definitions'!$A$1:$S$31597,9),"")=0,"",IFERROR(VLOOKUP($H31,'Field Definitions'!$A$1:$S$31597,9),"")) | T31: =IF(IFERROR(VLOOKUP($H31,'Field Definitions'!$A$1:$S$31597,10),"")=0,"",IFERROR(VLOOKUP($H31,'Field Definitions'!$A$1:$S$31597,10),"")) | U31: =IF(IFERROR(VLOOKUP($H31,'Field Definitions'!$A$1:$S$31597,12),"")=0,"",IFERROR(VLOOKUP($H31,'Field Definitions'!$A$1:$S$31597,12),"")) -> Y|Yes|~N|No| | X31: =";PRTY^"&J31&"^"&M31&"^"&N31 -> ;PRTY^29^CHR^1
D32: MVP | E32: MVP | G32: =IFERROR(VLOOKUP(H32,'Field Definitions'!$A$1:$S$31597,3),"") -> ARENTITY | H32: ARENBUSINESS | I32: =IFERROR(VLOOKUP(H32,'Field Definitions'!$A$1:$S$31597,2),"") -> Business? | J32: 30 | L32: Values: Y, N | M32: =IFERROR(VLOOKUP($H32,'Field Definitions'!$A$1:$S$31597,4),"") -> CHR | N32: =IFERROR(VLOOKUP($H32,'Field Definitions'!$A$1:$S$31597,5),"") -> 1 | O32: N | P32: N | Q32: N | R32: =IF(IFERROR(VLOOKUP($H32,'Field Definitions'!$A$1:$S$31597,8),"")=0,"",IFERROR(VLOOKUP($H32,'Field Definitions'!$A$1:$S$31597,8),"")) | S32: =IF(IFERROR(VLOOKUP($H32,'Field Definitions'!$A$1:$S$31597,9),"")=0,"",IFERROR(VLOOKUP($H32,'Field Definitions'!$A$1:$S$31597,9),"")) | T32: =IF(IFERROR(VLOOKUP($H32,'Field Definitions'!$A$1:$S$31597,10),"")=0,"",IFERROR(VLOOKUP($H32,'Field Definitions'!$A$1:$S$31597,10),"")) | U32: =IF(IFERROR(VLOOKUP($H32,'Field Definitions'!$A$1:$S$31597,12),"")=0,"",IFERROR(VLOOKUP($H32,'Field Definitions'!$A$1:$S$31597,12),"")) -> Y|Entity is a Business|~N|Entity is a Person| | X32: =";PRTY^"&J32&"^"&M32&"^"&N32 -> ;PRTY^30^CHR^1
D33: MVP | E33: MVP | G33: =IFERROR(VLOOKUP(H33,'Field Definitions'!$A$1:$S$31597,3),"") -> ARENTITY | H33: ARENFIRM | I33: =IFERROR(VLOOKUP(H33,'Field Definitions'!$A$1:$S$31597,2),"") -> Business Name | J33: 31 | M33: =IFERROR(VLOOKUP($H33,'Field Definitions'!$A$1:$S$31597,4),"") -> CHR | N33: =IFERROR(VLOOKUP($H33,'Field Definitions'!$A$1:$S$31597,5),"") -> 35 | O33: This is not a business | P33: This is not a business | Q33: This is not a business | R33: =IF(IFERROR(VLOOKUP($H33,'Field Definitions'!$A$1:$S$31597,8),"")=0,"",IFERROR(VLOOKUP($H33,'Field Definitions'!$A$1:$S$31597,8),"")) | S33: =IF(IFERROR(VLOOKUP($H33,'Field Definitions'!$A$1:$S$31597,9),"")=0,"",IFERROR(VLOOKUP($H33,'Field Definitions'!$A$1:$S$31597,9),"")) | T33: =IF(IFERROR(VLOOKUP($H33,'Field Definitions'!$A$1:$S$31597,10),"")=0,"",IFERROR(VLOOKUP($H33,'Field Definitions'!$A$1:$S$31597,10),"")) | U33: =IF(IFERROR(VLOOKUP($H33,'Field Definitions'!$A$1:$S$31597,12),"")=0,"",IFERROR(VLOOKUP($H33,'Field Definitions'!$A$1:$S$31597,12),"")) | X33: =";PRTY^"&J33&"^"&M33&"^"&N33 -> ;PRTY^31^CHR^35
D34: MVP | E34: MVP | G34: =IFERROR(VLOOKUP(H34,'Field Definitions'!$A$1:$S$31597,3),"") -> ARENTITY | H34: ARENEIN | I34: =IFERROR(VLOOKUP(H34,'Field Definitions'!$A$1:$S$31597,2),"") -> Employer Identification Number | J34: 32 | M34: =IFERROR(VLOOKUP($H34,'Field Definitions'!$A$1:$S$31597,4),"") -> CHR | N34: =IFERROR(VLOOKUP($H34,'Field Definitions'!$A$1:$S$31597,5),"") -> 10 | O34: 35-123412341234 | P34: 35-123412341234 | Q34: 35-123412341234 | R34: =IF(IFERROR(VLOOKUP($H34,'Field Definitions'!$A$1:$S$31597,8),"")=0,"",IFERROR(VLOOKUP($H34,'Field Definitions'!$A$1:$S$31597,8),"")) | S34: =IF(IFERROR(VLOOKUP($H34,'Field Definitions'!$A$1:$S$31597,9),"")=0,"",IFERROR(VLOOKUP($H34,'Field Definitions'!$A$1:$S$31597,9),"")) | T34: =IF(IFERROR(VLOOKUP($H34,'Field Definitions'!$A$1:$S$31597,10),"")=0,"",IFERROR(VLOOKUP($H34,'Field Definitions'!$A$1:$S$31597,10),"")) | U34: =IF(IFERROR(VLOOKUP($H34,'Field Definitions'!$A$1:$S$31597,12),"")=0,"",IFERROR(VLOOKUP($H34,'Field Definitions'!$A$1:$S$31597,12),"")) | X34: =";PRTY^"&J34&"^"&M34&"^"&N34 -> ;PRTY^32^CHR^10
D35: MVP | E35: MVP | G35: =IFERROR(VLOOKUP(H35,'Field Definitions'!$A$1:$S$31597,3),"") -> ARRELATIONSHIP | H35: ARRELENINIRSPBAL | I35: =IFERROR(VLOOKUP(H35,'Field Definitions'!$A$1:$S$31597,2),"") -> Entity Responsible Balance (Initial) | J35: 33 | L35: Leave this blank if all RP's are responsible for entire balance | M35: =IFERROR(VLOOKUP($H35,'Field Definitions'!$A$1:$S$31597,4),"") -> AMT | N35: =IFERROR(VLOOKUP($H35,'Field Definitions'!$A$1:$S$31597,5),"") -> 14 | O35: 1000 | P35: 143.74 | Q35: 143.74 | R35: =IF(IFERROR(VLOOKUP($H35,'Field Definitions'!$A$1:$S$31597,8),"")=0,"",IFERROR(VLOOKUP($H35,'Field Definitions'!$A$1:$S$31597,8),"")) | S35: =IF(IFERROR(VLOOKUP($H35,'Field Definitions'!$A$1:$S$31597,9),"")=0,"",IFERROR(VLOOKUP($H35,'Field Definitions'!$A$1:$S$31597,9),"")) | T35: =IF(IFERROR(VLOOKUP($H35,'Field Definitions'!$A$1:$S$31597,10),"")=0,"",IFERROR(VLOOKUP($H35,'Field Definitions'!$A$1:$S$31597,10),"")) | U35: =IF(IFERROR(VLOOKUP($H35,'Field Definitions'!$A$1:$S$31597,12),"")=0,"",IFERROR(VLOOKUP($H35,'Field Definitions'!$A$1:$S$31597,12),"")) | X35: =";PRTY^"&J35&"^"&M35&"^"&N35 -> ;PRTY^33^AMT^14
D36: Use POE record | F36: POE | G36: =IFERROR(VLOOKUP(H36,'Field Definitions'!$A$1:$S$31597,3),"") -> ARENTITY | H36: ARENPOE | I36: =IFERROR(VLOOKUP(H36,'Field Definitions'!$A$1:$S$31597,2),"") -> Place of Employment | J36: =J35+1 -> 34 | L36: Use only if UsePOETable option not enabled. Else use record 22 | M36: =IFERROR(VLOOKUP($H36,'Field Definitions'!$A$1:$S$31597,4),"") -> CHR | N36: =IFERROR(VLOOKUP($H36,'Field Definitions'!$A$1:$S$31597,5),"") -> 50 | O36: BOA | P36: BOA | Q36: BOA | R36: =IF(IFERROR(VLOOKUP($H36,'Field Definitions'!$A$1:$S$31597,8),"")=0,"",IFERROR(VLOOKUP($H36,'Field Definitions'!$A$1:$S$31597,8),"")) | S36: =IF(IFERROR(VLOOKUP($H36,'Field Definitions'!$A$1:$S$31597,9),"")=0,"",IFERROR(VLOOKUP($H36,'Field Definitions'!$A$1:$S$31597,9),"")) | T36: =IF(IFERROR(VLOOKUP($H36,'Field Definitions'!$A$1:$S$31597,10),"")=0,"",IFERROR(VLOOKUP($H36,'Field Definitions'!$A$1:$S$31597,10),"")) | U36: =IF(IFERROR(VLOOKUP($H36,'Field Definitions'!$A$1:$S$31597,12),"")=0,"",IFERROR(VLOOKUP($H36,'Field Definitions'!$A$1:$S$31597,12),"")) | X36: =";PRTY^"&J36&"^"&M36&"^"&N36 -> ;PRTY^34^CHR^50
D37: Use POE record | G37: =IFERROR(VLOOKUP(H37,'Field Definitions'!$A$1:$S$31597,3),"") -> ARENTITY | H37: ARENPOEADR | I37: =IFERROR(VLOOKUP(H37,'Field Definitions'!$A$1:$S$31597,2),"") -> POE Address Line | J37: =J36+1 -> 35 | L37: Use only if UsePOETable option not enabled. Else use record 22 | M37: =IFERROR(VLOOKUP($H37,'Field Definitions'!$A$1:$S$31597,4),"") -> CHR | N37: =IFERROR(VLOOKUP($H37,'Field Definitions'!$A$1:$S$31597,5),"") -> 40 | O37: 123 Somewhere St | P37: 123 Somewhere St | Q37: 123 Somewhere St | R37: =IF(IFERROR(VLOOKUP($H37,'Field Definitions'!$A$1:$S$31597,8),"")=0,"",IFERROR(VLOOKUP($H37,'Field Definitions'!$A$1:$S$31597,8),"")) | S37: =IF(IFERROR(VLOOKUP($H37,'Field Definitions'!$A$1:$S$31597,9),"")=0,"",IFERROR(VLOOKUP($H37,'Field Definitions'!$A$1:$S$31597,9),"")) | T37: =IF(IFERROR(VLOOKUP($H37,'Field Definitions'!$A$1:$S$31597,10),"")=0,"",IFERROR(VLOOKUP($H37,'Field Definitions'!$A$1:$S$31597,10),"")) | U37: =IF(IFERROR(VLOOKUP($H37,'Field Definitions'!$A$1:$S$31597,12),"")=0,"",IFERROR(VLOOKUP($H37,'Field Definitions'!$A$1:$S$31597,12),"")) | X37: =";PRTY^"&J37&"^"&M37&"^"&N37 -> ;PRTY^35^CHR^40
D38: Use POE record | G38: =IFERROR(VLOOKUP(H38,'Field Definitions'!$A$1:$S$31597,3),"") -> ARENTITY | H38: ARENPOEUNT | I38: =IFERROR(VLOOKUP(H38,'Field Definitions'!$A$1:$S$31597,2),"") -> POE Address Unit (Box, Suite) | J38: =J37+1 -> 36 | L38: Use only if UsePOETable option not enabled. Else use record 22 | M38: =IFERROR(VLOOKUP($H38,'Field Definitions'!$A$1:$S$31597,4),"") -> CHR | N38: =IFERROR(VLOOKUP($H38,'Field Definitions'!$A$1:$S$31597,5),"") -> 40 | O38: Suite A | P38: Suite A | Q38: Suite A | R38: =IF(IFERROR(VLOOKUP($H38,'Field Definitions'!$A$1:$S$31597,8),"")=0,"",IFERROR(VLOOKUP($H38,'Field Definitions'!$A$1:$S$31597,8),"")) | S38: =IF(IFERROR(VLOOKUP($H38,'Field Definitions'!$A$1:$S$31597,9),"")=0,"",IFERROR(VLOOKUP($H38,'Field Definitions'!$A$1:$S$31597,9),"")) | T38: =IF(IFERROR(VLOOKUP($H38,'Field Definitions'!$A$1:$S$31597,10),"")=0,"",IFERROR(VLOOKUP($H38,'Field Definitions'!$A$1:$S$31597,10),"")) | U38: =IF(IFERROR(VLOOKUP($H38,'Field Definitions'!$A$1:$S$31597,12),"")=0,"",IFERROR(VLOOKUP($H38,'Field Definitions'!$A$1:$S$31597,12),"")) | X38: =";PRTY^"&J38&"^"&M38&"^"&N38 -> ;PRTY^36^CHR^40
D39: Use POE record | G39: =IFERROR(VLOOKUP(H39,'Field Definitions'!$A$1:$S$31597,3),"") -> ARENTITY | H39: ARENPOECTY | I39: =IFERROR(VLOOKUP(H39,'Field Definitions'!$A$1:$S$31597,2),"") -> POE City | J39: =J38+1 -> 37 | L39: Use only if UsePOETable option not enabled. Else use record 22 | M39: =IFERROR(VLOOKUP($H39,'Field Definitions'!$A$1:$S$31597,4),"") -> CHR | N39: =IFERROR(VLOOKUP($H39,'Field Definitions'!$A$1:$S$31597,5),"") -> 20 | O39: Some Place | P39: Some Place | Q39: Some Place | R39: =IF(IFERROR(VLOOKUP($H39,'Field Definitions'!$A$1:$S$31597,8),"")=0,"",IFERROR(VLOOKUP($H39,'Field Definitions'!$A$1:$S$31597,8),"")) | S39: =IF(IFERROR(VLOOKUP($H39,'Field Definitions'!$A$1:$S$31597,9),"")=0,"",IFERROR(VLOOKUP($H39,'Field Definitions'!$A$1:$S$31597,9),"")) | T39: =IF(IFERROR(VLOOKUP($H39,'Field Definitions'!$A$1:$S$31597,10),"")=0,"",IFERROR(VLOOKUP($H39,'Field Definitions'!$A$1:$S$31597,10),"")) | U39: =IF(IFERROR(VLOOKUP($H39,'Field Definitions'!$A$1:$S$31597,12),"")=0,"",IFERROR(VLOOKUP($H39,'Field Definitions'!$A$1:$S$31597,12),"")) | X39: =";PRTY^"&J39&"^"&M39&"^"&N39 -> ;PRTY^37^CHR^20
D40: Use POE record | G40: =IFERROR(VLOOKUP(H40,'Field Definitions'!$A$1:$S$31597,3),"") -> ARENTITY | H40: ARENPOEST | I40: =IFERROR(VLOOKUP(H40,'Field Definitions'!$A$1:$S$31597,2),"") -> POE State | J40: =J39+1 -> 38 | L40: Use only if UsePOETable option not enabled. Else use record 22 | M40: =IFERROR(VLOOKUP($H40,'Field Definitions'!$A$1:$S$31597,4),"") -> CHR | N40: =IFERROR(VLOOKUP($H40,'Field Definitions'!$A$1:$S$31597,5),"") -> 2 | O40: IN | P40: IN | Q40: IN | R40: =IF(IFERROR(VLOOKUP($H40,'Field Definitions'!$A$1:$S$31597,8),"")=0,"",IFERROR(VLOOKUP($H40,'Field Definitions'!$A$1:$S$31597,8),"")) | S40: =IF(IFERROR(VLOOKUP($H40,'Field Definitions'!$A$1:$S$31597,9),"")=0,"",IFERROR(VLOOKUP($H40,'Field Definitions'!$A$1:$S$31597,9),"")) | T40: =IF(IFERROR(VLOOKUP($H40,'Field Definitions'!$A$1:$S$31597,10),"")=0,"",IFERROR(VLOOKUP($H40,'Field Definitions'!$A$1:$S$31597,10),"")) -> STATES | U40: =IF(IFERROR(VLOOKUP($H40,'Field Definitions'!$A$1:$S$31597,12),"")=0,"",IFERROR(VLOOKUP($H40,'Field Definitions'!$A$1:$S$31597,12),"")) | X40: =";PRTY^"&J40&"^"&M40&"^"&N40 -> ;PRTY^38^CHR^2
D41: Use POE record | G41: =IFERROR(VLOOKUP(H41,'Field Definitions'!$A$1:$S$31597,3),"") -> ARENTITY | H41: ARENPOEZIP | I41: =IFERROR(VLOOKUP(H41,'Field Definitions'!$A$1:$S$31597,2),"") -> POE Postal Code | J41: =J40+1 -> 39 | L41: Use only if UsePOETable option not enabled. Else use record 22 | M41: =IFERROR(VLOOKUP($H41,'Field Definitions'!$A$1:$S$31597,4),"") -> ZIP | N41: =IFERROR(VLOOKUP($H41,'Field Definitions'!$A$1:$S$31597,5),"") -> 10 | O41: 47304 | P41: 47304 | Q41: 47304 | R41: =IF(IFERROR(VLOOKUP($H41,'Field Definitions'!$A$1:$S$31597,8),"")=0,"",IFERROR(VLOOKUP($H41,'Field Definitions'!$A$1:$S$31597,8),"")) | S41: =IF(IFERROR(VLOOKUP($H41,'Field Definitions'!$A$1:$S$31597,9),"")=0,"",IFERROR(VLOOKUP($H41,'Field Definitions'!$A$1:$S$31597,9),"")) | T41: =IF(IFERROR(VLOOKUP($H41,'Field Definitions'!$A$1:$S$31597,10),"")=0,"",IFERROR(VLOOKUP($H41,'Field Definitions'!$A$1:$S$31597,10),"")) | U41: =IF(IFERROR(VLOOKUP($H41,'Field Definitions'!$A$1:$S$31597,12),"")=0,"",IFERROR(VLOOKUP($H41,'Field Definitions'!$A$1:$S$31597,12),"")) | X41: =";PRTY^"&J41&"^"&M41&"^"&N41 -> ;PRTY^39^ZIP^10
D42: Use POE record | G42: =IFERROR(VLOOKUP(H42,'Field Definitions'!$A$1:$S$31597,3),"") -> ARENTITY | H42: ARENPOECNTRY | I42: =IFERROR(VLOOKUP(H42,'Field Definitions'!$A$1:$S$31597,2),"") -> POE Country | J42: =J41+1 -> 40 | L42: Use only if UsePOETable option not enabled. Else use record 22 | M42: =IFERROR(VLOOKUP($H42,'Field Definitions'!$A$1:$S$31597,4),"") -> CHR | N42: =IFERROR(VLOOKUP($H42,'Field Definitions'!$A$1:$S$31597,5),"") -> 35 | O42: USA | P42: USA | Q42: USA | R42: =IF(IFERROR(VLOOKUP($H42,'Field Definitions'!$A$1:$S$31597,8),"")=0,"",IFERROR(VLOOKUP($H42,'Field Definitions'!$A$1:$S$31597,8),"")) | S42: =IF(IFERROR(VLOOKUP($H42,'Field Definitions'!$A$1:$S$31597,9),"")=0,"",IFERROR(VLOOKUP($H42,'Field Definitions'!$A$1:$S$31597,9),"")) | T42: =IF(IFERROR(VLOOKUP($H42,'Field Definitions'!$A$1:$S$31597,10),"")=0,"",IFERROR(VLOOKUP($H42,'Field Definitions'!$A$1:$S$31597,10),"")) | U42: =IF(IFERROR(VLOOKUP($H42,'Field Definitions'!$A$1:$S$31597,12),"")=0,"",IFERROR(VLOOKUP($H42,'Field Definitions'!$A$1:$S$31597,12),"")) | X42: =";PRTY^"&J42&"^"&M42&"^"&N42 -> ;PRTY^40^CHR^35
D43: Use POE record | G43: =IFERROR(VLOOKUP(H43,'Field Definitions'!$A$1:$S$31597,3),"") -> ARENTITY | H43: ARENPOEPH | I43: =IFERROR(VLOOKUP(H43,'Field Definitions'!$A$1:$S$31597,2),"") -> POE Phone Number | J43: =J42+1 -> 41 | L43: Use only if UsePOETable option not enabled. Else use record 22 | M43: =IFERROR(VLOOKUP($H43,'Field Definitions'!$A$1:$S$31597,4),"") -> PHONE | N43: =IFERROR(VLOOKUP($H43,'Field Definitions'!$A$1:$S$31597,5),"") -> 12 | O43: 7657517200 | P43: 7657517200 | Q43: 7657517200 | R43: =IF(IFERROR(VLOOKUP($H43,'Field Definitions'!$A$1:$S$31597,8),"")=0,"",IFERROR(VLOOKUP($H43,'Field Definitions'!$A$1:$S$31597,8),"")) | S43: =IF(IFERROR(VLOOKUP($H43,'Field Definitions'!$A$1:$S$31597,9),"")=0,"",IFERROR(VLOOKUP($H43,'Field Definitions'!$A$1:$S$31597,9),"")) | T43: =IF(IFERROR(VLOOKUP($H43,'Field Definitions'!$A$1:$S$31597,10),"")=0,"",IFERROR(VLOOKUP($H43,'Field Definitions'!$A$1:$S$31597,10),"")) | U43: =IF(IFERROR(VLOOKUP($H43,'Field Definitions'!$A$1:$S$31597,12),"")=0,"",IFERROR(VLOOKUP($H43,'Field Definitions'!$A$1:$S$31597,12),"")) | X43: =";PRTY^"&J43&"^"&M43&"^"&N43 -> ;PRTY^41^PHONE^12
D44: Use POE record | G44: =IFERROR(VLOOKUP(H44,'Field Definitions'!$A$1:$S$31597,3),"") -> ARENTITY | H44: ARENPOEPF | I44: =IFERROR(VLOOKUP(H44,'Field Definitions'!$A$1:$S$31597,2),"") -> POE Phone Flag | J44: =J43+1 -> 42 | L44: Use only if UsePOETable option not enabled. Else use record 22 | M44: =IFERROR(VLOOKUP($H44,'Field Definitions'!$A$1:$S$31597,4),"") -> CHR | N44: =IFERROR(VLOOKUP($H44,'Field Definitions'!$A$1:$S$31597,5),"") -> 1 | O44: G | P44: G | Q44: G | R44: =IF(IFERROR(VLOOKUP($H44,'Field Definitions'!$A$1:$S$31597,8),"")=0,"",IFERROR(VLOOKUP($H44,'Field Definitions'!$A$1:$S$31597,8),"")) | S44: =IF(IFERROR(VLOOKUP($H44,'Field Definitions'!$A$1:$S$31597,9),"")=0,"",IFERROR(VLOOKUP($H44,'Field Definitions'!$A$1:$S$31597,9),"")) | T44: =IF(IFERROR(VLOOKUP($H44,'Field Definitions'!$A$1:$S$31597,10),"")=0,"",IFERROR(VLOOKUP($H44,'Field Definitions'!$A$1:$S$31597,10),"")) | U44: =IF(IFERROR(VLOOKUP($H44,'Field Definitions'!$A$1:$S$31597,12),"")=0,"",IFERROR(VLOOKUP($H44,'Field Definitions'!$A$1:$S$31597,12),"")) | X44: =";PRTY^"&J44&"^"&M44&"^"&N44 -> ;PRTY^42^CHR^1
D45: Use POE record | G45: =IFERROR(VLOOKUP(H45,'Field Definitions'!$A$1:$S$31597,3),"") -> ARENTITY | H45: ARENPOEEXT | I45: =IFERROR(VLOOKUP(H45,'Field Definitions'!$A$1:$S$31597,2),"") -> POE Phone Extension | J45: =J44+1 -> 43 | L45: Use only if UsePOETable option not enabled. Else use record 22 | M45: =IFERROR(VLOOKUP($H45,'Field Definitions'!$A$1:$S$31597,4),"") -> CHR | N45: =IFERROR(VLOOKUP($H45,'Field Definitions'!$A$1:$S$31597,5),"") -> 5 | O45: 1234 | P45: 1234 | Q45: 1234 | R45: =IF(IFERROR(VLOOKUP($H45,'Field Definitions'!$A$1:$S$31597,8),"")=0,"",IFERROR(VLOOKUP($H45,'Field Definitions'!$A$1:$S$31597,8),"")) | S45: =IF(IFERROR(VLOOKUP($H45,'Field Definitions'!$A$1:$S$31597,9),"")=0,"",IFERROR(VLOOKUP($H45,'Field Definitions'!$A$1:$S$31597,9),"")) | T45: =IF(IFERROR(VLOOKUP($H45,'Field Definitions'!$A$1:$S$31597,10),"")=0,"",IFERROR(VLOOKUP($H45,'Field Definitions'!$A$1:$S$31597,10),"")) | U45: =IF(IFERROR(VLOOKUP($H45,'Field Definitions'!$A$1:$S$31597,12),"")=0,"",IFERROR(VLOOKUP($H45,'Field Definitions'!$A$1:$S$31597,12),"")) | X45: =";PRTY^"&J45&"^"&M45&"^"&N45 -> ;PRTY^43^CHR^5
D46: Use POE record | G46: =IFERROR(VLOOKUP(H46,'Field Definitions'!$A$1:$S$31597,3),"") -> ARENTITY | H46: ARENHIREDTE | I46: =IFERROR(VLOOKUP(H46,'Field Definitions'!$A$1:$S$31597,2),"") -> Date of Hire | J46: =J45+1 -> 44 | L46: Use only if UsePOETable option not enabled. Else use record 22 | M46: =IFERROR(VLOOKUP($H46,'Field Definitions'!$A$1:$S$31597,4),"") -> DATE | N46: =IFERROR(VLOOKUP($H46,'Field Definitions'!$A$1:$S$31597,5),"") -> 10 | O46: 01/01/1990 | P46: 01/01/1990 | Q46: 01/01/1990 | R46: =IF(IFERROR(VLOOKUP($H46,'Field Definitions'!$A$1:$S$31597,8),"")=0,"",IFERROR(VLOOKUP($H46,'Field Definitions'!$A$1:$S$31597,8),"")) | S46: =IF(IFERROR(VLOOKUP($H46,'Field Definitions'!$A$1:$S$31597,9),"")=0,"",IFERROR(VLOOKUP($H46,'Field Definitions'!$A$1:$S$31597,9),"")) | T46: =IF(IFERROR(VLOOKUP($H46,'Field Definitions'!$A$1:$S$31597,10),"")=0,"",IFERROR(VLOOKUP($H46,'Field Definitions'!$A$1:$S$31597,10),"")) | U46: =IF(IFERROR(VLOOKUP($H46,'Field Definitions'!$A$1:$S$31597,12),"")=0,"",IFERROR(VLOOKUP($H46,'Field Definitions'!$A$1:$S$31597,12),"")) | X46: =";PRTY^"&J46&"^"&M46&"^"&N46 -> ;PRTY^44^DATE^10
D47: Use POE record | G47: =IFERROR(VLOOKUP(H47,'Field Definitions'!$A$1:$S$31597,3),"") -> ARENTITY | H47: ARENEMPLOYED | I47: =IFERROR(VLOOKUP(H47,'Field Definitions'!$A$1:$S$31597,2),"") -> Responsible Party Employed? | J47: =J46+1 -> 45 | L47: Use only if UsePOETable option not enabled. Else use record 22 | M47: =IFERROR(VLOOKUP($H47,'Field Definitions'!$A$1:$S$31597,4),"") -> CHR | N47: =IFERROR(VLOOKUP($H47,'Field Definitions'!$A$1:$S$31597,5),"") -> 1 | O47: Y | P47: Y | Q47: Y | R47: =IF(IFERROR(VLOOKUP($H47,'Field Definitions'!$A$1:$S$31597,8),"")=0,"",IFERROR(VLOOKUP($H47,'Field Definitions'!$A$1:$S$31597,8),"")) | S47: =IF(IFERROR(VLOOKUP($H47,'Field Definitions'!$A$1:$S$31597,9),"")=0,"",IFERROR(VLOOKUP($H47,'Field Definitions'!$A$1:$S$31597,9),"")) | T47: =IF(IFERROR(VLOOKUP($H47,'Field Definitions'!$A$1:$S$31597,10),"")=0,"",IFERROR(VLOOKUP($H47,'Field Definitions'!$A$1:$S$31597,10),"")) | U47: =IF(IFERROR(VLOOKUP($H47,'Field Definitions'!$A$1:$S$31597,12),"")=0,"",IFERROR(VLOOKUP($H47,'Field Definitions'!$A$1:$S$31597,12),"")) -> Y|Employed|AR4877~N|Not Employed|AR4878~X|Unsure of Employment|AR4879 | X47: =";PRTY^"&J47&"^"&M47&"^"&N47 -> ;PRTY^45^CHR^1
D48: Use POE record | G48: =IFERROR(VLOOKUP(H48,'Field Definitions'!$A$1:$S$31597,3),"") -> ARENTITY | H48: ARENPOESAL | I48: =IFERROR(VLOOKUP(H48,'Field Definitions'!$A$1:$S$31597,2),"") -> POE Annual Salary | J48: =J47+1 -> 46 | L48: Use only if UsePOETable option not enabled. Else use record 22 | M48: =IFERROR(VLOOKUP($H48,'Field Definitions'!$A$1:$S$31597,4),"") -> AMT | N48: =IFERROR(VLOOKUP($H48,'Field Definitions'!$A$1:$S$31597,5),"") -> 12 | O48: 52000.01 | P48: 52000.01 | Q48: 52000.01 | R48: =IF(IFERROR(VLOOKUP($H48,'Field Definitions'!$A$1:$S$31597,8),"")=0,"",IFERROR(VLOOKUP($H48,'Field Definitions'!$A$1:$S$31597,8),"")) | S48: =IF(IFERROR(VLOOKUP($H48,'Field Definitions'!$A$1:$S$31597,9),"")=0,"",IFERROR(VLOOKUP($H48,'Field Definitions'!$A$1:$S$31597,9),"")) -> 1e+09 | T48: =IF(IFERROR(VLOOKUP($H48,'Field Definitions'!$A$1:$S$31597,10),"")=0,"",IFERROR(VLOOKUP($H48,'Field Definitions'!$A$1:$S$31597,10),"")) | U48: =IF(IFERROR(VLOOKUP($H48,'Field Definitions'!$A$1:$S$31597,12),"")=0,"",IFERROR(VLOOKUP($H48,'Field Definitions'!$A$1:$S$31597,12),"")) | X48: =";PRTY^"&J48&"^"&M48&"^"&N48 -> ;PRTY^46^AMT^12
D49: Use POE record | G49: =IFERROR(VLOOKUP(H49,'Field Definitions'!$A$1:$S$31597,3),"") -> ARENTITY | H49: ARENPOEFNM | I49: =IFERROR(VLOOKUP(H49,'Field Definitions'!$A$1:$S$31597,2),"") -> POE Contact First Name | J49: =J48+1 -> 47 | L49: Use only if UsePOETable option not enabled. Else use record 22 | M49: =IFERROR(VLOOKUP($H49,'Field Definitions'!$A$1:$S$31597,4),"") -> CHR | N49: =IFERROR(VLOOKUP($H49,'Field Definitions'!$A$1:$S$31597,5),"") -> 15 | O49: POE Contact First Name | P49: POE Contact First Name | Q49: POE Contact First Name | R49: =IF(IFERROR(VLOOKUP($H49,'Field Definitions'!$A$1:$S$31597,8),"")=0,"",IFERROR(VLOOKUP($H49,'Field Definitions'!$A$1:$S$31597,8),"")) | S49: =IF(IFERROR(VLOOKUP($H49,'Field Definitions'!$A$1:$S$31597,9),"")=0,"",IFERROR(VLOOKUP($H49,'Field Definitions'!$A$1:$S$31597,9),"")) | T49: =IF(IFERROR(VLOOKUP($H49,'Field Definitions'!$A$1:$S$31597,10),"")=0,"",IFERROR(VLOOKUP($H49,'Field Definitions'!$A$1:$S$31597,10),"")) | U49: =IF(IFERROR(VLOOKUP($H49,'Field Definitions'!$A$1:$S$31597,12),"")=0,"",IFERROR(VLOOKUP($H49,'Field Definitions'!$A$1:$S$31597,12),"")) | X49: =";PRTY^"&J49&"^"&M49&"^"&N49 -> ;PRTY^47^CHR^15
D50: Use POE record | G50: =IFERROR(VLOOKUP(H50,'Field Definitions'!$A$1:$S$31597,3),"") -> ARENTITY | H50: ARENPOELNM | I50: =IFERROR(VLOOKUP(H50,'Field Definitions'!$A$1:$S$31597,2),"") -> POE Contact Last Name | J50: =J49+1 -> 48 | L50: Use only if UsePOETable option not enabled. Else use record 22 | M50: =IFERROR(VLOOKUP($H50,'Field Definitions'!$A$1:$S$31597,4),"") -> CHR | N50: =IFERROR(VLOOKUP($H50,'Field Definitions'!$A$1:$S$31597,5),"") -> 20 | O50: POE Contact Last Name | P50: POE Contact Last Name | Q50: POE Contact Last Name | R50: =IF(IFERROR(VLOOKUP($H50,'Field Definitions'!$A$1:$S$31597,8),"")=0,"",IFERROR(VLOOKUP($H50,'Field Definitions'!$A$1:$S$31597,8),"")) | S50: =IF(IFERROR(VLOOKUP($H50,'Field Definitions'!$A$1:$S$31597,9),"")=0,"",IFERROR(VLOOKUP($H50,'Field Definitions'!$A$1:$S$31597,9),"")) | T50: =IF(IFERROR(VLOOKUP($H50,'Field Definitions'!$A$1:$S$31597,10),"")=0,"",IFERROR(VLOOKUP($H50,'Field Definitions'!$A$1:$S$31597,10),"")) | U50: =IF(IFERROR(VLOOKUP($H50,'Field Definitions'!$A$1:$S$31597,12),"")=0,"",IFERROR(VLOOKUP($H50,'Field Definitions'!$A$1:$S$31597,12),"")) | X50: =";PRTY^"&J50&"^"&M50&"^"&N50 -> ;PRTY^48^CHR^20
D51: Use POE record | G51: =IFERROR(VLOOKUP(H51,'Field Definitions'!$A$1:$S$31597,3),"") -> ARENTITY | H51: ARENPOETTL | I51: =IFERROR(VLOOKUP(H51,'Field Definitions'!$A$1:$S$31597,2),"") -> POE Contact Title | J51: =J50+1 -> 49 | L51: Use only if UsePOETable option not enabled. Else use record 22 | M51: =IFERROR(VLOOKUP($H51,'Field Definitions'!$A$1:$S$31597,4),"") -> CHR | N51: =IFERROR(VLOOKUP($H51,'Field Definitions'!$A$1:$S$31597,5),"") -> 30 | O51: Person to contact | P51: Person to contact | Q51: Person to contact | R51: =IF(IFERROR(VLOOKUP($H51,'Field Definitions'!$A$1:$S$31597,8),"")=0,"",IFERROR(VLOOKUP($H51,'Field Definitions'!$A$1:$S$31597,8),"")) | S51: =IF(IFERROR(VLOOKUP($H51,'Field Definitions'!$A$1:$S$31597,9),"")=0,"",IFERROR(VLOOKUP($H51,'Field Definitions'!$A$1:$S$31597,9),"")) | T51: =IF(IFERROR(VLOOKUP($H51,'Field Definitions'!$A$1:$S$31597,10),"")=0,"",IFERROR(VLOOKUP($H51,'Field Definitions'!$A$1:$S$31597,10),"")) | U51: =IF(IFERROR(VLOOKUP($H51,'Field Definitions'!$A$1:$S$31597,12),"")=0,"",IFERROR(VLOOKUP($H51,'Field Definitions'!$A$1:$S$31597,12),"")) | X51: =";PRTY^"&J51&"^"&M51&"^"&N51 -> ;PRTY^49^CHR^30
D52: Use POE record | G52: =IFERROR(VLOOKUP(H52,'Field Definitions'!$A$1:$S$31597,3),"") -> ARENTITY | H52: ARENPOEFAX | I52: =IFERROR(VLOOKUP(H52,'Field Definitions'!$A$1:$S$31597,2),"") -> POE Fax Number | J52: =J51+1 -> 50 | L52: Use only if UsePOETable option not enabled. Else use record 22 | M52: =IFERROR(VLOOKUP($H52,'Field Definitions'!$A$1:$S$31597,4),"") -> PHONE | N52: 10 | O52: 7657517199 | P52: 7657517199 | Q52: 7657517199 | R52: =IF(IFERROR(VLOOKUP($H52,'Field Definitions'!$A$1:$S$31597,8),"")=0,"",IFERROR(VLOOKUP($H52,'Field Definitions'!$A$1:$S$31597,8),"")) | S52: =IF(IFERROR(VLOOKUP($H52,'Field Definitions'!$A$1:$S$31597,9),"")=0,"",IFERROR(VLOOKUP($H52,'Field Definitions'!$A$1:$S$31597,9),"")) | T52: =IF(IFERROR(VLOOKUP($H52,'Field Definitions'!$A$1:$S$31597,10),"")=0,"",IFERROR(VLOOKUP($H52,'Field Definitions'!$A$1:$S$31597,10),"")) | U52: =IF(IFERROR(VLOOKUP($H52,'Field Definitions'!$A$1:$S$31597,12),"")=0,"",IFERROR(VLOOKUP($H52,'Field Definitions'!$A$1:$S$31597,12),"")) | X52: =";PRTY^"&J52&"^"&M52&"^"&N52 -> ;PRTY^50^PHONE^10
D53: MVP | E53: MVP | F53: Bankruptcy | G53: =IFERROR(VLOOKUP(H53,'Field Definitions'!$A$1:$S$31597,3),"") -> ARENTITY | H53: ARENBNKRPT | I53: =IFERROR(VLOOKUP(H53,'Field Definitions'!$A$1:$S$31597,2),"") -> Entity Bankrupt? | J53: 34 | L53: Values: Y, N | M53: =IFERROR(VLOOKUP($H53,'Field Definitions'!$A$1:$S$31597,4),"") -> CHR | N53: =IFERROR(VLOOKUP($H53,'Field Definitions'!$A$1:$S$31597,5),"") -> 1 | O53: Y | P53: Y | Q53: Y | R53: =IF(IFERROR(VLOOKUP($H53,'Field Definitions'!$A$1:$S$31597,8),"")=0,"",IFERROR(VLOOKUP($H53,'Field Definitions'!$A$1:$S$31597,8),"")) | S53: =IF(IFERROR(VLOOKUP($H53,'Field Definitions'!$A$1:$S$31597,9),"")=0,"",IFERROR(VLOOKUP($H53,'Field Definitions'!$A$1:$S$31597,9),"")) | T53: =IF(IFERROR(VLOOKUP($H53,'Field Definitions'!$A$1:$S$31597,10),"")=0,"",IFERROR(VLOOKUP($H53,'Field Definitions'!$A$1:$S$31597,10),"")) | U53: =IF(IFERROR(VLOOKUP($H53,'Field Definitions'!$A$1:$S$31597,12),"")=0,"",IFERROR(VLOOKUP($H53,'Field Definitions'!$A$1:$S$31597,12),"")) -> Y||~N|| | X53: =";PRTY^"&J53&"^"&M53&"^"&N53 -> ;PRTY^34^CHR^1
D54: MVP | E54: MVP | G54: =IFERROR(VLOOKUP(H54,'Field Definitions'!$A$1:$S$31597,3),"") -> ARENTITY | H54: ARENBNKCHP | I54: =IFERROR(VLOOKUP(H54,'Field Definitions'!$A$1:$S$31597,2),"") -> Bankruptcy Chapter | J54: 35 | M54: =IFERROR(VLOOKUP($H54,'Field Definitions'!$A$1:$S$31597,4),"") -> CHR | N54: =IFERROR(VLOOKUP($H54,'Field Definitions'!$A$1:$S$31597,5),"") -> 2 | O54: 13 | P54: 13 | Q54: 13 | R54: =IF(IFERROR(VLOOKUP($H54,'Field Definitions'!$A$1:$S$31597,8),"")=0,"",IFERROR(VLOOKUP($H54,'Field Definitions'!$A$1:$S$31597,8),"")) | S54: =IF(IFERROR(VLOOKUP($H54,'Field Definitions'!$A$1:$S$31597,9),"")=0,"",IFERROR(VLOOKUP($H54,'Field Definitions'!$A$1:$S$31597,9),"")) | T54: =IF(IFERROR(VLOOKUP($H54,'Field Definitions'!$A$1:$S$31597,10),"")=0,"",IFERROR(VLOOKUP($H54,'Field Definitions'!$A$1:$S$31597,10),"")) | U54: =IF(IFERROR(VLOOKUP($H54,'Field Definitions'!$A$1:$S$31597,12),"")=0,"",IFERROR(VLOOKUP($H54,'Field Definitions'!$A$1:$S$31597,12),"")) -> 7||~11||~12||~13|| | X54: =";PRTY^"&J54&"^"&M54&"^"&N54 -> ;PRTY^35^CHR^2
D55: MVP | E55: MVP | G55: =IFERROR(VLOOKUP(H55,'Field Definitions'!$A$1:$S$31597,3),"") -> ARENTITY | H55: ARENBNKDTE | I55: =IFERROR(VLOOKUP(H55,'Field Definitions'!$A$1:$S$31597,2),"") -> Date bankruptcy filed | J55: 36 | M55: =IFERROR(VLOOKUP($H55,'Field Definitions'!$A$1:$S$31597,4),"") -> DATE | N55: =IFERROR(VLOOKUP($H55,'Field Definitions'!$A$1:$S$31597,5),"") -> 10 | O55: 01/01/2009 | P55: 01/01/2009 | Q55: 01/01/2009 | R55: =IF(IFERROR(VLOOKUP($H55,'Field Definitions'!$A$1:$S$31597,8),"")=0,"",IFERROR(VLOOKUP($H55,'Field Definitions'!$A$1:$S$31597,8),"")) | S55: =IF(IFERROR(VLOOKUP($H55,'Field Definitions'!$A$1:$S$31597,9),"")=0,"",IFERROR(VLOOKUP($H55,'Field Definitions'!$A$1:$S$31597,9),"")) | T55: =IF(IFERROR(VLOOKUP($H55,'Field Definitions'!$A$1:$S$31597,10),"")=0,"",IFERROR(VLOOKUP($H55,'Field Definitions'!$A$1:$S$31597,10),"")) | U55: =IF(IFERROR(VLOOKUP($H55,'Field Definitions'!$A$1:$S$31597,12),"")=0,"",IFERROR(VLOOKUP($H55,'Field Definitions'!$A$1:$S$31597,12),"")) | X55: =";PRTY^"&J55&"^"&M55&"^"&N55 -> ;PRTY^36^DATE^10
D56: MVP | E56: MVP | G56: =IFERROR(VLOOKUP(H56,'Field Definitions'!$A$1:$S$31597,3),"") -> ARENTITY | H56: ARENBKRCSNUM | I56: =IFERROR(VLOOKUP(H56,'Field Definitions'!$A$1:$S$31597,2),"") -> Bankruptcy Case Number | J56: 37 | M56: =IFERROR(VLOOKUP($H56,'Field Definitions'!$A$1:$S$31597,4),"") -> CHR | N56: =IFERROR(VLOOKUP($H56,'Field Definitions'!$A$1:$S$31597,5),"") -> 30 | O56: 123412341234123 | P56: 123412341234123 | Q56: 123412341234123 | R56: =IF(IFERROR(VLOOKUP($H56,'Field Definitions'!$A$1:$S$31597,8),"")=0,"",IFERROR(VLOOKUP($H56,'Field Definitions'!$A$1:$S$31597,8),"")) | S56: =IF(IFERROR(VLOOKUP($H56,'Field Definitions'!$A$1:$S$31597,9),"")=0,"",IFERROR(VLOOKUP($H56,'Field Definitions'!$A$1:$S$31597,9),"")) | T56: =IF(IFERROR(VLOOKUP($H56,'Field Definitions'!$A$1:$S$31597,10),"")=0,"",IFERROR(VLOOKUP($H56,'Field Definitions'!$A$1:$S$31597,10),"")) | U56: =IF(IFERROR(VLOOKUP($H56,'Field Definitions'!$A$1:$S$31597,12),"")=0,"",IFERROR(VLOOKUP($H56,'Field Definitions'!$A$1:$S$31597,12),"")) | X56: =";PRTY^"&J56&"^"&M56&"^"&N56 -> ;PRTY^37^CHR^30
D57: MVP | E57: MVP | G57: =IFERROR(VLOOKUP(H57,'Field Definitions'!$A$1:$S$31597,3),"") -> ARENTITY | H57: ARENBNKCHPPREV | I57: =IFERROR(VLOOKUP(H57,'Field Definitions'!$A$1:$S$31597,2),"") -> Previous Bankruptcy Chapter | J57: 38 | M57: =IFERROR(VLOOKUP($H57,'Field Definitions'!$A$1:$S$31597,4),"") -> CHR | N57: =IFERROR(VLOOKUP($H57,'Field Definitions'!$A$1:$S$31597,5),"") -> 2 | O57: 11 | P57: 11 | Q57: 11 | R57: =IF(IFERROR(VLOOKUP($H57,'Field Definitions'!$A$1:$S$31597,8),"")=0,"",IFERROR(VLOOKUP($H57,'Field Definitions'!$A$1:$S$31597,8),"")) | S57: =IF(IFERROR(VLOOKUP($H57,'Field Definitions'!$A$1:$S$31597,9),"")=0,"",IFERROR(VLOOKUP($H57,'Field Definitions'!$A$1:$S$31597,9),"")) | T57: =IF(IFERROR(VLOOKUP($H57,'Field Definitions'!$A$1:$S$31597,10),"")=0,"",IFERROR(VLOOKUP($H57,'Field Definitions'!$A$1:$S$31597,10),"")) | U57: =IF(IFERROR(VLOOKUP($H57,'Field Definitions'!$A$1:$S$31597,12),"")=0,"",IFERROR(VLOOKUP($H57,'Field Definitions'!$A$1:$S$31597,12),"")) | X57: =";PRTY^"&J57&"^"&M57&"^"&N57 -> ;PRTY^38^CHR^2
D58: MVP | E58: MVP | G58: =IFERROR(VLOOKUP(H58,'Field Definitions'!$A$1:$S$31597,3),"") -> ARENTITY | H58: ARENBNKCNVDTE | I58: =IFERROR(VLOOKUP(H58,'Field Definitions'!$A$1:$S$31597,2),"") -> Bankruptcy Ch. Conversion Date | J58: 39 | M58: =IFERROR(VLOOKUP($H58,'Field Definitions'!$A$1:$S$31597,4),"") -> DATE | N58: =IFERROR(VLOOKUP($H58,'Field Definitions'!$A$1:$S$31597,5),"") -> 10 | O58: 01/01/2008 | P58: 01/01/2008 | Q58: 01/01/2008 | R58: =IF(IFERROR(VLOOKUP($H58,'Field Definitions'!$A$1:$S$31597,8),"")=0,"",IFERROR(VLOOKUP($H58,'Field Definitions'!$A$1:$S$31597,8),"")) | S58: =IF(IFERROR(VLOOKUP($H58,'Field Definitions'!$A$1:$S$31597,9),"")=0,"",IFERROR(VLOOKUP($H58,'Field Definitions'!$A$1:$S$31597,9),"")) | T58: =IF(IFERROR(VLOOKUP($H58,'Field Definitions'!$A$1:$S$31597,10),"")=0,"",IFERROR(VLOOKUP($H58,'Field Definitions'!$A$1:$S$31597,10),"")) | U58: =IF(IFERROR(VLOOKUP($H58,'Field Definitions'!$A$1:$S$31597,12),"")=0,"",IFERROR(VLOOKUP($H58,'Field Definitions'!$A$1:$S$31597,12),"")) | X58: =";PRTY^"&J58&"^"&M58&"^"&N58 -> ;PRTY^39^DATE^10
D59: MVP | E59: MVP | G59: =IFERROR(VLOOKUP(H59,'Field Definitions'!$A$1:$S$31597,3),"") -> ARENTITY | H59: ARENBNKCNVRSN | I59: =IFERROR(VLOOKUP(H59,'Field Definitions'!$A$1:$S$31597,2),"") -> Bankruptcy Ch Conv Reason | J59: 40 | M59: =IFERROR(VLOOKUP($H59,'Field Definitions'!$A$1:$S$31597,4),"") -> CHR | N59: =IFERROR(VLOOKUP($H59,'Field Definitions'!$A$1:$S$31597,5),"") -> 180 | O59: Moving onto next step | P59: Moving onto next step | Q59: Moving onto next step | R59: =IF(IFERROR(VLOOKUP($H59,'Field Definitions'!$A$1:$S$31597,8),"")=0,"",IFERROR(VLOOKUP($H59,'Field Definitions'!$A$1:$S$31597,8),"")) | S59: =IF(IFERROR(VLOOKUP($H59,'Field Definitions'!$A$1:$S$31597,9),"")=0,"",IFERROR(VLOOKUP($H59,'Field Definitions'!$A$1:$S$31597,9),"")) | T59: =IF(IFERROR(VLOOKUP($H59,'Field Definitions'!$A$1:$S$31597,10),"")=0,"",IFERROR(VLOOKUP($H59,'Field Definitions'!$A$1:$S$31597,10),"")) | U59: =IF(IFERROR(VLOOKUP($H59,'Field Definitions'!$A$1:$S$31597,12),"")=0,"",IFERROR(VLOOKUP($H59,'Field Definitions'!$A$1:$S$31597,12),"")) | X59: =";PRTY^"&J59&"^"&M59&"^"&N59 -> ;PRTY^40^CHR^180
D60: MVP | E60: MVP | G60: =IFERROR(VLOOKUP(H60,'Field Definitions'!$A$1:$S$31597,3),"") -> ARENTITY | H60: ARENBKRCONF | I60: =IFERROR(VLOOKUP(H60,'Field Definitions'!$A$1:$S$31597,2),"") -> Bankruptcy Confirmation | J60: 41 | M60: =IFERROR(VLOOKUP($H60,'Field Definitions'!$A$1:$S$31597,4),"") -> CHR | N60: =IFERROR(VLOOKUP($H60,'Field Definitions'!$A$1:$S$31597,5),"") -> 1 | O60: P | P60: P | Q60: P | R60: =IF(IFERROR(VLOOKUP($H60,'Field Definitions'!$A$1:$S$31597,8),"")=0,"",IFERROR(VLOOKUP($H60,'Field Definitions'!$A$1:$S$31597,8),"")) | S60: =IF(IFERROR(VLOOKUP($H60,'Field Definitions'!$A$1:$S$31597,9),"")=0,"",IFERROR(VLOOKUP($H60,'Field Definitions'!$A$1:$S$31597,9),"")) | T60: =IF(IFERROR(VLOOKUP($H60,'Field Definitions'!$A$1:$S$31597,10),"")=0,"",IFERROR(VLOOKUP($H60,'Field Definitions'!$A$1:$S$31597,10),"")) | U60: =IF(IFERROR(VLOOKUP($H60,'Field Definitions'!$A$1:$S$31597,12),"")=0,"",IFERROR(VLOOKUP($H60,'Field Definitions'!$A$1:$S$31597,12),"")) -> N|No|~Y|Yes|~P|Pending| | X60: =";PRTY^"&J60&"^"&M60&"^"&N60 -> ;PRTY^41^CHR^1
D61: Later | F61: Assets | G61: =IFERROR(VLOOKUP(H61,'Field Definitions'!$A$1:$S$31597,3),"") -> ARENTITY | H61: ARENASBKAC | I61: =IFERROR(VLOOKUP(H61,'Field Definitions'!$A$1:$S$31597,2),"") -> Asset Checking Bank Account # | J61: =J60+1 -> 42 | M61: =IFERROR(VLOOKUP($H61,'Field Definitions'!$A$1:$S$31597,4),"") -> CHR | N61: =IFERROR(VLOOKUP($H61,'Field Definitions'!$A$1:$S$31597,5),"") -> 30 | O61: Account#1 | P61: Account#5 | Q61: Account#3 | R61: =IF(IFERROR(VLOOKUP($H61,'Field Definitions'!$A$1:$S$31597,8),"")=0,"",IFERROR(VLOOKUP($H61,'Field Definitions'!$A$1:$S$31597,8),"")) | S61: =IF(IFERROR(VLOOKUP($H61,'Field Definitions'!$A$1:$S$31597,9),"")=0,"",IFERROR(VLOOKUP($H61,'Field Definitions'!$A$1:$S$31597,9),"")) | T61: =IF(IFERROR(VLOOKUP($H61,'Field Definitions'!$A$1:$S$31597,10),"")=0,"",IFERROR(VLOOKUP($H61,'Field Definitions'!$A$1:$S$31597,10),"")) | U61: =IF(IFERROR(VLOOKUP($H61,'Field Definitions'!$A$1:$S$31597,12),"")=0,"",IFERROR(VLOOKUP($H61,'Field Definitions'!$A$1:$S$31597,12),"")) | X61: =";PRTY^"&J61&"^"&M61&"^"&N61 -> ;PRTY^42^CHR^30
D62: Later | G62: =IFERROR(VLOOKUP(H62,'Field Definitions'!$A$1:$S$31597,3),"") -> ARENTITY | H62: ARENASBKID | I62: =IFERROR(VLOOKUP(H62,'Field Definitions'!$A$1:$S$31597,2),"") -> Asset Checking Bank ID | J62: =J61+1 -> 43 | L62: ABA Number | M62: =IFERROR(VLOOKUP($H62,'Field Definitions'!$A$1:$S$31597,4),"") -> CHR | N62: =IFERROR(VLOOKUP($H62,'Field Definitions'!$A$1:$S$31597,5),"") -> 40 | O62: 101000019 | P62: 101000019 | Q62: 101000019 | R62: =IF(IFERROR(VLOOKUP($H62,'Field Definitions'!$A$1:$S$31597,8),"")=0,"",IFERROR(VLOOKUP($H62,'Field Definitions'!$A$1:$S$31597,8),"")) | S62: =IF(IFERROR(VLOOKUP($H62,'Field Definitions'!$A$1:$S$31597,9),"")=0,"",IFERROR(VLOOKUP($H62,'Field Definitions'!$A$1:$S$31597,9),"")) | T62: =IF(IFERROR(VLOOKUP($H62,'Field Definitions'!$A$1:$S$31597,10),"")=0,"",IFERROR(VLOOKUP($H62,'Field Definitions'!$A$1:$S$31597,10),"")) -> STBANK | U62: =IF(IFERROR(VLOOKUP($H62,'Field Definitions'!$A$1:$S$31597,12),"")=0,"",IFERROR(VLOOKUP($H62,'Field Definitions'!$A$1:$S$31597,12),"")) | X62: =";PRTY^"&J62&"^"&M62&"^"&N62 -> ;PRTY^43^CHR^40
D63: Later | G63: =IFERROR(VLOOKUP(H63,'Field Definitions'!$A$1:$S$31597,3),"") -> ARENTITY | H63: ARENASBKSVAC | I63: =IFERROR(VLOOKUP(H63,'Field Definitions'!$A$1:$S$31597,2),"") -> Asset Savings Bank Acct Num | J63: =J62+1 -> 44 | M63: =IFERROR(VLOOKUP($H63,'Field Definitions'!$A$1:$S$31597,4),"") -> CHR | N63: =IFERROR(VLOOKUP($H63,'Field Definitions'!$A$1:$S$31597,5),"") -> 30 | O63: Account#2 | P63: Account#5 | Q63: Account#4 | R63: =IF(IFERROR(VLOOKUP($H63,'Field Definitions'!$A$1:$S$31597,8),"")=0,"",IFERROR(VLOOKUP($H63,'Field Definitions'!$A$1:$S$31597,8),"")) | S63: =IF(IFERROR(VLOOKUP($H63,'Field Definitions'!$A$1:$S$31597,9),"")=0,"",IFERROR(VLOOKUP($H63,'Field Definitions'!$A$1:$S$31597,9),"")) | T63: =IF(IFERROR(VLOOKUP($H63,'Field Definitions'!$A$1:$S$31597,10),"")=0,"",IFERROR(VLOOKUP($H63,'Field Definitions'!$A$1:$S$31597,10),"")) | U63: =IF(IFERROR(VLOOKUP($H63,'Field Definitions'!$A$1:$S$31597,12),"")=0,"",IFERROR(VLOOKUP($H63,'Field Definitions'!$A$1:$S$31597,12),"")) | X63: =";PRTY^"&J63&"^"&M63&"^"&N63 -> ;PRTY^44^CHR^30
D64: Later | G64: =IFERROR(VLOOKUP(H64,'Field Definitions'!$A$1:$S$31597,3),"") -> ARENTITY | H64: ARENASBKSVID | I64: =IFERROR(VLOOKUP(H64,'Field Definitions'!$A$1:$S$31597,2),"") -> Asset Savings Bank ID | J64: =J63+1 -> 45 | L64: ABA Number | M64: =IFERROR(VLOOKUP($H64,'Field Definitions'!$A$1:$S$31597,4),"") -> CHR | N64: =IFERROR(VLOOKUP($H64,'Field Definitions'!$A$1:$S$31597,5),"") -> 40 | O64: 101000019 | P64: 101000019 | Q64: 101000019 | R64: =IF(IFERROR(VLOOKUP($H64,'Field Definitions'!$A$1:$S$31597,8),"")=0,"",IFERROR(VLOOKUP($H64,'Field Definitions'!$A$1:$S$31597,8),"")) | S64: =IF(IFERROR(VLOOKUP($H64,'Field Definitions'!$A$1:$S$31597,9),"")=0,"",IFERROR(VLOOKUP($H64,'Field Definitions'!$A$1:$S$31597,9),"")) | T64: =IF(IFERROR(VLOOKUP($H64,'Field Definitions'!$A$1:$S$31597,10),"")=0,"",IFERROR(VLOOKUP($H64,'Field Definitions'!$A$1:$S$31597,10),"")) -> STBANK | U64: =IF(IFERROR(VLOOKUP($H64,'Field Definitions'!$A$1:$S$31597,12),"")=0,"",IFERROR(VLOOKUP($H64,'Field Definitions'!$A$1:$S$31597,12),"")) | X64: =";PRTY^"&J64&"^"&M64&"^"&N64 -> ;PRTY^45^CHR^40
D65: Later | G65: =IFERROR(VLOOKUP(H65,'Field Definitions'!$A$1:$S$31597,3),"") -> ARENTITY | H65: ARENASCC | I65: =IFERROR(VLOOKUP(H65,'Field Definitions'!$A$1:$S$31597,2),"") -> Charge Card | J65: =J64+1 -> 46 | L65: Type: American Express, VISA, MasterCard, etc. | M65: =IFERROR(VLOOKUP($H65,'Field Definitions'!$A$1:$S$31597,4),"") -> CHR | N65: =IFERROR(VLOOKUP($H65,'Field Definitions'!$A$1:$S$31597,5),"") -> 20 | O65: American Express | P65: American Express | Q65: American Express | R65: =IF(IFERROR(VLOOKUP($H65,'Field Definitions'!$A$1:$S$31597,8),"")=0,"",IFERROR(VLOOKUP($H65,'Field Definitions'!$A$1:$S$31597,8),"")) | S65: =IF(IFERROR(VLOOKUP($H65,'Field Definitions'!$A$1:$S$31597,9),"")=0,"",IFERROR(VLOOKUP($H65,'Field Definitions'!$A$1:$S$31597,9),"")) | T65: =IF(IFERROR(VLOOKUP($H65,'Field Definitions'!$A$1:$S$31597,10),"")=0,"",IFERROR(VLOOKUP($H65,'Field Definitions'!$A$1:$S$31597,10),"")) | U65: =IF(IFERROR(VLOOKUP($H65,'Field Definitions'!$A$1:$S$31597,12),"")=0,"",IFERROR(VLOOKUP($H65,'Field Definitions'!$A$1:$S$31597,12),"")) | X65: =";PRTY^"&J65&"^"&M65&"^"&N65 -> ;PRTY^46^CHR^20
D66: Later | G66: =IFERROR(VLOOKUP(H66,'Field Definitions'!$A$1:$S$31597,3),"") -> ARENTITY | H66: ARENASCCEX | I66: =IFERROR(VLOOKUP(H66,'Field Definitions'!$A$1:$S$31597,2),"") -> Charge Card Expiration Date | J66: =J65+1 -> 47 | M66: =IFERROR(VLOOKUP($H66,'Field Definitions'!$A$1:$S$31597,4),"") -> DATE | N66: =IFERROR(VLOOKUP($H66,'Field Definitions'!$A$1:$S$31597,5),"") -> 10 | O66: 01/01/2012 | P66: 01/01/2012 | Q66: 01/01/2012 | R66: =IF(IFERROR(VLOOKUP($H66,'Field Definitions'!$A$1:$S$31597,8),"")=0,"",IFERROR(VLOOKUP($H66,'Field Definitions'!$A$1:$S$31597,8),"")) | S66: =IF(IFERROR(VLOOKUP($H66,'Field Definitions'!$A$1:$S$31597,9),"")=0,"",IFERROR(VLOOKUP($H66,'Field Definitions'!$A$1:$S$31597,9),"")) | T66: =IF(IFERROR(VLOOKUP($H66,'Field Definitions'!$A$1:$S$31597,10),"")=0,"",IFERROR(VLOOKUP($H66,'Field Definitions'!$A$1:$S$31597,10),"")) | U66: =IF(IFERROR(VLOOKUP($H66,'Field Definitions'!$A$1:$S$31597,12),"")=0,"",IFERROR(VLOOKUP($H66,'Field Definitions'!$A$1:$S$31597,12),"")) | X66: =";PRTY^"&J66&"^"&M66&"^"&N66 -> ;PRTY^47^DATE^10
D67: Later | G67: =IFERROR(VLOOKUP(H67,'Field Definitions'!$A$1:$S$31597,3),"") -> ARENTITY | H67: ARENASCCNO | I67: =IFERROR(VLOOKUP(H67,'Field Definitions'!$A$1:$S$31597,2),"") -> Charge Card Number | J67: =J66+1 -> 48 | M67: =IFERROR(VLOOKUP($H67,'Field Definitions'!$A$1:$S$31597,4),"") -> CHR | N67: =IFERROR(VLOOKUP($H67,'Field Definitions'!$A$1:$S$31597,5),"") -> 20 | O67: 1234123412341234 | P67: 1234123412341234 | Q67: 1234123412341234 | R67: =IF(IFERROR(VLOOKUP($H67,'Field Definitions'!$A$1:$S$31597,8),"")=0,"",IFERROR(VLOOKUP($H67,'Field Definitions'!$A$1:$S$31597,8),"")) | S67: =IF(IFERROR(VLOOKUP($H67,'Field Definitions'!$A$1:$S$31597,9),"")=0,"",IFERROR(VLOOKUP($H67,'Field Definitions'!$A$1:$S$31597,9),"")) | T67: =IF(IFERROR(VLOOKUP($H67,'Field Definitions'!$A$1:$S$31597,10),"")=0,"",IFERROR(VLOOKUP($H67,'Field Definitions'!$A$1:$S$31597,10),"")) | U67: =IF(IFERROR(VLOOKUP($H67,'Field Definitions'!$A$1:$S$31597,12),"")=0,"",IFERROR(VLOOKUP($H67,'Field Definitions'!$A$1:$S$31597,12),"")) | X67: =";PRTY^"&J67&"^"&M67&"^"&N67 -> ;PRTY^48^CHR^20
D68: Later | G68: =IFERROR(VLOOKUP(H68,'Field Definitions'!$A$1:$S$31597,3),"") -> ARENTITY | H68: ARENASMISC | I68: =IFERROR(VLOOKUP(H68,'Field Definitions'!$A$1:$S$31597,2),"") -> Miscellaneous Asset Info | J68: =J67+1 -> 49 | M68: =IFERROR(VLOOKUP($H68,'Field Definitions'!$A$1:$S$31597,4),"") -> EDITOR | N68: =IFERROR(VLOOKUP($H68,'Field Definitions'!$A$1:$S$31597,5),"") -> 65 | O68: No longer good | P68: No longer good | Q68: No longer good | R68: =IF(IFERROR(VLOOKUP($H68,'Field Definitions'!$A$1:$S$31597,8),"")=0,"",IFERROR(VLOOKUP($H68,'Field Definitions'!$A$1:$S$31597,8),"")) | S68: =IF(IFERROR(VLOOKUP($H68,'Field Definitions'!$A$1:$S$31597,9),"")=0,"",IFERROR(VLOOKUP($H68,'Field Definitions'!$A$1:$S$31597,9),"")) | T68: =IF(IFERROR(VLOOKUP($H68,'Field Definitions'!$A$1:$S$31597,10),"")=0,"",IFERROR(VLOOKUP($H68,'Field Definitions'!$A$1:$S$31597,10),"")) | U68: =IF(IFERROR(VLOOKUP($H68,'Field Definitions'!$A$1:$S$31597,12),"")=0,"",IFERROR(VLOOKUP($H68,'Field Definitions'!$A$1:$S$31597,12),"")) | X68: =";PRTY^"&J68&"^"&M68&"^"&N68 -> ;PRTY^49^EDITOR^65
D69: Later | G69: =IFERROR(VLOOKUP(H69,'Field Definitions'!$A$1:$S$31597,3),"") -> ARENTITY | H69: ARENASPR | I69: =IFERROR(VLOOKUP(H69,'Field Definitions'!$A$1:$S$31597,2),"") -> Property | J69: =J68+1 -> 50 | M69: =IFERROR(VLOOKUP($H69,'Field Definitions'!$A$1:$S$31597,4),"") -> CHR | N69: =IFERROR(VLOOKUP($H69,'Field Definitions'!$A$1:$S$31597,5),"") -> 25 | O69: Home | P69: Home | Q69: Home | R69: =IF(IFERROR(VLOOKUP($H69,'Field Definitions'!$A$1:$S$31597,8),"")=0,"",IFERROR(VLOOKUP($H69,'Field Definitions'!$A$1:$S$31597,8),"")) | S69: =IF(IFERROR(VLOOKUP($H69,'Field Definitions'!$A$1:$S$31597,9),"")=0,"",IFERROR(VLOOKUP($H69,'Field Definitions'!$A$1:$S$31597,9),"")) | T69: =IF(IFERROR(VLOOKUP($H69,'Field Definitions'!$A$1:$S$31597,10),"")=0,"",IFERROR(VLOOKUP($H69,'Field Definitions'!$A$1:$S$31597,10),"")) | U69: =IF(IFERROR(VLOOKUP($H69,'Field Definitions'!$A$1:$S$31597,12),"")=0,"",IFERROR(VLOOKUP($H69,'Field Definitions'!$A$1:$S$31597,12),"")) | X69: =";PRTY^"&J69&"^"&M69&"^"&N69 -> ;PRTY^50^CHR^25
D70: Later | G70: =IFERROR(VLOOKUP(H70,'Field Definitions'!$A$1:$S$31597,3),"") -> ARENTITY | H70: ARENASPRAD | I70: =IFERROR(VLOOKUP(H70,'Field Definitions'!$A$1:$S$31597,2),"") -> Property Address | J70: =J69+1 -> 51 | M70: =IFERROR(VLOOKUP($H70,'Field Definitions'!$A$1:$S$31597,4),"") -> CHR | N70: =IFERROR(VLOOKUP($H70,'Field Definitions'!$A$1:$S$31597,5),"") -> 25 | O70: 123 Home address St | P70: 123 Home address St | Q70: 123 Home address St | R70: =IF(IFERROR(VLOOKUP($H70,'Field Definitions'!$A$1:$S$31597,8),"")=0,"",IFERROR(VLOOKUP($H70,'Field Definitions'!$A$1:$S$31597,8),"")) | S70: =IF(IFERROR(VLOOKUP($H70,'Field Definitions'!$A$1:$S$31597,9),"")=0,"",IFERROR(VLOOKUP($H70,'Field Definitions'!$A$1:$S$31597,9),"")) | T70: =IF(IFERROR(VLOOKUP($H70,'Field Definitions'!$A$1:$S$31597,10),"")=0,"",IFERROR(VLOOKUP($H70,'Field Definitions'!$A$1:$S$31597,10),"")) | U70: =IF(IFERROR(VLOOKUP($H70,'Field Definitions'!$A$1:$S$31597,12),"")=0,"",IFERROR(VLOOKUP($H70,'Field Definitions'!$A$1:$S$31597,12),"")) | X70: =";PRTY^"&J70&"^"&M70&"^"&N70 -> ;PRTY^51^CHR^25
D71: Later | G71: =IFERROR(VLOOKUP(H71,'Field Definitions'!$A$1:$S$31597,3),"") -> ARENTITY | H71: ARENASPRUNT | I71: =IFERROR(VLOOKUP(H71,'Field Definitions'!$A$1:$S$31597,2),"") -> Property Unit | J71: =J70+1 -> 52 | M71: =IFERROR(VLOOKUP($H71,'Field Definitions'!$A$1:$S$31597,4),"") -> CHR | N71: =IFERROR(VLOOKUP($H71,'Field Definitions'!$A$1:$S$31597,5),"") -> 25 | O71: Apt 123 | P71: Apt 123 | Q71: Apt 123 | R71: =IF(IFERROR(VLOOKUP($H71,'Field Definitions'!$A$1:$S$31597,8),"")=0,"",IFERROR(VLOOKUP($H71,'Field Definitions'!$A$1:$S$31597,8),"")) | S71: =IF(IFERROR(VLOOKUP($H71,'Field Definitions'!$A$1:$S$31597,9),"")=0,"",IFERROR(VLOOKUP($H71,'Field Definitions'!$A$1:$S$31597,9),"")) | T71: =IF(IFERROR(VLOOKUP($H71,'Field Definitions'!$A$1:$S$31597,10),"")=0,"",IFERROR(VLOOKUP($H71,'Field Definitions'!$A$1:$S$31597,10),"")) | U71: =IF(IFERROR(VLOOKUP($H71,'Field Definitions'!$A$1:$S$31597,12),"")=0,"",IFERROR(VLOOKUP($H71,'Field Definitions'!$A$1:$S$31597,12),"")) | X71: =";PRTY^"&J71&"^"&M71&"^"&N71 -> ;PRTY^52^CHR^25
D72: Later | G72: =IFERROR(VLOOKUP(H72,'Field Definitions'!$A$1:$S$31597,3),"") -> ARENTITY | H72: ARENASPRCTY | I72: =IFERROR(VLOOKUP(H72,'Field Definitions'!$A$1:$S$31597,2),"") -> Property City | J72: =J71+1 -> 53 | M72: =IFERROR(VLOOKUP($H72,'Field Definitions'!$A$1:$S$31597,4),"") -> CHR | N72: =IFERROR(VLOOKUP($H72,'Field Definitions'!$A$1:$S$31597,5),"") -> 20 | O72: Somecity | P72: Somecity | Q72: Somecity | R72: =IF(IFERROR(VLOOKUP($H72,'Field Definitions'!$A$1:$S$31597,8),"")=0,"",IFERROR(VLOOKUP($H72,'Field Definitions'!$A$1:$S$31597,8),"")) | S72: =IF(IFERROR(VLOOKUP($H72,'Field Definitions'!$A$1:$S$31597,9),"")=0,"",IFERROR(VLOOKUP($H72,'Field Definitions'!$A$1:$S$31597,9),"")) | T72: =IF(IFERROR(VLOOKUP($H72,'Field Definitions'!$A$1:$S$31597,10),"")=0,"",IFERROR(VLOOKUP($H72,'Field Definitions'!$A$1:$S$31597,10),"")) | U72: =IF(IFERROR(VLOOKUP($H72,'Field Definitions'!$A$1:$S$31597,12),"")=0,"",IFERROR(VLOOKUP($H72,'Field Definitions'!$A$1:$S$31597,12),"")) | X72: =";PRTY^"&J72&"^"&M72&"^"&N72 -> ;PRTY^53^CHR^20
D73: Later | G73: =IFERROR(VLOOKUP(H73,'Field Definitions'!$A$1:$S$31597,3),"") -> ARENTITY | H73: ARENASPRST | I73: =IFERROR(VLOOKUP(H73,'Field Definitions'!$A$1:$S$31597,2),"") -> Property State | J73: =J72+1 -> 54 | M73: =IFERROR(VLOOKUP($H73,'Field Definitions'!$A$1:$S$31597,4),"") -> CHR | N73: =IFERROR(VLOOKUP($H73,'Field Definitions'!$A$1:$S$31597,5),"") -> 2 | O73: IN | P73: IN | Q73: IN | R73: =IF(IFERROR(VLOOKUP($H73,'Field Definitions'!$A$1:$S$31597,8),"")=0,"",IFERROR(VLOOKUP($H73,'Field Definitions'!$A$1:$S$31597,8),"")) | S73: =IF(IFERROR(VLOOKUP($H73,'Field Definitions'!$A$1:$S$31597,9),"")=0,"",IFERROR(VLOOKUP($H73,'Field Definitions'!$A$1:$S$31597,9),"")) | T73: =IF(IFERROR(VLOOKUP($H73,'Field Definitions'!$A$1:$S$31597,10),"")=0,"",IFERROR(VLOOKUP($H73,'Field Definitions'!$A$1:$S$31597,10),"")) -> STATES | U73: =IF(IFERROR(VLOOKUP($H73,'Field Definitions'!$A$1:$S$31597,12),"")=0,"",IFERROR(VLOOKUP($H73,'Field Definitions'!$A$1:$S$31597,12),"")) | X73: =";PRTY^"&J73&"^"&M73&"^"&N73 -> ;PRTY^54^CHR^2
D74: Later | G74: =IFERROR(VLOOKUP(H74,'Field Definitions'!$A$1:$S$31597,3),"") -> ARENTITY | H74: ARENASPRZIP | I74: =IFERROR(VLOOKUP(H74,'Field Definitions'!$A$1:$S$31597,2),"") -> Property Postal Code | J74: =J73+1 -> 55 | M74: =IFERROR(VLOOKUP($H74,'Field Definitions'!$A$1:$S$31597,4),"") -> ZIP | N74: =IFERROR(VLOOKUP($H74,'Field Definitions'!$A$1:$S$31597,5),"") -> 10 | O74: 47304 | P74: 47304 | Q74: 47304 | R74: =IF(IFERROR(VLOOKUP($H74,'Field Definitions'!$A$1:$S$31597,8),"")=0,"",IFERROR(VLOOKUP($H74,'Field Definitions'!$A$1:$S$31597,8),"")) | S74: =IF(IFERROR(VLOOKUP($H74,'Field Definitions'!$A$1:$S$31597,9),"")=0,"",IFERROR(VLOOKUP($H74,'Field Definitions'!$A$1:$S$31597,9),"")) | T74: =IF(IFERROR(VLOOKUP($H74,'Field Definitions'!$A$1:$S$31597,10),"")=0,"",IFERROR(VLOOKUP($H74,'Field Definitions'!$A$1:$S$31597,10),"")) | U74: =IF(IFERROR(VLOOKUP($H74,'Field Definitions'!$A$1:$S$31597,12),"")=0,"",IFERROR(VLOOKUP($H74,'Field Definitions'!$A$1:$S$31597,12),"")) | X74: =";PRTY^"&J74&"^"&M74&"^"&N74 -> ;PRTY^55^ZIP^10
D75: Later | G75: =IFERROR(VLOOKUP(H75,'Field Definitions'!$A$1:$S$31597,3),"") -> ARENTITY | H75: ARENASAODESC | I75: =IFERROR(VLOOKUP(H75,'Field Definitions'!$A$1:$S$31597,2),"") -> Auto Description | J75: =J74+1 -> 56 | M75: =IFERROR(VLOOKUP($H75,'Field Definitions'!$A$1:$S$31597,4),"") -> CHR | N75: =IFERROR(VLOOKUP($H75,'Field Definitions'!$A$1:$S$31597,5),"") -> 30 | O75: Chevy Malibu | P75: Honda Accord | Q75: Honda Accord | R75: =IF(IFERROR(VLOOKUP($H75,'Field Definitions'!$A$1:$S$31597,8),"")=0,"",IFERROR(VLOOKUP($H75,'Field Definitions'!$A$1:$S$31597,8),"")) | S75: =IF(IFERROR(VLOOKUP($H75,'Field Definitions'!$A$1:$S$31597,9),"")=0,"",IFERROR(VLOOKUP($H75,'Field Definitions'!$A$1:$S$31597,9),"")) | T75: =IF(IFERROR(VLOOKUP($H75,'Field Definitions'!$A$1:$S$31597,10),"")=0,"",IFERROR(VLOOKUP($H75,'Field Definitions'!$A$1:$S$31597,10),"")) | U75: =IF(IFERROR(VLOOKUP($H75,'Field Definitions'!$A$1:$S$31597,12),"")=0,"",IFERROR(VLOOKUP($H75,'Field Definitions'!$A$1:$S$31597,12),"")) | X75: =";PRTY^"&J75&"^"&M75&"^"&N75 -> ;PRTY^56^CHR^30
D76: Later | G76: =IFERROR(VLOOKUP(H76,'Field Definitions'!$A$1:$S$31597,3),"") -> ARENTITY | H76: ARENASAOTAG | I76: =IFERROR(VLOOKUP(H76,'Field Definitions'!$A$1:$S$31597,2),"") -> Asset Auto Tag Number | J76: =J75+1 -> 57 | M76: =IFERROR(VLOOKUP($H76,'Field Definitions'!$A$1:$S$31597,4),"") -> CHR | N76: =IFERROR(VLOOKUP($H76,'Field Definitions'!$A$1:$S$31597,5),"") -> 20 | O76: 12 BF 1234 | P76: 12 BF 1235 | Q76: 12 BF 1235 | R76: =IF(IFERROR(VLOOKUP($H76,'Field Definitions'!$A$1:$S$31597,8),"")=0,"",IFERROR(VLOOKUP($H76,'Field Definitions'!$A$1:$S$31597,8),"")) | S76: =IF(IFERROR(VLOOKUP($H76,'Field Definitions'!$A$1:$S$31597,9),"")=0,"",IFERROR(VLOOKUP($H76,'Field Definitions'!$A$1:$S$31597,9),"")) | T76: =IF(IFERROR(VLOOKUP($H76,'Field Definitions'!$A$1:$S$31597,10),"")=0,"",IFERROR(VLOOKUP($H76,'Field Definitions'!$A$1:$S$31597,10),"")) | U76: =IF(IFERROR(VLOOKUP($H76,'Field Definitions'!$A$1:$S$31597,12),"")=0,"",IFERROR(VLOOKUP($H76,'Field Definitions'!$A$1:$S$31597,12),"")) | X76: =";PRTY^"&J76&"^"&M76&"^"&N76 -> ;PRTY^57^CHR^20
D77: Later | G77: =IFERROR(VLOOKUP(H77,'Field Definitions'!$A$1:$S$31597,3),"") -> ARENTITY | H77: ARENASAOTITLE | I77: =IFERROR(VLOOKUP(H77,'Field Definitions'!$A$1:$S$31597,2),"") -> Automobile Title | J77: =J76+1 -> 58 | M77: =IFERROR(VLOOKUP($H77,'Field Definitions'!$A$1:$S$31597,4),"") -> CHR | N77: =IFERROR(VLOOKUP($H77,'Field Definitions'!$A$1:$S$31597,5),"") -> 30 | O77: 123412341234 | P77: 123412346 | Q77: 123412346 | R77: =IF(IFERROR(VLOOKUP($H77,'Field Definitions'!$A$1:$S$31597,8),"")=0,"",IFERROR(VLOOKUP($H77,'Field Definitions'!$A$1:$S$31597,8),"")) | S77: =IF(IFERROR(VLOOKUP($H77,'Field Definitions'!$A$1:$S$31597,9),"")=0,"",IFERROR(VLOOKUP($H77,'Field Definitions'!$A$1:$S$31597,9),"")) | T77: =IF(IFERROR(VLOOKUP($H77,'Field Definitions'!$A$1:$S$31597,10),"")=0,"",IFERROR(VLOOKUP($H77,'Field Definitions'!$A$1:$S$31597,10),"")) | U77: =IF(IFERROR(VLOOKUP($H77,'Field Definitions'!$A$1:$S$31597,12),"")=0,"",IFERROR(VLOOKUP($H77,'Field Definitions'!$A$1:$S$31597,12),"")) | X77: =";PRTY^"&J77&"^"&M77&"^"&N77 -> ;PRTY^58^CHR^30
D78: Later | G78: =IFERROR(VLOOKUP(H78,'Field Definitions'!$A$1:$S$31597,3),"") -> ARENTITY | H78: ARENASAOVALUE | I78: =IFERROR(VLOOKUP(H78,'Field Definitions'!$A$1:$S$31597,2),"") -> Automobile Value | J78: =J77+1 -> 59 | M78: =IFERROR(VLOOKUP($H78,'Field Definitions'!$A$1:$S$31597,4),"") -> AMT | N78: =IFERROR(VLOOKUP($H78,'Field Definitions'!$A$1:$S$31597,5),"") -> 12 | O78: 250.00 | P78: 30231.14 | Q78: 30231.14 | R78: =IF(IFERROR(VLOOKUP($H78,'Field Definitions'!$A$1:$S$31597,8),"")=0,"",IFERROR(VLOOKUP($H78,'Field Definitions'!$A$1:$S$31597,8),"")) | S78: =IF(IFERROR(VLOOKUP($H78,'Field Definitions'!$A$1:$S$31597,9),"")=0,"",IFERROR(VLOOKUP($H78,'Field Definitions'!$A$1:$S$31597,9),"")) | T78: =IF(IFERROR(VLOOKUP($H78,'Field Definitions'!$A$1:$S$31597,10),"")=0,"",IFERROR(VLOOKUP($H78,'Field Definitions'!$A$1:$S$31597,10),"")) | U78: =IF(IFERROR(VLOOKUP($H78,'Field Definitions'!$A$1:$S$31597,12),"")=0,"",IFERROR(VLOOKUP($H78,'Field Definitions'!$A$1:$S$31597,12),"")) | X78: =";PRTY^"&J78&"^"&M78&"^"&N78 -> ;PRTY^59^AMT^12
D79: Later | H79: SourcePartyId | I79: Source Party Id | J79: =J78+1 -> 60 | L79: Note 1 | M79: CHR | N79: 50 | P79: 12341114820-1306 | X79: =";PRTY^"&J79&"^"&M79&"^"&N79 -> ;PRTY^60^CHR^50
D80: MVP | E80: MVP | G80: ARENTITY | H80: ARENLANG | I80: Language | J80: 42 | L80: Values: English, Spanish | M80: CHR | N80: 20 | O80: ENG | P80: ENG | Q80: SPA | T80: FDLANG | X80: =";PRTY^"&J80&"^"&M80&"^"&N80 -> ;PRTY^42^CHR^20
D81: NA | F81: Status Override | G81: =IFERROR(VLOOKUP(H81,'Field Definitions'!$A$1:$S$31597,3),"") -> ARRELATIONSHIP | H81: ARRELSTATUSID | I81: =IFERROR(VLOOKUP(H81,'Field Definitions'!$A$1:$S$31597,2),"") -> Status | J81: =J80+1 -> 43 | L81: Note 2 | M81: =IFERROR(VLOOKUP($H81,'Field Definitions'!$A$1:$S$31597,4),"") -> CHR | N81: =IFERROR(VLOOKUP($H81,'Field Definitions'!$A$1:$S$31597,5),"") -> 20 | P81: COLLECTION | Q81: DECEASED | R81: =IF(IFERROR(VLOOKUP($H81,'Field Definitions'!$A$1:$S$31597,8),"")=0,"",IFERROR(VLOOKUP($H81,'Field Definitions'!$A$1:$S$31597,8),"")) | S81: =IF(IFERROR(VLOOKUP($H81,'Field Definitions'!$A$1:$S$31597,9),"")=0,"",IFERROR(VLOOKUP($H81,'Field Definitions'!$A$1:$S$31597,9),"")) | T81: =IF(IFERROR(VLOOKUP($H81,'Field Definitions'!$A$1:$S$31597,10),"")=0,"",IFERROR(VLOOKUP($H81,'Field Definitions'!$A$1:$S$31597,10),"")) -> ARSTATUS | X81: =";PRTY^"&J81&"^"&M81&"^"&N81 -> ;PRTY^43^CHR^20
D82: NA | G82: =IFERROR(VLOOKUP(H82,'Field Definitions'!$A$1:$S$31597,3),"") -> ARRELATIONSHIP | H82: ARRELPHSDTE | I82: Status change date | J82: =J81+1 -> 44 | M82: =IFERROR(VLOOKUP($H82,'Field Definitions'!$A$1:$S$31597,4),"") -> DATE | N82: =IFERROR(VLOOKUP($H82,'Field Definitions'!$A$1:$S$31597,5),"") -> 10 | P82: 06/11/2013 | Q82: 01/01/2013 | R82: =IF(IFERROR(VLOOKUP($H82,'Field Definitions'!$A$1:$S$31597,8),"")=0,"",IFERROR(VLOOKUP($H82,'Field Definitions'!$A$1:$S$31597,8),"")) | S82: =IF(IFERROR(VLOOKUP($H82,'Field Definitions'!$A$1:$S$31597,9),"")=0,"",IFERROR(VLOOKUP($H82,'Field Definitions'!$A$1:$S$31597,9),"")) | T82: =IF(IFERROR(VLOOKUP($H82,'Field Definitions'!$A$1:$S$31597,10),"")=0,"",IFERROR(VLOOKUP($H82,'Field Definitions'!$A$1:$S$31597,10),"")) | X82: =";PRTY^"&J82&"^"&M82&"^"&N82 -> ;PRTY^44^DATE^10
D83: NA | G83: =IFERROR(VLOOKUP(H83,'Field Definitions'!$A$1:$S$31597,3),"") -> ARRELATIONSHIP | H83: ARRELWAITDTE | I83: =IFERROR(VLOOKUP(H83,'Field Definitions'!$A$1:$S$31597,2),"") -> Follow-up Date | J83: =J82+1 -> 45 | L83: Note 3 | M83: =IFERROR(VLOOKUP($H83,'Field Definitions'!$A$1:$S$31597,4),"") -> DATE | N83: =IFERROR(VLOOKUP($H83,'Field Definitions'!$A$1:$S$31597,5),"") -> 10 | P83: 06/11/2014 | R83: =IF(IFERROR(VLOOKUP($H83,'Field Definitions'!$A$1:$S$31597,8),"")=0,"",IFERROR(VLOOKUP($H83,'Field Definitions'!$A$1:$S$31597,8),"")) | S83: =IF(IFERROR(VLOOKUP($H83,'Field Definitions'!$A$1:$S$31597,9),"")=0,"",IFERROR(VLOOKUP($H83,'Field Definitions'!$A$1:$S$31597,9),"")) | T83: =IF(IFERROR(VLOOKUP($H83,'Field Definitions'!$A$1:$S$31597,10),"")=0,"",IFERROR(VLOOKUP($H83,'Field Definitions'!$A$1:$S$31597,10),"")) | X83: =";PRTY^"&J83&"^"&M83&"^"&N83 -> ;PRTY^45^DATE^10
D84: NA | G84: =IFERROR(VLOOKUP(H84,'Field Definitions'!$A$1:$S$31597,3),"") -> ARRELATIONSHIP | H84: ARRELUSERID | I84: =IFERROR(VLOOKUP(H84,'Field Definitions'!$A$1:$S$31597,2),"") -> Relationship user | J84: =J83+1 -> 46 | M84: =IFERROR(VLOOKUP($H84,'Field Definitions'!$A$1:$S$31597,4),"") -> CHR | N84: =IFERROR(VLOOKUP($H84,'Field Definitions'!$A$1:$S$31597,5),"") -> 4 | P84: LOW | R84: =IF(IFERROR(VLOOKUP($H84,'Field Definitions'!$A$1:$S$31597,8),"")=0,"",IFERROR(VLOOKUP($H84,'Field Definitions'!$A$1:$S$31597,8),"")) | S84: =IF(IFERROR(VLOOKUP($H84,'Field Definitions'!$A$1:$S$31597,9),"")=0,"",IFERROR(VLOOKUP($H84,'Field Definitions'!$A$1:$S$31597,9),"")) | T84: =IF(IFERROR(VLOOKUP($H84,'Field Definitions'!$A$1:$S$31597,10),"")=0,"",IFERROR(VLOOKUP($H84,'Field Definitions'!$A$1:$S$31597,10),"")) -> STUSER | X84: =";PRTY^"&J84&"^"&M84&"^"&N84 -> ;PRTY^46^CHR^4
D85: NA | G85: ARENTITY | H85: ARENSLEDIANKEY | I85: =IFERROR(VLOOKUP(H85,'Field Definitions'!$A$1:$S$31597,2),"") -> Dept of ED IAN Key | J85: =J84+1 -> 47 | X85: =";PRTY^"&J85&"^"&M85&"^"&N85 -> ;PRTY^47^^
D86: NA | G86: ARENTITY | H86: ARENADRSOURCE | I86: =IFERROR(VLOOKUP(H86,'Field Definitions'!$A$1:$S$31597,2),"") -> Address Source | J86: =J85+1 -> 48 | X86: =";PRTY^"&J86&"^"&M86&"^"&N86 -> ;PRTY^48^^
D87: Later | F87: Student Loan | G87: ARENTITY | H87: ARENFAUXSSN | I87: =IFERROR(VLOOKUP(H87,'Field Definitions'!$A$1:$S$31597,2),"") -> Faux SSN | J87: =J86+1 -> 49 | X87: =";PRTY^"&J87&"^"&M87&"^"&N87 -> ;PRTY^49^^
D88: Later | G88: ARENTITY | H88: ARENADRSTATUS | I88: =IFERROR(VLOOKUP(H88,'Field Definitions'!$A$1:$S$31597,2),"") -> Address Status | J88: =J87+1 -> 50 | X88: =";PRTY^"&J88&"^"&M88&"^"&N88 -> ;PRTY^50^^
D89: Later | G89: ARENTITY | H89: ARENREGIONCODE | I89: =IFERROR(VLOOKUP(H89,'Field Definitions'!$A$1:$S$31597,2),"") -> Account Region Code (A Record) | J89: =J88+1 -> 51 | X89: =";PRTY^"&J89&"^"&M89&"^"&N89 -> ;PRTY^51^^
D90: Later | G90: ARENTITY | H90: ARENAGYLOCATION | I90: =IFERROR(VLOOKUP(H90,'Field Definitions'!$A$1:$S$31597,2),"") -> Coll Agency Location Code | J90: =J89+1 -> 52 | X90: =";PRTY^"&J90&"^"&M90&"^"&N90 -> ;PRTY^52^^
D91: Later | G91: ARENTITY | H91: ARENDAYSDELQ | I91: =IFERROR(VLOOKUP(H91,'Field Definitions'!$A$1:$S$31597,2),"") -> Days Delinquent | J91: =J90+1 -> 53 | X91: =";PRTY^"&J91&"^"&M91&"^"&N91 -> ;PRTY^53^^
D92: Later | G92: ARENTITY | H92: ARENDAYSNOTPD | I92: =IFERROR(VLOOKUP(H92,'Field Definitions'!$A$1:$S$31597,2),"") -> Days Not Paid | J92: =J91+1 -> 54 | X92: =";PRTY^"&J92&"^"&M92&"^"&N92 -> ;PRTY^54^^
D93: Later | G93: ARENTITY | H93: ARENNUMDEBTS | I93: =IFERROR(VLOOKUP(H93,'Field Definitions'!$A$1:$S$31597,2),"") -> Number of Debts | J93: =J92+1 -> 55 | X93: =";PRTY^"&J93&"^"&M93&"^"&N93 -> ;PRTY^55^^
D94: MVP | E94: MVP | F94: Bankruptcy Legal Entity | G94: ARENTITYLGL | H94: ARENLGLTYPE | I94: Type | J94: 43 | M94: CHR | N94: 15 | O94: BANKRUPTCY | U94: BANKRUPTCY|Bankruptcy|~PROBATE|Probate|~LITIGATION|Litigation| | X94: =";PRTY^"&J94&"^"&M94&"^"&N94 -> ;PRTY^43^CHR^15
D95: MVP | E95: MVP | G95: ARENTITY | H95: ARENBKRVERDATE | I95: Bankruptcty Verification Date | J95: 44 | M95: DATE | N95: 10 | O95: 02/08/2009 | X95: =";PRTY^"&J95&"^"&M95&"^"&N95 -> ;PRTY^44^DATE^10
D96: MVP | E96: MVP | G96: ARENTITYLGL | H96: ARENLGL341HASINFO | I96: Has 341 Info? | J96: 45 | M96: CHR | N96: 1 | O96: Y | U96: Y|Yes|~N|No| | X96: =";PRTY^"&J96&"^"&M96&"^"&N96 -> ;PRTY^45^CHR^1
D97: MVP | E97: MVP | G97: ARENTITYLGL | H97: ARENLGL341DATE | I97: 341 Date | J97: 46 | M97: DATE | N97: 10 | O97: 01/29/2009 | X97: =";PRTY^"&J97&"^"&M97&"^"&N97 -> ;PRTY^46^DATE^10
D98: MVP | E98: MVP | G98: ARENTITYLGL | H98: ARENLGL341LOCATION | I98: 341 Location | J98: 47 | M98: CHR | N98: 100 | O98: Somewhere | X98: =";PRTY^"&J98&"^"&M98&"^"&N98 -> ;PRTY^47^CHR^100
D99: MVP | E99: MVP | G99: ARENTITYLGL | H99: ARENLGL341TIME | I99: 341 Time | J99: 48 | M99: TIME | N99: 6 | O99: 10:00 | X99: =";PRTY^"&J99&"^"&M99&"^"&N99 -> ;PRTY^48^TIME^6
D100: MVP | E100: MVP | G100: ARENTITYLGL | H100: ARENLGLCRTNAME | I100: Court Name | J100: 49 | M100: CHR | N100: 80 | O100: A Court | X100: =";PRTY^"&J100&"^"&M100&"^"&N100 -> ;PRTY^49^CHR^80
...

Sheet PHN
A1: Source | D1: SaaS mapping/ timeline | E1: =COUNTIF(D6:D78,"MVP")-COUNTIF(E6:E78,"MVP") -> 13 | G1: Destination
A2: FACS | B2: TCS | E2: In Migration Import? | G2: Table | H2: Column | I2: Description | J2: Position | K2: Required? | L2: Instructions | M2: Data Type | N2: Length | O2: 20 | P2: 20 | Q2: 20 | R2: Min | S2: Max | T2: Foreign Table | U2: Validation
D3: MVP | I3: Rec ID = PHN | J3: 1 | K3: Yes | X3: =";PHN^"&J3&"^"&M3&"^"&N3 -> ;PHN^1^^
D4: MVP | I4: Account_ID | J4: 2 | K4: Yes | X4: =";PHN^"&J4&"^"&M4&"^"&N4 -> ;PHN^2^^
D5: MVP | I5: Consumer_ID | J5: 3 | K5: Yes | L5: Values: P, SE, S, C, G, PA, PR, D, E, N, A | X5: =";PHN^"&J5&"^"&M5&"^"&N5 -> ;PHN^3^^
D6: . | F6: Core | G6: =IFERROR(VLOOKUP(H6,'Field Definitions'!$A$1:$S$31597,3),"") -> ARRELATIONSHIP | H6: ARRELTYPID | I6: =IFERROR(VLOOKUP(H6,'Field Definitions'!$A$1:$S$31597,2),"") -> Relationship type key | J6: 2 | K6: Yes | L6: For multiple co-makers use COMAK_1, COMAK_2, etc. | M6: =IFERROR(VLOOKUP($H6,'Field Definitions'!$A$1:$S$31597,4),"") -> CHR | N6: =IFERROR(VLOOKUP($H6,'Field Definitions'!$A$1:$S$31597,5),"") -> 10 | O6: PRIM | P6: COMAK_1 | Q6: SPOUSE | R6: =IF(IFERROR(VLOOKUP($H6,'Field Definitions'!$A$1:$S$31597,8),"")=0,"",IFERROR(VLOOKUP($H6,'Field Definitions'!$A$1:$S$31597,8),"")) | S6: =IF(IFERROR(VLOOKUP($H6,'Field Definitions'!$A$1:$S$31597,9),"")=0,"",IFERROR(VLOOKUP($H6,'Field Definitions'!$A$1:$S$31597,9),"")) | T6: =IF(IFERROR(VLOOKUP($H6,'Field Definitions'!$A$1:$S$31597,10),"")=0,"",IFERROR(VLOOKUP($H6,'Field Definitions'!$A$1:$S$31597,10),"")) -> ARRELTYPE | U6: AUTH|Authorized User|~BUSINESS|Business|AR43360~COMAK|Comaker|AR13409~DEPEND|Dependent|AR13410~EXEC|Executor|AR43575~GUAR|Guarantor|AR43574~OWNER|Business Owner|AR43359~PRIM|Primary Responsible Party|AR13411~SPOUSE|Spouse|AR13412~
D7: MVP | G7: ARPHONE | H7: ARPHPHONE | I7: =IFERROR(VLOOKUP(H7,'Field Definitions'!$A$1:$S$31597,2),"") -> Phone Number | J7: 4 | K7: Yes | M7: =IFERROR(VLOOKUP($H7,'Field Definitions'!$A$1:$S$31597,4),"") -> PHONE | N7: 20 | O7: 7655552223 | P7: 7655551111 | Q7: 7655552244 | R7: =IF(IFERROR(VLOOKUP($H7,'Field Definitions'!$A$1:$S$31597,8),"")=0,"",IFERROR(VLOOKUP($H7,'Field Definitions'!$A$1:$S$31597,8),"")) | S7: =IF(IFERROR(VLOOKUP($H7,'Field Definitions'!$A$1:$S$31597,9),"")=0,"",IFERROR(VLOOKUP($H7,'Field Definitions'!$A$1:$S$31597,9),"")) | T7: =IF(IFERROR(VLOOKUP($H7,'Field Definitions'!$A$1:$S$31597,10),"")=0,"",IFERROR(VLOOKUP($H7,'Field Definitions'!$A$1:$S$31597,10),"")) | U7: =IF(IFERROR(VLOOKUP($H7,'Field Definitions'!$A$1:$S$31597,12),"")=0,"",IFERROR(VLOOKUP($H7,'Field Definitions'!$A$1:$S$31597,12),"")) | X7: =";PHN^"&J7&"^"&M7&"^"&N7 -> ;PHN^4^PHONE^20
D8: MVP | G8: ARPHONE | H8: ARPHEXT | I8: =IFERROR(VLOOKUP(H8,'Field Definitions'!$A$1:$S$31597,2),"") -> Extension | J8: 5 | M8: =IFERROR(VLOOKUP($H8,'Field Definitions'!$A$1:$S$31597,4),"") -> CHR | N8: =IFERROR(VLOOKUP($H8,'Field Definitions'!$A$1:$S$31597,5),"") -> 10 | O8: 333 | P8: Firstname | R8: =IF(IFERROR(VLOOKUP($H8,'Field Definitions'!$A$1:$S$31597,8),"")=0,"",IFERROR(VLOOKUP($H8,'Field Definitions'!$A$1:$S$31597,8),"")) | S8: =IF(IFERROR(VLOOKUP($H8,'Field Definitions'!$A$1:$S$31597,9),"")=0,"",IFERROR(VLOOKUP($H8,'Field Definitions'!$A$1:$S$31597,9),"")) | T8: =IF(IFERROR(VLOOKUP($H8,'Field Definitions'!$A$1:$S$31597,10),"")=0,"",IFERROR(VLOOKUP($H8,'Field Definitions'!$A$1:$S$31597,10),"")) | U8: =IF(IFERROR(VLOOKUP($H8,'Field Definitions'!$A$1:$S$31597,12),"")=0,"",IFERROR(VLOOKUP($H8,'Field Definitions'!$A$1:$S$31597,12),"")) | X8: =";PHN^"&J8&"^"&M8&"^"&N8 -> ;PHN^5^CHR^10
D9: MVP | G9: ARPHONE | H9: ARPHTYPE | I9: =IFERROR(VLOOKUP(H9,'Field Definitions'!$A$1:$S$31597,2),"") -> Type | J9: 6 | K9: Yes | L9: Values: Home, Work, Mobile, Other | M9: =IFERROR(VLOOKUP($H9,'Field Definitions'!$A$1:$S$31597,4),"") -> CHR | N9: =IFERROR(VLOOKUP($H9,'Field Definitions'!$A$1:$S$31597,5),"") -> 20 | O9: WORK | P9: MOBILE | R9: =IF(IFERROR(VLOOKUP($H9,'Field Definitions'!$A$1:$S$31597,8),"")=0,"",IFERROR(VLOOKUP($H9,'Field Definitions'!$A$1:$S$31597,8),"")) | S9: =IF(IFERROR(VLOOKUP($H9,'Field Definitions'!$A$1:$S$31597,9),"")=0,"",IFERROR(VLOOKUP($H9,'Field Definitions'!$A$1:$S$31597,9),"")) | T9: ARFLDVAL.ARFVKEY = ARPHTYPE | U9: BUSINESS|Business|FAX|Fax|HOME|Home|MOBILE|Mobile|OTHER|Other|WORK|Work | X9: =";PHN^"&J9&"^"&M9&"^"&N9 -> ;PHN^6^CHR^20
D10: MVP | G10: ARPHONE | H10: ARPHMAPKEY | I10: =IFERROR(VLOOKUP(H10,'Field Definitions'!$A$1:$S$31597,2),"") -> Map Key | J10: 7 | L10: Not used. UseAs field on the User Interface | M10: =IFERROR(VLOOKUP($H10,'Field Definitions'!$A$1:$S$31597,4),"") -> CHR | N10: =IFERROR(VLOOKUP($H10,'Field Definitions'!$A$1:$S$31597,5),"") -> 999 | O10: POE | P10: PRIM | Q10: TERTIARY | R10: =IF(IFERROR(VLOOKUP($H10,'Field Definitions'!$A$1:$S$31597,8),"")=0,"",IFERROR(VLOOKUP($H10,'Field Definitions'!$A$1:$S$31597,8),"")) | S10: =IF(IFERROR(VLOOKUP($H10,'Field Definitions'!$A$1:$S$31597,9),"")=0,"",IFERROR(VLOOKUP($H10,'Field Definitions'!$A$1:$S$31597,9),"")) | T10: ARPHONEMAP | U10: NONE|POE|PRIMARY|SECONDARY|TERTIARY | X10: =";PHN^"&J10&"^"&M10&"^"&N10 -> ;PHN^7^CHR^999
D11: . | G11: ARCELLPHCNST | H11: ARCELLPHCNSTFLAG | I11: =IFERROR(VLOOKUP(H11,'Field Definitions'!$A$1:$S$31597,2),"") -> Consent? | M11: =IFERROR(VLOOKUP($H11,'Field Definitions'!$A$1:$S$31597,4),"") -> CHR | N11: =IFERROR(VLOOKUP($H11,'Field Definitions'!$A$1:$S$31597,5),"") -> 1 | Q11: N | R11: =IF(IFERROR(VLOOKUP($H11,'Field Definitions'!$A$1:$S$31597,8),"")=0,"",IFERROR(VLOOKUP($H11,'Field Definitions'!$A$1:$S$31597,8),"")) | S11: =IF(IFERROR(VLOOKUP($H11,'Field Definitions'!$A$1:$S$31597,9),"")=0,"",IFERROR(VLOOKUP($H11,'Field Definitions'!$A$1:$S$31597,9),"")) | T11: =IF(IFERROR(VLOOKUP($H11,'Field Definitions'!$A$1:$S$31597,10),"")=0,"",IFERROR(VLOOKUP($H11,'Field Definitions'!$A$1:$S$31597,10),"")) | U11: =IF(IFERROR(VLOOKUP($H11,'Field Definitions'!$A$1:$S$31597,12),"")=0,"",IFERROR(VLOOKUP($H11,'Field Definitions'!$A$1:$S$31597,12),"")) -> N|No consent to autodial|~Y|Consent to autodial| | X11: =";PHN^"&J11&"^"&M11&"^"&N11 -> ;PHN^^CHR^1
D12: . | G12: ARPHONE | H12: ARPHBAD | I12: =IFERROR(VLOOKUP(H12,'Field Definitions'!$A$1:$S$31597,2),"") -> Is Bad? | M12: =IFERROR(VLOOKUP($H12,'Field Definitions'!$A$1:$S$31597,4),"") -> CHR | N12: =IFERROR(VLOOKUP($H12,'Field Definitions'!$A$1:$S$31597,5),"") -> 1 | Q12: Y | R12: =IF(IFERROR(VLOOKUP($H12,'Field Definitions'!$A$1:$S$31597,8),"")=0,"",IFERROR(VLOOKUP($H12,'Field Definitions'!$A$1:$S$31597,8),"")) | S12: =IF(IFERROR(VLOOKUP($H12,'Field Definitions'!$A$1:$S$31597,9),"")=0,"",IFERROR(VLOOKUP($H12,'Field Definitions'!$A$1:$S$31597,9),"")) | T12: =IF(IFERROR(VLOOKUP($H12,'Field Definitions'!$A$1:$S$31597,10),"")=0,"",IFERROR(VLOOKUP($H12,'Field Definitions'!$A$1:$S$31597,10),"")) | U12: =IF(IFERROR(VLOOKUP($H12,'Field Definitions'!$A$1:$S$31597,12),"")=0,"",IFERROR(VLOOKUP($H12,'Field Definitions'!$A$1:$S$31597,12),"")) -> Y|Yes|~N|No| | X12: =";PHN^"&J12&"^"&M12&"^"&N12 -> ;PHN^^CHR^1
D13: . | G13: ARPHONE | H13: ARPHCEASE | I13: =IFERROR(VLOOKUP(H13,'Field Definitions'!$A$1:$S$31597,2),"") -> Cease Communication? | M13: =IFERROR(VLOOKUP($H13,'Field Definitions'!$A$1:$S$31597,4),"") -> CHR | N13: =IFERROR(VLOOKUP($H13,'Field Definitions'!$A$1:$S$31597,5),"") -> 1 | Q13: Y | R13: =IF(IFERROR(VLOOKUP($H13,'Field Definitions'!$A$1:$S$31597,8),"")=0,"",IFERROR(VLOOKUP($H13,'Field Definitions'!$A$1:$S$31597,8),"")) | S13: =IF(IFERROR(VLOOKUP($H13,'Field Definitions'!$A$1:$S$31597,9),"")=0,"",IFERROR(VLOOKUP($H13,'Field Definitions'!$A$1:$S$31597,9),"")) | T13: =IF(IFERROR(VLOOKUP($H13,'Field Definitions'!$A$1:$S$31597,10),"")=0,"",IFERROR(VLOOKUP($H13,'Field Definitions'!$A$1:$S$31597,10),"")) | U13: =IF(IFERROR(VLOOKUP($H13,'Field Definitions'!$A$1:$S$31597,12),"")=0,"",IFERROR(VLOOKUP($H13,'Field Definitions'!$A$1:$S$31597,12),"")) -> Y|Yes|~N|No| | X13: =";PHN^"&J13&"^"&M13&"^"&N13 -> ;PHN^^CHR^1
D14: . | G14: ARPHONE | H14: ARPHEXHAUSTED | I14: =IFERROR(VLOOKUP(H14,'Field Definitions'!$A$1:$S$31597,2),"") -> Exhausted? | M14: =IFERROR(VLOOKUP($H14,'Field Definitions'!$A$1:$S$31597,4),"") -> CHR | N14: =IFERROR(VLOOKUP($H14,'Field Definitions'!$A$1:$S$31597,5),"") -> 1 | Q14: Y | R14: =IF(IFERROR(VLOOKUP($H14,'Field Definitions'!$A$1:$S$31597,8),"")=0,"",IFERROR(VLOOKUP($H14,'Field Definitions'!$A$1:$S$31597,8),"")) | S14: =IF(IFERROR(VLOOKUP($H14,'Field Definitions'!$A$1:$S$31597,9),"")=0,"",IFERROR(VLOOKUP($H14,'Field Definitions'!$A$1:$S$31597,9),"")) | T14: =IF(IFERROR(VLOOKUP($H14,'Field Definitions'!$A$1:$S$31597,10),"")=0,"",IFERROR(VLOOKUP($H14,'Field Definitions'!$A$1:$S$31597,10),"")) | U14: =IF(IFERROR(VLOOKUP($H14,'Field Definitions'!$A$1:$S$31597,12),"")=0,"",IFERROR(VLOOKUP($H14,'Field Definitions'!$A$1:$S$31597,12),"")) -> Y|Yes|~N|No| | X14: =";PHN^"&J14&"^"&M14&"^"&N14 -> ;PHN^^CHR^1
D15: . | G15: ARPHNMIGDATA | H15: Remaining Layout to Match ARCUSTMIGFIELDMAP | J15: 11-#### | L15: Add as many comma separated field paces as needed. The import will dynamically map to all provided fields. | R15: =IF(IFERROR(VLOOKUP($H15,'Field Definitions'!$A$1:$S$31597,8),"")=0,"",IFERROR(VLOOKUP($H15,'Field Definitions'!$A$1:$S$31597,8),"")) | S15: =IF(IFERROR(VLOOKUP($H15,'Field Definitions'!$A$1:$S$31597,9),"")=0,"",IFERROR(VLOOKUP($H15,'Field Definitions'!$A$1:$S$31597,9),"")) -> 4 | T15: =IF(IFERROR(VLOOKUP($H15,'Field Definitions'!$A$1:$S$31597,10),"")=0,"",IFERROR(VLOOKUP($H15,'Field Definitions'!$A$1:$S$31597,10),"")) | U15: =IF(IFERROR(VLOOKUP($H15,'Field Definitions'!$A$1:$S$31597,12),"")=0,"",IFERROR(VLOOKUP($H15,'Field Definitions'!$A$1:$S$31597,12),"")) | X15: =";PHN^"&J15&"^"&M15&"^"&N15 -> ;PHN^11-####^^
D16: MVP | I16: Phone status | J16: 8 | L16: Values: UNVERIFIED, VERIFIED, BAD, WRONG, GOOD, UNKNOWN, NEVERCALL | M16: =IFERROR(VLOOKUP($H16,'Field Definitions'!$A$1:$S$31597,4),"") | R16: =IF(IFERROR(VLOOKUP($H16,'Field Definitions'!$A$1:$S$31597,8),"")=0,"",IFERROR(VLOOKUP($H16,'Field Definitions'!$A$1:$S$31597,8),"")) | S16: =IF(IFERROR(VLOOKUP($H16,'Field Definitions'!$A$1:$S$31597,9),"")=0,"",IFERROR(VLOOKUP($H16,'Field Definitions'!$A$1:$S$31597,9),"")) | T16: =IF(IFERROR(VLOOKUP($H16,'Field Definitions'!$A$1:$S$31597,10),"")=0,"",IFERROR(VLOOKUP($H16,'Field Definitions'!$A$1:$S$31597,10),"")) | U16: =IF(IFERROR(VLOOKUP($H16,'Field Definitions'!$A$1:$S$31597,12),"")=0,"",IFERROR(VLOOKUP($H16,'Field Definitions'!$A$1:$S$31597,12),"")) | X16: =";PHN^"&J16&"^"&M16&"^"&N16 -> ;PHN^8^^
D17: MVP | I17: Call Consent | J17: 9 | L17: Values: Y, N | M17: CHR | R17: =IF(IFERROR(VLOOKUP($H17,'Field Definitions'!$A$1:$S$31597,8),"")=0,"",IFERROR(VLOOKUP($H17,'Field Definitions'!$A$1:$S$31597,8),"")) | S17: =IF(IFERROR(VLOOKUP($H17,'Field Definitions'!$A$1:$S$31597,9),"")=0,"",IFERROR(VLOOKUP($H17,'Field Definitions'!$A$1:$S$31597,9),"")) | T17: =IF(IFERROR(VLOOKUP($H17,'Field Definitions'!$A$1:$S$31597,10),"")=0,"",IFERROR(VLOOKUP($H17,'Field Definitions'!$A$1:$S$31597,10),"")) | U17: =IF(IFERROR(VLOOKUP($H17,'Field Definitions'!$A$1:$S$31597,12),"")=0,"",IFERROR(VLOOKUP($H17,'Field Definitions'!$A$1:$S$31597,12),"")) | X17: =";PHN^"&J17&"^"&M17&"^"&N17 -> ;PHN^9^CHR^
D18: MVP | I18: Call Consent Date | J18: 10 | M18: =IFERROR(VLOOKUP($H18,'Field Definitions'!$A$1:$S$31597,4),"") | R18: =IF(IFERROR(VLOOKUP($H18,'Field Definitions'!$A$1:$S$31597,8),"")=0,"",IFERROR(VLOOKUP($H18,'Field Definitions'!$A$1:$S$31597,8),"")) | S18: =IF(IFERROR(VLOOKUP($H18,'Field Definitions'!$A$1:$S$31597,9),"")=0,"",IFERROR(VLOOKUP($H18,'Field Definitions'!$A$1:$S$31597,9),"")) | T18: =IF(IFERROR(VLOOKUP($H18,'Field Definitions'!$A$1:$S$31597,10),"")=0,"",IFERROR(VLOOKUP($H18,'Field Definitions'!$A$1:$S$31597,10),"")) | U18: =IF(IFERROR(VLOOKUP($H18,'Field Definitions'!$A$1:$S$31597,12),"")=0,"",IFERROR(VLOOKUP($H18,'Field Definitions'!$A$1:$S$31597,12),"")) | X18: =";PHN^"&J18&"^"&M18&"^"&N18 -> ;PHN^10^^
D19: MVP | I19: SMS Consent | J19: 11 | L19: Values: Y, N | M19: CHR | R19: =IF(IFERROR(VLOOKUP($H19,'Field Definitions'!$A$1:$S$31597,8),"")=0,"",IFERROR(VLOOKUP($H19,'Field Definitions'!$A$1:$S$31597,8),"")) | S19: =IF(IFERROR(VLOOKUP($H19,'Field Definitions'!$A$1:$S$31597,9),"")=0,"",IFERROR(VLOOKUP($H19,'Field Definitions'!$A$1:$S$31597,9),"")) | T19: =IF(IFERROR(VLOOKUP($H19,'Field Definitions'!$A$1:$S$31597,10),"")=0,"",IFERROR(VLOOKUP($H19,'Field Definitions'!$A$1:$S$31597,10),"")) | U19: =IF(IFERROR(VLOOKUP($H19,'Field Definitions'!$A$1:$S$31597,12),"")=0,"",IFERROR(VLOOKUP($H19,'Field Definitions'!$A$1:$S$31597,12),"")) | X19: =";PHN^"&J19&"^"&M19&"^"&N19 -> ;PHN^11^CHR^
D20: MVP | I20: SMS Consent Date | J20: 12 | M20: =IFERROR(VLOOKUP($H20,'Field Definitions'!$A$1:$S$31597,4),"") | R20: =IF(IFERROR(VLOOKUP($H20,'Field Definitions'!$A$1:$S$31597,8),"")=0,"",IFERROR(VLOOKUP($H20,'Field Definitions'!$A$1:$S$31597,8),"")) | S20: =IF(IFERROR(VLOOKUP($H20,'Field Definitions'!$A$1:$S$31597,9),"")=0,"",IFERROR(VLOOKUP($H20,'Field Definitions'!$A$1:$S$31597,9),"")) | T20: =IF(IFERROR(VLOOKUP($H20,'Field Definitions'!$A$1:$S$31597,10),"")=0,"",IFERROR(VLOOKUP($H20,'Field Definitions'!$A$1:$S$31597,10),"")) | U20: =IF(IFERROR(VLOOKUP($H20,'Field Definitions'!$A$1:$S$31597,12),"")=0,"",IFERROR(VLOOKUP($H20,'Field Definitions'!$A$1:$S$31597,12),"")) | X20: =";PHN^"&J20&"^"&M20&"^"&N20 -> ;PHN^12^^
D21: MVP | I21: Pre-Recorded Msg Consent | J21: 13 | L21: Values: Y, N | M21: CHR | R21: =IF(IFERROR(VLOOKUP($H21,'Field Definitions'!$A$1:$S$31597,8),"")=0,"",IFERROR(VLOOKUP($H21,'Field Definitions'!$A$1:$S$31597,8),"")) | S21: =IF(IFERROR(VLOOKUP($H21,'Field Definitions'!$A$1:$S$31597,9),"")=0,"",IFERROR(VLOOKUP($H21,'Field Definitions'!$A$1:$S$31597,9),"")) | T21: =IF(IFERROR(VLOOKUP($H21,'Field Definitions'!$A$1:$S$31597,10),"")=0,"",IFERROR(VLOOKUP($H21,'Field Definitions'!$A$1:$S$31597,10),"")) | U21: =IF(IFERROR(VLOOKUP($H21,'Field Definitions'!$A$1:$S$31597,12),"")=0,"",IFERROR(VLOOKUP($H21,'Field Definitions'!$A$1:$S$31597,12),"")) | X21: =";PHN^"&J21&"^"&M21&"^"&N21 -> ;PHN^13^CHR^
D22: MVP | I22: Pre-Recorded Msg Consent Date | J22: 14 | M22: =IFERROR(VLOOKUP($H22,'Field Definitions'!$A$1:$S$31597,4),"") | R22: =IF(IFERROR(VLOOKUP($H22,'Field Definitions'!$A$1:$S$31597,8),"")=0,"",IFERROR(VLOOKUP($H22,'Field Definitions'!$A$1:$S$31597,8),"")) | S22: =IF(IFERROR(VLOOKUP($H22,'Field Definitions'!$A$1:$S$31597,9),"")=0,"",IFERROR(VLOOKUP($H22,'Field Definitions'!$A$1:$S$31597,9),"")) | T22: =IF(IFERROR(VLOOKUP($H22,'Field Definitions'!$A$1:$S$31597,10),"")=0,"",IFERROR(VLOOKUP($H22,'Field Definitions'!$A$1:$S$31597,10),"")) | U22: =IF(IFERROR(VLOOKUP($H22,'Field Definitions'!$A$1:$S$31597,12),"")=0,"",IFERROR(VLOOKUP($H22,'Field Definitions'!$A$1:$S$31597,12),"")) | X22: =";PHN^"&J22&"^"&M22&"^"&N22 -> ;PHN^14^^
D23: MVP | I23: Artificial Voice Consent | J23: 15 | L23: Values: Y, N | M23: CHR | R23: =IF(IFERROR(VLOOKUP($H23,'Field Definitions'!$A$1:$S$31597,8),"")=0,"",IFERROR(VLOOKUP($H23,'Field Definitions'!$A$1:$S$31597,8),"")) | S23: =IF(IFERROR(VLOOKUP($H23,'Field Definitions'!$A$1:$S$31597,9),"")=0,"",IFERROR(VLOOKUP($H23,'Field Definitions'!$A$1:$S$31597,9),"")) | T23: =IF(IFERROR(VLOOKUP($H23,'Field Definitions'!$A$1:$S$31597,10),"")=0,"",IFERROR(VLOOKUP($H23,'Field Definitions'!$A$1:$S$31597,10),"")) | U23: =IF(IFERROR(VLOOKUP($H23,'Field Definitions'!$A$1:$S$31597,12),"")=0,"",IFERROR(VLOOKUP($H23,'Field Definitions'!$A$1:$S$31597,12),"")) | X23: =";PHN^"&J23&"^"&M23&"^"&N23 -> ;PHN^15^CHR^
D24: MVP | I24: Artificial Voice Consent Date | J24: 16 | M24: =IFERROR(VLOOKUP($H24,'Field Definitions'!$A$1:$S$31597,4),"") | R24: =IF(IFERROR(VLOOKUP($H24,'Field Definitions'!$A$1:$S$31597,8),"")=0,"",IFERROR(VLOOKUP($H24,'Field Definitions'!$A$1:$S$31597,8),"")) | S24: =IF(IFERROR(VLOOKUP($H24,'Field Definitions'!$A$1:$S$31597,9),"")=0,"",IFERROR(VLOOKUP($H24,'Field Definitions'!$A$1:$S$31597,9),"")) | T24: =IF(IFERROR(VLOOKUP($H24,'Field Definitions'!$A$1:$S$31597,10),"")=0,"",IFERROR(VLOOKUP($H24,'Field Definitions'!$A$1:$S$31597,10),"")) | U24: =IF(IFERROR(VLOOKUP($H24,'Field Definitions'!$A$1:$S$31597,12),"")=0,"",IFERROR(VLOOKUP($H24,'Field Definitions'!$A$1:$S$31597,12),"")) | X24: =";PHN^"&J24&"^"&M24&"^"&N24 -> ;PHN^16^^
I25: Is primary | J25: 17 | L25: Values: Y, N | M25: CHR | N25: 1 | R25: =IF(IFERROR(VLOOKUP($H25,'Field Definitions'!$A$1:$S$31597,8),"")=0,"",IFERROR(VLOOKUP($H25,'Field Definitions'!$A$1:$S$31597,8),"")) | S25: =IF(IFERROR(VLOOKUP($H25,'Field Definitions'!$A$1:$S$31597,9),"")=0,"",IFERROR(VLOOKUP($H25,'Field Definitions'!$A$1:$S$31597,9),"")) | T25: =IF(IFERROR(VLOOKUP($H25,'Field Definitions'!$A$1:$S$31597,10),"")=0,"",IFERROR(VLOOKUP($H25,'Field Definitions'!$A$1:$S$31597,10),"")) | U25: =IF(IFERROR(VLOOKUP($H25,'Field Definitions'!$A$1:$S$31597,12),"")=0,"",IFERROR(VLOOKUP($H25,'Field Definitions'!$A$1:$S$31597,12),""))
I26: Source | J26: 18 | L26: Values: CLIENT, CONSUMER, PORTAL, VENDOR | M26: CHR | R26: =IF(IFERROR(VLOOKUP($H26,'Field Definitions'!$A$1:$S$31597,8),"")=0,"",IFERROR(VLOOKUP($H26,'Field Definitions'!$A$1:$S$31597,8),"")) | S26: =IF(IFERROR(VLOOKUP($H26,'Field Definitions'!$A$1:$S$31597,9),"")=0,"",IFERROR(VLOOKUP($H26,'Field Definitions'!$A$1:$S$31597,9),"")) | T26: =IF(IFERROR(VLOOKUP($H26,'Field Definitions'!$A$1:$S$31597,10),"")=0,"",IFERROR(VLOOKUP($H26,'Field Definitions'!$A$1:$S$31597,10),"")) | U26: =IF(IFERROR(VLOOKUP($H26,'Field Definitions'!$A$1:$S$31597,12),"")=0,"",IFERROR(VLOOKUP($H26,'Field Definitions'!$A$1:$S$31597,12),""))
M27: =IFERROR(VLOOKUP($H27,'Field Definitions'!$A$1:$S$31597,4),"") | R27: =IF(IFERROR(VLOOKUP($H27,'Field Definitions'!$A$1:$S$31597,8),"")=0,"",IFERROR(VLOOKUP($H27,'Field Definitions'!$A$1:$S$31597,8),"")) | S27: =IF(IFERROR(VLOOKUP($H27,'Field Definitions'!$A$1:$S$31597,9),"")=0,"",IFERROR(VLOOKUP($H27,'Field Definitions'!$A$1:$S$31597,9),"")) | T27: =IF(IFERROR(VLOOKUP($H27,'Field Definitions'!$A$1:$S$31597,10),"")=0,"",IFERROR(VLOOKUP($H27,'Field Definitions'!$A$1:$S$31597,10),"")) | U27: =IF(IFERROR(VLOOKUP($H27,'Field Definitions'!$A$1:$S$31597,12),"")=0,"",IFERROR(VLOOKUP($H27,'Field Definitions'!$A$1:$S$31597,12),""))
M28: =IFERROR(VLOOKUP($H28,'Field Definitions'!$A$1:$S$31597,4),"") | R28: =IF(IFERROR(VLOOKUP($H28,'Field Definitions'!$A$1:$S$31597,8),"")=0,"",IFERROR(VLOOKUP($H28,'Field Definitions'!$A$1:$S$31597,8),"")) | S28: =IF(IFERROR(VLOOKUP($H28,'Field Definitions'!$A$1:$S$31597,9),"")=0,"",IFERROR(VLOOKUP($H28,'Field Definitions'!$A$1:$S$31597,9),"")) | T28: =IF(IFERROR(VLOOKUP($H28,'Field Definitions'!$A$1:$S$31597,10),"")=0,"",IFERROR(VLOOKUP($H28,'Field Definitions'!$A$1:$S$31597,10),"")) | U28: =IF(IFERROR(VLOOKUP($H28,'Field Definitions'!$A$1:$S$31597,12),"")=0,"",IFERROR(VLOOKUP($H28,'Field Definitions'!$A$1:$S$31597,12),""))
M29: =IFERROR(VLOOKUP($H29,'Field Definitions'!$A$1:$S$31597,4),"") | R29: =IF(IFERROR(VLOOKUP($H29,'Field Definitions'!$A$1:$S$31597,8),"")=0,"",IFERROR(VLOOKUP($H29,'Field Definitions'!$A$1:$S$31597,8),"")) | S29: =IF(IFERROR(VLOOKUP($H29,'Field Definitions'!$A$1:$S$31597,9),"")=0,"",IFERROR(VLOOKUP($H29,'Field Definitions'!$A$1:$S$31597,9),"")) | T29: =IF(IFERROR(VLOOKUP($H29,'Field Definitions'!$A$1:$S$31597,10),"")=0,"",IFERROR(VLOOKUP($H29,'Field Definitions'!$A$1:$S$31597,10),"")) | U29: =IF(IFERROR(VLOOKUP($H29,'Field Definitions'!$A$1:$S$31597,12),"")=0,"",IFERROR(VLOOKUP($H29,'Field Definitions'!$A$1:$S$31597,12),""))
